Workbook

Sheet Vue d'ensemble
A1: Matrice de scoring — Profil du dirigeant & Rayonnement
A2: Version normative V2.1 • Scoring validé • Fiche de diagnostic commercial par prospect • Nom public final : Radar by FeexPay
A5: Architecture retenue
A6: Couche | B6: Sortie | C6: Public / interne | D6: Base | E6: Objectif | F6: Échelle | G6: Décision clé | H6: Statut
A7: Profil du dirigeant | B7: 1 archétype principal + secondaire éventuel | C7: Public | D7: 14 réponses | E7: Créer une restitution ludique | F7: 8 archétypes | G7: +2 dimension principale, +1 secondaire | H7: Validé — norme V2.1
A8: Pilotage FeexPay | B8: Maturité opérationnelle | C8: Interne | D8: 8 indicateurs | E8: Qualifier les besoins réels | F8: 0–100 | G8: Q9D est neutre et exclue du dénominateur | H8: Validé — norme V2.1
A9: Rayonnement | B9: Score, niveau et météo | C9: Public | D9: 6 questions scorées + 1 tag | E9: Mesurer les manifestations visibles | F9: 0–100 / 5 niveaux | G9: Q3 qualifie sans hiérarchiser | H9: Validé — norme V2.1
A10: Lecture croisée | B10: Cohérence causale | C10: Interne + rapport | D10: Pilotage vs rayonnement | E10: Lire la relation fondations → rayonnement | F10: 4 lectures | G10: Seuil de solidité : 60/100 | H10: Validé — norme V2.1
A12: Principes de scoring
A13: 1 | B13: Les formulations validées sont reprises sans modification.
A14: 2 | B14: Le profil public et la qualification FeexPay sont deux calculs distincts.
A15: 3 | B15: Une réponse opérationnellement faible ne retire aucun point à un archétype : elle alimente le score interne de pilotage.
A16: 4 | B16: Être seul à encaisser n’est pas assimilé à un manque d’organisation : Q9D est non applicable au score de délégation.
A17: 5 | B17: Le canal de vente, le déclencheur d’adoption et le besoin prioritaire sont des tags commerciaux, pas des notes de valeur.
A18: 6 | B18: Prix, proximité, qualité et avantage distinctif sont quatre natures de différenciation non hiérarchisées.
A19: 7 | B19: Le Rayonnement est traité comme une conséquence observable de la manière dont l’activité est structurée et pilotée.
A20: 8 | B20: Les seuils et poids sont versionnés afin de préserver l’explicabilité des résultats.
A22: Sources de travail
A23: Questions | B23: 14 questions Dirigeant et 7 questions Rayonnement validées par le client le 18 août 2026.
A24: Profils et règles | B24: TDR_Radar_by_FeexPay_V1_Valide.docx — archétypes, empreintes, départages et niveaux.
A25: Évolution V2.1 | B25: Ajout d’une lecture prospect : faits déclarés, difficultés précises, hypothèses à confirmer et questions de relance — sans recommandation de produit.

Sheet Simulateur
A1: Simulateur de validation du scoring
A2: Modifiez uniquement les cellules jaunes « Choix ». Le scoring reste inchangé et les réponses alimentent automatiquement la Fiche prospect.
A3: Profil principal | B3: =INDEX($G$27:$G$34,MATCH(MAX($H$27:$H$34),$H$27:$H$34,0)) | C3: Affinité | D3: =MAX($H$27:$H$34) | E3: Profil secondaire | F3: =IF(AND(LARGE($H$27:$H$34,2)>=55,LARGE($H$27:$H$34,2)>=MAX($H$27:$H$34)*90%,MAX($H$27:$H$34)-LARGE($H$27:$H$34,2)<=8),INDEX($G$27:$G$34,MATCH(LARGE($H$27:$H$34,2),$H$27:$H$34,0)),"Aucun") | G3: Pilotage interne | H3: =IFERROR(SUM($K$10:$K$23)/SUM($L$10:$L$23)*100,0) | I3: Niveau de pilotage | J3: =IF(H3>=75,"Pilotage structuré",IF(H3>=50,"Pilotage partiellement structuré",IF(H3>=25,"Pilotage réactif","Pilotage informel")))
A5: Rayonnement | B5: =SUM($D$50:$D$54) | C5: Niveau | D5: =IF(B5>=80,"Dominant",IF(B5>=60,"Challenger fort",IF(B5>=40,"Acteur silencieux",IF(B5>=20,"Marque fragile","Zone de disparition")))) | E5: Météo | F5: =IF(B5>=80,"Soleil",IF(B5>=60,"Éclaircies",IF(B5>=40,"Nuageux",IF(B5>=20,"Pluie","Tempête")))) | G5: Nuance météo | H5: =IF(B5>=80,"—",IF(AND(H50-B5<=5,H51>=2,H52>=20),"avec potentiel d’éclaircie","—"))
A6: Lecture croisée | B6: =IF(AND($H$3>=60,$B$5>=60),"Cohérence consolidée",IF(AND($H$3>=60,$B$5<60),"Potentiel sous-exploité",IF(AND($H$3<60,$B$5>=60),"Rayonnement sous tension","Fondations à renforcer"))) | F6: Écart R − P | G6: =B5-H3 | H6: Qualificatif | I6: =IF(ABS(G6)<=15,"Cohérence relative",IF(G6>15,"Le rayonnement dépasse les fondations","Les fondations dépassent le rayonnement"))
A9: N° | B9: Question Dirigeant | C9: Choix | D9: Code | E9: Option sélectionnée | F9: Dim. +2 | G9: Dim. +1 | H9: Pts qual. | I9: Poids | J9: Applicable | K9: Contribution | L9: Poids app. | M9: Tag
A10: 1 | B10: Une nouvelle opportunité se présente. Qu’est-ce qui vous pousse le plus à avancer ? | C10: B | D10: =IF(C10="","","Q"&A10&C10) | E10: =IFERROR(INDEX('Dirigeant - Matrice'!$D$5:$D$60,MATCH(D10,'Dirigeant - Matrice'!$A$5:$A$60,0)),"") | F10: =IFERROR(INDEX('Dirigeant - Matrice'!$E$5:$E$60,MATCH(D10,'Dirigeant - Matrice'!$A$5:$A$60,0)),"") | G10: =IFERROR(INDEX('Dirigeant - Matrice'!$G$5:$G$60,MATCH(D10,'Dirigeant - Matrice'!$A$5:$A$60,0)),"") | H10: =IFERROR(INDEX('Dirigeant - Matrice'!$J$5:$J$60,MATCH(D10,'Dirigeant - Matrice'!$A$5:$A$60,0)),"") | I10: =IFERROR(INDEX('Dirigeant - Matrice'!$K$5:$K$60,MATCH(D10,'Dirigeant - Matrice'!$A$5:$A$60,0)),0) | J10: =IFERROR(INDEX('Dirigeant - Matrice'!$L$5:$L$60,MATCH(D10,'Dirigeant - Matrice'!$A$5:$A$60,0)),0) | K10: =IF(OR(H10="",J10=0),0,H10/3*I10) | L10: =I10*J10 | M10: =IFERROR(INDEX('Dirigeant - Matrice'!$N$5:$N$60,MATCH(D10,'Dirigeant - Matrice'!$A$5:$A$60,0)),"")&IF(IFERROR(INDEX('Dirigeant - Matrice'!$P$5:$P$60,MATCH(D10,'Dirigeant - Matrice'!$A$5:$A$60,0)),"")<>""," | "&IFERROR(INDEX('Dirigeant - Matrice'!$P$5:$P$60,MATCH(D10,'Dirigeant - Matrice'!$A$5:$A$60,0)),""),"")
A11: 2 | B11: Vos ventes augmentent brusquement. Quelle devient votre première priorité ? | C11: C | D11: =IF(C11="","","Q"&A11&C11) | E11: =IFERROR(INDEX('Dirigeant - Matrice'!$D$5:$D$60,MATCH(D11,'Dirigeant - Matrice'!$A$5:$A$60,0)),"") | F11: =IFERROR(INDEX('Dirigeant - Matrice'!$E$5:$E$60,MATCH(D11,'Dirigeant - Matrice'!$A$5:$A$60,0)),"") | G11: =IFERROR(INDEX('Dirigeant - Matrice'!$G$5:$G$60,MATCH(D11,'Dirigeant - Matrice'!$A$5:$A$60,0)),"") | H11: =IFERROR(INDEX('Dirigeant - Matrice'!$J$5:$J$60,MATCH(D11,'Dirigeant - Matrice'!$A$5:$A$60,0)),"") | I11: =IFERROR(INDEX('Dirigeant - Matrice'!$K$5:$K$60,MATCH(D11,'Dirigeant - Matrice'!$A$5:$A$60,0)),0) | J11: =IFERROR(INDEX('Dirigeant - Matrice'!$L$5:$L$60,MATCH(D11,'Dirigeant - Matrice'!$A$5:$A$60,0)),0) | K11: =IF(OR(H11="",J11=0),0,H11/3*I11) | L11: =I11*J11 | M11: =IFERROR(INDEX('Dirigeant - Matrice'!$N$5:$N$60,MATCH(D11,'Dirigeant - Matrice'!$A$5:$A$60,0)),"")&IF(IFERROR(INDEX('Dirigeant - Matrice'!$P$5:$P$60,MATCH(D11,'Dirigeant - Matrice'!$A$5:$A$60,0)),"")<>""," | "&IFERROR(INDEX('Dirigeant - Matrice'!$P$5:$P$60,MATCH(D11,'Dirigeant - Matrice'!$A$5:$A$60,0)),""),"")
A12: 3 | B12: Vous devez prendre une décision sans avoir toutes les informations. Que faites-vous ? | C12: B | D12: =IF(C12="","","Q"&A12&C12) | E12: =IFERROR(INDEX('Dirigeant - Matrice'!$D$5:$D$60,MATCH(D12,'Dirigeant - Matrice'!$A$5:$A$60,0)),"") | F12: =IFERROR(INDEX('Dirigeant - Matrice'!$E$5:$E$60,MATCH(D12,'Dirigeant - Matrice'!$A$5:$A$60,0)),"") | G12: =IFERROR(INDEX('Dirigeant - Matrice'!$G$5:$G$60,MATCH(D12,'Dirigeant - Matrice'!$A$5:$A$60,0)),"") | H12: =IFERROR(INDEX('Dirigeant - Matrice'!$J$5:$J$60,MATCH(D12,'Dirigeant - Matrice'!$A$5:$A$60,0)),"") | I12: =IFERROR(INDEX('Dirigeant - Matrice'!$K$5:$K$60,MATCH(D12,'Dirigeant - Matrice'!$A$5:$A$60,0)),0) | J12: =IFERROR(INDEX('Dirigeant - Matrice'!$L$5:$L$60,MATCH(D12,'Dirigeant - Matrice'!$A$5:$A$60,0)),0) | K12: =IF(OR(H12="",J12=0),0,H12/3*I12) | L12: =I12*J12 | M12: =IFERROR(INDEX('Dirigeant - Matrice'!$N$5:$N$60,MATCH(D12,'Dirigeant - Matrice'!$A$5:$A$60,0)),"")&IF(IFERROR(INDEX('Dirigeant - Matrice'!$P$5:$P$60,MATCH(D12,'Dirigeant - Matrice'!$A$5:$A$60,0)),"")<>""," | "&IFERROR(INDEX('Dirigeant - Matrice'!$P$5:$P$60,MATCH(D12,'Dirigeant - Matrice'!$A$5:$A$60,0)),""),"")
A13: 4 | B13: Comment suivez-vous généralement les ventes réalisées au cours d’une semaine ? | C13: A | D13: =IF(C13="","","Q"&A13&C13) | E13: =IFERROR(INDEX('Dirigeant - Matrice'!$D$5:$D$60,MATCH(D13,'Dirigeant - Matrice'!$A$5:$A$60,0)),"") | F13: =IFERROR(INDEX('Dirigeant - Matrice'!$E$5:$E$60,MATCH(D13,'Dirigeant - Matrice'!$A$5:$A$60,0)),"") | G13: =IFERROR(INDEX('Dirigeant - Matrice'!$G$5:$G$60,MATCH(D13,'Dirigeant - Matrice'!$A$5:$A$60,0)),"") | H13: =IFERROR(INDEX('Dirigeant - Matrice'!$J$5:$J$60,MATCH(D13,'Dirigeant - Matrice'!$A$5:$A$60,0)),"") | I13: =IFERROR(INDEX('Dirigeant - Matrice'!$K$5:$K$60,MATCH(D13,'Dirigeant - Matrice'!$A$5:$A$60,0)),0) | J13: =IFERROR(INDEX('Dirigeant - Matrice'!$L$5:$L$60,MATCH(D13,'Dirigeant - Matrice'!$A$5:$A$60,0)),0) | K13: =IF(OR(H13="",J13=0),0,H13/3*I13) | L13: =I13*J13 | M13: =IFERROR(INDEX('Dirigeant - Matrice'!$N$5:$N$60,MATCH(D13,'Dirigeant - Matrice'!$A$5:$A$60,0)),"")&IF(IFERROR(INDEX('Dirigeant - Matrice'!$P$5:$P$60,MATCH(D13,'Dirigeant - Matrice'!$A$5:$A$60,0)),"")<>""," | "&IFERROR(INDEX('Dirigeant - Matrice'!$P$5:$P$60,MATCH(D13,'Dirigeant - Matrice'!$A$5:$A$60,0)),""),"")
A14: 5 | B14: Le montant encaissé ne correspond pas aux ventes réalisées. Quel est votre premier réflexe ? | C14: D | D14: =IF(C14="","","Q"&A14&C14) | E14: =IFERROR(INDEX('Dirigeant - Matrice'!$D$5:$D$60,MATCH(D14,'Dirigeant - Matrice'!$A$5:$A$60,0)),"") | F14: =IFERROR(INDEX('Dirigeant - Matrice'!$E$5:$E$60,MATCH(D14,'Dirigeant - Matrice'!$A$5:$A$60,0)),"") | G14: =IFERROR(INDEX('Dirigeant - Matrice'!$G$5:$G$60,MATCH(D14,'Dirigeant - Matrice'!$A$5:$A$60,0)),"") | H14: =IFERROR(INDEX('Dirigeant - Matrice'!$J$5:$J$60,MATCH(D14,'Dirigeant - Matrice'!$A$5:$A$60,0)),"") | I14: =IFERROR(INDEX('Dirigeant - Matrice'!$K$5:$K$60,MATCH(D14,'Dirigeant - Matrice'!$A$5:$A$60,0)),0) | J14: =IFERROR(INDEX('Dirigeant - Matrice'!$L$5:$L$60,MATCH(D14,'Dirigeant - Matrice'!$A$5:$A$60,0)),0) | K14: =IF(OR(H14="",J14=0),0,H14/3*I14) | L14: =I14*J14 | M14: =IFERROR(INDEX('Dirigeant - Matrice'!$N$5:$N$60,MATCH(D14,'Dirigeant - Matrice'!$A$5:$A$60,0)),"")&IF(IFERROR(INDEX('Dirigeant - Matrice'!$P$5:$P$60,MATCH(D14,'Dirigeant - Matrice'!$A$5:$A$60,0)),"")<>""," | "&IFERROR(INDEX('Dirigeant - Matrice'!$P$5:$P$60,MATCH(D14,'Dirigeant - Matrice'!$A$5:$A$60,0)),""),"")
A15: 6 | B15: Vos clients utilisent plusieurs moyens de paiement. Comment gardez-vous une vue d’ensemble ? | C15: B | D15: =IF(C15="","","Q"&A15&C15) | E15: =IFERROR(INDEX('Dirigeant - Matrice'!$D$5:$D$60,MATCH(D15,'Dirigeant - Matrice'!$A$5:$A$60,0)),"") | F15: =IFERROR(INDEX('Dirigeant - Matrice'!$E$5:$E$60,MATCH(D15,'Dirigeant - Matrice'!$A$5:$A$60,0)),"") | G15: =IFERROR(INDEX('Dirigeant - Matrice'!$G$5:$G$60,MATCH(D15,'Dirigeant - Matrice'!$A$5:$A$60,0)),"") | H15: =IFERROR(INDEX('Dirigeant - Matrice'!$J$5:$J$60,MATCH(D15,'Dirigeant - Matrice'!$A$5:$A$60,0)),"") | I15: =IFERROR(INDEX('Dirigeant - Matrice'!$K$5:$K$60,MATCH(D15,'Dirigeant - Matrice'!$A$5:$A$60,0)),0) | J15: =IFERROR(INDEX('Dirigeant - Matrice'!$L$5:$L$60,MATCH(D15,'Dirigeant - Matrice'!$A$5:$A$60,0)),0) | K15: =IF(OR(H15="",J15=0),0,H15/3*I15) | L15: =I15*J15 | M15: =IFERROR(INDEX('Dirigeant - Matrice'!$N$5:$N$60,MATCH(D15,'Dirigeant - Matrice'!$A$5:$A$60,0)),"")&IF(IFERROR(INDEX('Dirigeant - Matrice'!$P$5:$P$60,MATCH(D15,'Dirigeant - Matrice'!$A$5:$A$60,0)),"")<>""," | "&IFERROR(INDEX('Dirigeant - Matrice'!$P$5:$P$60,MATCH(D15,'Dirigeant - Matrice'!$A$5:$A$60,0)),""),"")
A16: 7 | B16: À quel moment savez-vous réellement ce que votre entreprise peut dépenser ? | C16: A | D16: =IF(C16="","","Q"&A16&C16) | E16: =IFERROR(INDEX('Dirigeant - Matrice'!$D$5:$D$60,MATCH(D16,'Dirigeant - Matrice'!$A$5:$A$60,0)),"") | F16: =IFERROR(INDEX('Dirigeant - Matrice'!$E$5:$E$60,MATCH(D16,'Dirigeant - Matrice'!$A$5:$A$60,0)),"") | G16: =IFERROR(INDEX('Dirigeant - Matrice'!$G$5:$G$60,MATCH(D16,'Dirigeant - Matrice'!$A$5:$A$60,0)),"") | H16: =IFERROR(INDEX('Dirigeant - Matrice'!$J$5:$J$60,MATCH(D16,'Dirigeant - Matrice'!$A$5:$A$60,0)),"") | I16: =IFERROR(INDEX('Dirigeant - Matrice'!$K$5:$K$60,MATCH(D16,'Dirigeant - Matrice'!$A$5:$A$60,0)),0) | J16: =IFERROR(INDEX('Dirigeant - Matrice'!$L$5:$L$60,MATCH(D16,'Dirigeant - Matrice'!$A$5:$A$60,0)),0) | K16: =IF(OR(H16="",J16=0),0,H16/3*I16) | L16: =I16*J16 | M16: =IFERROR(INDEX('Dirigeant - Matrice'!$N$5:$N$60,MATCH(D16,'Dirigeant - Matrice'!$A$5:$A$60,0)),"")&IF(IFERROR(INDEX('Dirigeant - Matrice'!$P$5:$P$60,MATCH(D16,'Dirigeant - Matrice'!$A$5:$A$60,0)),"")<>""," | "&IFERROR(INDEX('Dirigeant - Matrice'!$P$5:$P$60,MATCH(D16,'Dirigeant - Matrice'!$A$5:$A$60,0)),""),"")
A17: 8 | B17: Lorsque vient le moment de faire la comptabilité, dans quel état se trouvent vos informations ? | C17: D | D17: =IF(C17="","","Q"&A17&C17) | E17: =IFERROR(INDEX('Dirigeant - Matrice'!$D$5:$D$60,MATCH(D17,'Dirigeant - Matrice'!$A$5:$A$60,0)),"") | F17: =IFERROR(INDEX('Dirigeant - Matrice'!$E$5:$E$60,MATCH(D17,'Dirigeant - Matrice'!$A$5:$A$60,0)),"") | G17: =IFERROR(INDEX('Dirigeant - Matrice'!$G$5:$G$60,MATCH(D17,'Dirigeant - Matrice'!$A$5:$A$60,0)),"") | H17: =IFERROR(INDEX('Dirigeant - Matrice'!$J$5:$J$60,MATCH(D17,'Dirigeant - Matrice'!$A$5:$A$60,0)),"") | I17: =IFERROR(INDEX('Dirigeant - Matrice'!$K$5:$K$60,MATCH(D17,'Dirigeant - Matrice'!$A$5:$A$60,0)),0) | J17: =IFERROR(INDEX('Dirigeant - Matrice'!$L$5:$L$60,MATCH(D17,'Dirigeant - Matrice'!$A$5:$A$60,0)),0) | K17: =IF(OR(H17="",J17=0),0,H17/3*I17) | L17: =I17*J17 | M17: =IFERROR(INDEX('Dirigeant - Matrice'!$N$5:$N$60,MATCH(D17,'Dirigeant - Matrice'!$A$5:$A$60,0)),"")&IF(IFERROR(INDEX('Dirigeant - Matrice'!$P$5:$P$60,MATCH(D17,'Dirigeant - Matrice'!$A$5:$A$60,0)),"")<>""," | "&IFERROR(INDEX('Dirigeant - Matrice'!$P$5:$P$60,MATCH(D17,'Dirigeant - Matrice'!$A$5:$A$60,0)),""),"")
A18: 9 | B18: Lorsque d’autres personnes encaissent pour votre entreprise, comment suivez-vous leur activité ? | C18: D | D18: =IF(C18="","","Q"&A18&C18) | E18: =IFERROR(INDEX('Dirigeant - Matrice'!$D$5:$D$60,MATCH(D18,'Dirigeant - Matrice'!$A$5:$A$60,0)),"") | F18: =IFERROR(INDEX('Dirigeant - Matrice'!$E$5:$E$60,MATCH(D18,'Dirigeant - Matrice'!$A$5:$A$60,0)),"") | G18: =IFERROR(INDEX('Dirigeant - Matrice'!$G$5:$G$60,MATCH(D18,'Dirigeant - Matrice'!$A$5:$A$60,0)),"") | H18: =IFERROR(INDEX('Dirigeant - Matrice'!$J$5:$J$60,MATCH(D18,'Dirigeant - Matrice'!$A$5:$A$60,0)),"") | I18: =IFERROR(INDEX('Dirigeant - Matrice'!$K$5:$K$60,MATCH(D18,'Dirigeant - Matrice'!$A$5:$A$60,0)),0) | J18: =IFERROR(INDEX('Dirigeant - Matrice'!$L$5:$L$60,MATCH(D18,'Dirigeant - Matrice'!$A$5:$A$60,0)),0) | K18: =IF(OR(H18="",J18=0),0,H18/3*I18) | L18: =I18*J18 | M18: =IFERROR(INDEX('Dirigeant - Matrice'!$N$5:$N$60,MATCH(D18,'Dirigeant - Matrice'!$A$5:$A$60,0)),"")&IF(IFERROR(INDEX('Dirigeant - Matrice'!$P$5:$P$60,MATCH(D18,'Dirigeant - Matrice'!$A$5:$A$60,0)),"")<>""," | "&IFERROR(INDEX('Dirigeant - Matrice'!$P$5:$P$60,MATCH(D18,'Dirigeant - Matrice'!$A$5:$A$60,0)),""),"")
A19: 10 | B19: Lorsqu’un client souhaite vous payer à distance, comment procédez-vous généralement ? | C19: B | D19: =IF(C19="","","Q"&A19&C19) | E19: =IFERROR(INDEX('Dirigeant - Matrice'!$D$5:$D$60,MATCH(D19,'Dirigeant - Matrice'!$A$5:$A$60,0)),"") | F19: =IFERROR(INDEX('Dirigeant - Matrice'!$E$5:$E$60,MATCH(D19,'Dirigeant - Matrice'!$A$5:$A$60,0)),"") | G19: =IFERROR(INDEX('Dirigeant - Matrice'!$G$5:$G$60,MATCH(D19,'Dirigeant - Matrice'!$A$5:$A$60,0)),"") | H19: =IFERROR(INDEX('Dirigeant - Matrice'!$J$5:$J$60,MATCH(D19,'Dirigeant - Matrice'!$A$5:$A$60,0)),"") | I19: =IFERROR(INDEX('Dirigeant - Matrice'!$K$5:$K$60,MATCH(D19,'Dirigeant - Matrice'!$A$5:$A$60,0)),0) | J19: =IFERROR(INDEX('Dirigeant - Matrice'!$L$5:$L$60,MATCH(D19,'Dirigeant - Matrice'!$A$5:$A$60,0)),0) | K19: =IF(OR(H19="",J19=0),0,H19/3*I19) | L19: =I19*J19 | M19: =IFERROR(INDEX('Dirigeant - Matrice'!$N$5:$N$60,MATCH(D19,'Dirigeant - Matrice'!$A$5:$A$60,0)),"")&IF(IFERROR(INDEX('Dirigeant - Matrice'!$P$5:$P$60,MATCH(D19,'Dirigeant - Matrice'!$A$5:$A$60,0)),"")<>""," | "&IFERROR(INDEX('Dirigeant - Matrice'!$P$5:$P$60,MATCH(D19,'Dirigeant - Matrice'!$A$5:$A$60,0)),""),"")
A20: 11 | B20: Quelle place le digital occupe-t-il actuellement dans vos ventes ? | C20: C | D20: =IF(C20="","","Q"&A20&C20) | E20: =IFERROR(INDEX('Dirigeant - Matrice'!$D$5:$D$60,MATCH(D20,'Dirigeant - Matrice'!$A$5:$A$60,0)),"") | F20: =IFERROR(INDEX('Dirigeant - Matrice'!$E$5:$E$60,MATCH(D20,'Dirigeant - Matrice'!$A$5:$A$60,0)),"") | G20: =IFERROR(INDEX('Dirigeant - Matrice'!$G$5:$G$60,MATCH(D20,'Dirigeant - Matrice'!$A$5:$A$60,0)),"") | H20: =IFERROR(INDEX('Dirigeant - Matrice'!$J$5:$J$60,MATCH(D20,'Dirigeant - Matrice'!$A$5:$A$60,0)),"") | I20: =IFERROR(INDEX('Dirigeant - Matrice'!$K$5:$K$60,MATCH(D20,'Dirigeant - Matrice'!$A$5:$A$60,0)),0) | J20: =IFERROR(INDEX('Dirigeant - Matrice'!$L$5:$L$60,MATCH(D20,'Dirigeant - Matrice'!$A$5:$A$60,0)),0) | K20: =IF(OR(H20="",J20=0),0,H20/3*I20) | L20: =I20*J20 | M20: =IFERROR(INDEX('Dirigeant - Matrice'!$N$5:$N$60,MATCH(D20,'Dirigeant - Matrice'!$A$5:$A$60,0)),"")&IF(IFERROR(INDEX('Dirigeant - Matrice'!$P$5:$P$60,MATCH(D20,'Dirigeant - Matrice'!$A$5:$A$60,0)),"")<>""," | "&IFERROR(INDEX('Dirigeant - Matrice'!$P$5:$P$60,MATCH(D20,'Dirigeant - Matrice'!$A$5:$A$60,0)),""),"")
A21: 12 | B21: Un client affirme avoir payé, mais vous ne retrouvez pas immédiatement son paiement. Que faites-vous ? | C21: A | D21: =IF(C21="","","Q"&A21&C21) | E21: =IFERROR(INDEX('Dirigeant - Matrice'!$D$5:$D$60,MATCH(D21,'Dirigeant - Matrice'!$A$5:$A$60,0)),"") | F21: =IFERROR(INDEX('Dirigeant - Matrice'!$E$5:$E$60,MATCH(D21,'Dirigeant - Matrice'!$A$5:$A$60,0)),"") | G21: =IFERROR(INDEX('Dirigeant - Matrice'!$G$5:$G$60,MATCH(D21,'Dirigeant - Matrice'!$A$5:$A$60,0)),"") | H21: =IFERROR(INDEX('Dirigeant - Matrice'!$J$5:$J$60,MATCH(D21,'Dirigeant - Matrice'!$A$5:$A$60,0)),"") | I21: =IFERROR(INDEX('Dirigeant - Matrice'!$K$5:$K$60,MATCH(D21,'Dirigeant - Matrice'!$A$5:$A$60,0)),0) | J21: =IFERROR(INDEX('Dirigeant - Matrice'!$L$5:$L$60,MATCH(D21,'Dirigeant - Matrice'!$A$5:$A$60,0)),0) | K21: =IF(OR(H21="",J21=0),0,H21/3*I21) | L21: =I21*J21 | M21: =IFERROR(INDEX('Dirigeant - Matrice'!$N$5:$N$60,MATCH(D21,'Dirigeant - Matrice'!$A$5:$A$60,0)),"")&IF(IFERROR(INDEX('Dirigeant - Matrice'!$P$5:$P$60,MATCH(D21,'Dirigeant - Matrice'!$A$5:$A$60,0)),"")<>""," | "&IFERROR(INDEX('Dirigeant - Matrice'!$P$5:$P$60,MATCH(D21,'Dirigeant - Matrice'!$A$5:$A$60,0)),""),"")
... A23: 14 | B23: Dans un an, quel progrès vous donnerait le plus le sentiment de mieux piloter votre entreprise ? | C23: A | D23: =IF(C23="","","Q"&A23&C23) | E23: =IFERROR(INDEX('Dirigeant - Matrice'!$D$5:$D$60,MATCH(D23,'Dirigeant - Matrice'!$A$5:$A$60,0)),"") | F23: =IFERROR(INDEX('Dirigeant - Matrice'!$E$5:$E$60,MATCH(D23,'Dirigeant - Matrice'!$A$5:$A$60,0)),"") | G23: =IFERROR(INDEX('Dirigeant - Matrice'!$G$5:$G$60,MATCH(D23,'Dirigeant - Matrice'!$A$5:$A$60,0)),"") | H23: =IFERROR(INDEX('Dirigeant - Matrice'!$J$5:$J$60,MATCH(D23,'Dirigeant - Matrice'!$A$5:$A$60,0)),"") | I23: =IFERROR(INDEX('Dirigeant - Matrice'!$K$5:$K$60,MATCH(D23,'Dirigeant - Matrice'!$A$5:$A$60,0)),0) | J23: =IFERROR(INDEX('Dirigeant - Matrice'!$L$5:$L$60,MATCH(D23,'Dirigeant - Matrice'!$A$5:$A$60,0)),0) | K23: =IF(OR(H23="",J23=0),0,H23/3*I23) | L23: =I23*J23 | M23: =IFERROR(INDEX('Dirigeant - Matrice'!$N$5:$N$60,MATCH(D23,'Dirigeant - Matrice'!$A$5:$A$60,0)),"")&IF(IFERROR(INDEX('Dirigeant - Matrice'!$P$5:$P$60,MATCH(D23,'Dirigeant - Matrice'!$A$5:$A$60,0)),"")<>""," | "&IFERROR(INDEX('Dirigeant - Matrice'!$P$5:$P$60,MATCH(D23,'Dirigeant - Matrice'!$A$5:$A$60,0)),""),"")
A25: Scores des dimensions | G25: Affinités des archétypes
A26: Dimension | B26: Code | C26: Score brut | D26: Maximum | E26: Score normalisé | G26: Archétype | H26: Affinité | I26: Dimension centrale
A27: Vision | B27: VIS | C27: =COUNTIF($F$10:$F$23,B27)*2+COUNTIF($G$10:$G$23,B27) | D27: =INDEX('Contrôles'!$E$5:$E$12,MATCH(B27,'Contrôles'!$B$5:$B$12,0)) | E27: =IFERROR(C27/D27*100,0) | G27: Stratège | H27: =$E$28*50%+$E$33*30%+$E$30*20% | I27: STR
A28: Stratégie | B28: STR | C28: =COUNTIF($F$10:$F$23,B28)*2+COUNTIF($G$10:$G$23,B28) | D28: =INDEX('Contrôles'!$E$5:$E$12,MATCH(B28,'Contrôles'!$B$5:$B$12,0)) | E28: =IFERROR(C28/D28*100,0) | G28: Visionnaire | H28: =$E$27*50%+$E$31*30%+$E$34*20% | I28: VIS
A29: Exécution | B29: EXE | C29: =COUNTIF($F$10:$F$23,B29)*2+COUNTIF($G$10:$G$23,B29) | D29: =INDEX('Contrôles'!$E$5:$E$12,MATCH(B29,'Contrôles'!$B$5:$B$12,0)) | E29: =IFERROR(C29/D29*100,0) | G29: Bâtisseur | H29: =$E$29*50%+$E$30*35%+$E$28*15% | I29: EXE
A30: Organisation | B30: ORG | C30: =COUNTIF($F$10:$F$23,B30)*2+COUNTIF($G$10:$G$23,B30) | D30: =INDEX('Contrôles'!$E$5:$E$12,MATCH(B30,'Contrôles'!$B$5:$B$12,0)) | E30: =IFERROR(C30/D30*100,0) | G30: Conquérant | H30: =$E$32*50%+$E$29*35%+$E$27*15% | I30: AUD
A31: Influence | B31: INF | C31: =COUNTIF($F$10:$F$23,B31)*2+COUNTIF($G$10:$G$23,B31) | D31: =INDEX('Contrôles'!$E$5:$E$12,MATCH(B31,'Contrôles'!$B$5:$B$12,0)) | E31: =IFERROR(C31/D31*100,0) | G31: Fédérateur | H31: =$E$31*50%+$E$33*30%+$E$27*20% | I31: INF
A32: Audace | B32: AUD | C32: =COUNTIF($F$10:$F$23,B32)*2+COUNTIF($G$10:$G$23,B32) | D32: =INDEX('Contrôles'!$E$5:$E$12,MATCH(B32,'Contrôles'!$B$5:$B$12,0)) | E32: =IFERROR(C32/D32*100,0) | G32: Résilient | H32: =$E$33*50%+$E$29*30%+$E$32*20% | I32: ADA
A33: Adaptabilité | B33: ADA | C33: =COUNTIF($F$10:$F$23,B33)*2+COUNTIF($G$10:$G$23,B33) | D33: =INDEX('Contrôles'!$E$5:$E$12,MATCH(B33,'Contrôles'!$B$5:$B$12,0)) | E33: =IFERROR(C33/D33*100,0) | G33: Gestionnaire | H33: =$E$30*45%+$E$28*30%+$E$29*25% | I33: ORG
A34: Transformation | B34: TRA | C34: =COUNTIF($F$10:$F$23,B34)*2+COUNTIF($G$10:$G$23,B34) | D34: =INDEX('Contrôles'!$E$5:$E$12,MATCH(B34,'Contrôles'!$B$5:$B$12,0)) | E34: =IFERROR(C34/D34*100,0) | G34: Réformateur | H34: =$E$34*50%+$E$32*30%+$E$27*20% | I34: TRA
A39: N° | B39: Question Rayonnement | C39: Choix | D39: Code | E39: Option sélectionnée | F39: Points | G39: Dimension | H39: Tag | I39: Valeur | J39: Règle
A40: 1 | B40: En dehors de vos clients actuels, jusqu’où votre entreprise est-elle connue ? | C40: C | D40: =IF(C40="","","R"&A40&C40) | E40: =IFERROR(INDEX('Rayonnement - Matrice'!$D$5:$D$32,MATCH(D40,'Rayonnement - Matrice'!$A$5:$A$32,0)),"") | F40: =IFERROR(INDEX('Rayonnement - Matrice'!$F$5:$F$32,MATCH(D40,'Rayonnement - Matrice'!$A$5:$A$32,0)),"") | G40: =IFERROR(INDEX('Rayonnement - Matrice'!$E$5:$E$32,MATCH(D40,'Rayonnement - Matrice'!$A$5:$A$32,0)),"") | H40: =IFERROR(INDEX('Rayonnement - Matrice'!$H$5:$H$32,MATCH(D40,'Rayonnement - Matrice'!$A$5:$A$32,0)),"") | I40: =IFERROR(INDEX('Rayonnement - Matrice'!$I$5:$I$32,MATCH(D40,'Rayonnement - Matrice'!$A$5:$A$32,0)),"") | J40: =IFERROR(INDEX('Rayonnement - Matrice'!$J$5:$J$32,MATCH(D40,'Rayonnement - Matrice'!$A$5:$A$32,0)),"")
A41: 2 | B41: Lorsqu’un prospect choisit un concurrent, savez-vous généralement pourquoi ? | C41: C | D41: =IF(C41="","","R"&A41&C41) | E41: =IFERROR(INDEX('Rayonnement - Matrice'!$D$5:$D$32,MATCH(D41,'Rayonnement - Matrice'!$A$5:$A$32,0)),"") | F41: =IFERROR(INDEX('Rayonnement - Matrice'!$F$5:$F$32,MATCH(D41,'Rayonnement - Matrice'!$A$5:$A$32,0)),"") | G41: =IFERROR(INDEX('Rayonnement - Matrice'!$E$5:$E$32,MATCH(D41,'Rayonnement - Matrice'!$A$5:$A$32,0)),"") | H41: =IFERROR(INDEX('Rayonnement - Matrice'!$H$5:$H$32,MATCH(D41,'Rayonnement - Matrice'!$A$5:$A$32,0)),"") | I41: =IFERROR(INDEX('Rayonnement - Matrice'!$I$5:$I$32,MATCH(D41,'Rayonnement - Matrice'!$A$5:$A$32,0)),"") | J41: =IFERROR(INDEX('Rayonnement - Matrice'!$J$5:$J$32,MATCH(D41,'Rayonnement - Matrice'!$A$5:$A$32,0)),"")
A42: 3 | B42: Pour quelle raison vos clients vous choisissent-ils principalement ? | C42: C | D42: =IF(C42="","","R"&A42&C42) | E42: =IFERROR(INDEX('Rayonnement - Matrice'!$D$5:$D$32,MATCH(D42,'Rayonnement - Matrice'!$A$5:$A$32,0)),"") | F42: =IFERROR(INDEX('Rayonnement - Matrice'!$F$5:$F$32,MATCH(D42,'Rayonnement - Matrice'!$A$5:$A$32,0)),"") | G42: =IFERROR(INDEX('Rayonnement - Matrice'!$E$5:$E$32,MATCH(D42,'Rayonnement - Matrice'!$A$5:$A$32,0)),"") | H42: =IFERROR(INDEX('Rayonnement - Matrice'!$H$5:$H$32,MATCH(D42,'Rayonnement - Matrice'!$A$5:$A$32,0)),"") | I42: =IFERROR(INDEX('Rayonnement - Matrice'!$I$5:$I$32,MATCH(D42,'Rayonnement - Matrice'!$A$5:$A$32,0)),"") | J42: =IFERROR(INDEX('Rayonnement - Matrice'!$J$5:$J$32,MATCH(D42,'Rayonnement - Matrice'!$A$5:$A$32,0)),"")
A43: 4 | B43: Une personne qui découvre votre entreprise comprend-elle facilement ce qui vous distingue ? | C43: C | D43: =IF(C43="","","R"&A43&C43) | E43: =IFERROR(INDEX('Rayonnement - Matrice'!$D$5:$D$32,MATCH(D43,'Rayonnement - Matrice'!$A$5:$A$32,0)),"") | F43: =IFERROR(INDEX('Rayonnement - Matrice'!$F$5:$F$32,MATCH(D43,'Rayonnement - Matrice'!$A$5:$A$32,0)),"") | G43: =IFERROR(INDEX('Rayonnement - Matrice'!$E$5:$E$32,MATCH(D43,'Rayonnement - Matrice'!$A$5:$A$32,0)),"") | H43: =IFERROR(INDEX('Rayonnement - Matrice'!$H$5:$H$32,MATCH(D43,'Rayonnement - Matrice'!$A$5:$A$32,0)),"") | I43: =IFERROR(INDEX('Rayonnement - Matrice'!$I$5:$I$32,MATCH(D43,'Rayonnement - Matrice'!$A$5:$A$32,0)),"") | J43: =IFERROR(INDEX('Rayonnement - Matrice'!$J$5:$J$32,MATCH(D43,'Rayonnement - Matrice'!$A$5:$A$32,0)),"")
A44: 5 | B44: Comment votre entreprise est-elle actuellement présente sur les canaux numériques ? | C44: C | D44: =IF(C44="","","R"&A44&C44) | E44: =IFERROR(INDEX('Rayonnement - Matrice'!$D$5:$D$32,MATCH(D44,'Rayonnement - Matrice'!$A$5:$A$32,0)),"") | F44: =IFERROR(INDEX('Rayonnement - Matrice'!$F$5:$F$32,MATCH(D44,'Rayonnement - Matrice'!$A$5:$A$32,0)),"") | G44: =IFERROR(INDEX('Rayonnement - Matrice'!$E$5:$E$32,MATCH(D44,'Rayonnement - Matrice'!$A$5:$A$32,0)),"") | H44: =IFERROR(INDEX('Rayonnement - Matrice'!$H$5:$H$32,MATCH(D44,'Rayonnement - Matrice'!$A$5:$A$32,0)),"") | I44: =IFERROR(INDEX('Rayonnement - Matrice'!$I$5:$I$32,MATCH(D44,'Rayonnement - Matrice'!$A$5:$A$32,0)),"") | J44: =IFERROR(INDEX('Rayonnement - Matrice'!$J$5:$J$32,MATCH(D44,'Rayonnement - Matrice'!$A$5:$A$32,0)),"")
A45: 6 | B45: Que produit concrètement votre présence numérique pour votre entreprise ? | C45: C | D45: =IF(C45="","","R"&A45&C45) | E45: =IFERROR(INDEX('Rayonnement - Matrice'!$D$5:$D$32,MATCH(D45,'Rayonnement - Matrice'!$A$5:$A$32,0)),"") | F45: =IFERROR(INDEX('Rayonnement - Matrice'!$F$5:$F$32,MATCH(D45,'Rayonnement - Matrice'!$A$5:$A$32,0)),"") | G45: =IFERROR(INDEX('Rayonnement - Matrice'!$E$5:$E$32,MATCH(D45,'Rayonnement - Matrice'!$A$5:$A$32,0)),"") | H45: =IFERROR(INDEX('Rayonnement - Matrice'!$H$5:$H$32,MATCH(D45,'Rayonnement - Matrice'!$A$5:$A$32,0)),"") | I45: =IFERROR(INDEX('Rayonnement - Matrice'!$I$5:$I$32,MATCH(D45,'Rayonnement - Matrice'!$A$5:$A$32,0)),"") | J45: =IFERROR(INDEX('Rayonnement - Matrice'!$J$5:$J$32,MATCH(D45,'Rayonnement - Matrice'!$A$5:$A$32,0)),"")
A46: 7 | B46: Si votre entreprise arrêtait ses activités demain, qui le remarquerait rapidement ? | C46: C | D46: =IF(C46="","","R"&A46&C46) | E46: =IFERROR(INDEX('Rayonnement - Matrice'!$D$5:$D$32,MATCH(D46,'Rayonnement - Matrice'!$A$5:$A$32,0)),"") | F46: =IFERROR(INDEX('Rayonnement - Matrice'!$F$5:$F$32,MATCH(D46,'Rayonnement - Matrice'!$A$5:$A$32,0)),"") | G46: =IFERROR(INDEX('Rayonnement - Matrice'!$E$5:$E$32,MATCH(D46,'Rayonnement - Matrice'!$A$5:$A$32,0)),"") | H46: =IFERROR(INDEX('Rayonnement - Matrice'!$H$5:$H$32,MATCH(D46,'Rayonnement - Matrice'!$A$5:$A$32,0)),"") | I46: =IFERROR(INDEX('Rayonnement - Matrice'!$I$5:$I$32,MATCH(D46,'Rayonnement - Matrice'!$A$5:$A$32,0)),"") | J46: =IFERROR(INDEX('Rayonnement - Matrice'!$J$5:$J$32,MATCH(D46,'Rayonnement - Matrice'!$A$5:$A$32,0)),"")
A48: Calcul du Rayonnement
A49: Dimension | B49: Score | C49: Poids global | D49: Contribution | E49: Source | G49: Aide technique | H49: Valeur
A50: Notoriété | B50: =F40/3*100 | C50: 0.2 | D50: =B50*C50 | E50: R1 | G50: Seuil suivant | H50: =IF($B$5>=80,100,IF($B$5>=60,80,IF($B$5>=40,60,IF($B$5>=20,40,20))))
A51: Lecture concurrentielle | B51: =F41/3*100 | C51: 0.15 | D51: =B51*C51 | E51: R2 | G51: Dimensions au seuil | H51: =COUNTIF($B$50:$B$54,">="&H50)
A52: Différenciation | B52: =F43/3*100 | C52: 0.25 | D52: =B52*C52 | E52: R4 | G52: Dimension minimale | H52: =MIN($B$50:$B$54)
A53: Digital | B53: =F44/3*100*60%+F45/3*100*40% | C53: 0.2 | D53: =B53*C53 | E53: R5 × 60 % + R6 × 40 %
A54: Empreinte | B54: =F46/3*100 | C54: 0.2 | D54: =B54*C54 | E54: R7

Sheet Fiche prospect
A1: Fiche de diagnostic commercial du prospect
A2: Lecture générée à partir des réponses déclarées. Elle prépare l’échange commercial : elle décrit des difficultés concrètes et des pistes à vérifier, sans recommander de produit.
M4: Code | N4: Parcours | O4: Dimension | P4: Nature | Q4: Gravité | R4: Niveau | S4: Constat | T4: Difficulté | U4: Hypothèse | V4: Relance | W4: Réponse | X4: Rang difficulté | Y4: Rang force
A5: Profil | B5: ='Simulateur'!B3 | C5: Pilotage | D5: ='Simulateur'!H3 | E5: Niveau de pilotage | F5: ='Simulateur'!J3 | M5: ='Simulateur'!D10 | N5: =IFERROR(INDEX('Bibliothèque constats'!$B$5:$B$88,MATCH($M5,'Bibliothèque constats'!$A$5:$A$88,0)),"") | O5: =IFERROR(INDEX('Bibliothèque constats'!$F$5:$F$88,MATCH($M5,'Bibliothèque constats'!$A$5:$A$88,0)),"") | P5: =IFERROR(INDEX('Bibliothèque constats'!$G$5:$G$88,MATCH($M5,'Bibliothèque constats'!$A$5:$A$88,0)),"") | Q5: =IFERROR(INDEX('Bibliothèque constats'!$H$5:$H$88,MATCH($M5,'Bibliothèque constats'!$A$5:$A$88,0)),"") | R5: =IFERROR(INDEX('Bibliothèque constats'!$I$5:$I$88,MATCH($M5,'Bibliothèque constats'!$A$5:$A$88,0)),"") | S5: =IFERROR(INDEX('Bibliothèque constats'!$J$5:$J$88,MATCH($M5,'Bibliothèque constats'!$A$5:$A$88,0)),"") | T5: =IFERROR(INDEX('Bibliothèque constats'!$K$5:$K$88,MATCH($M5,'Bibliothèque constats'!$A$5:$A$88,0)),"") | U5: =IFERROR(INDEX('Bibliothèque constats'!$L$5:$L$88,MATCH($M5,'Bibliothèque constats'!$A$5:$A$88,0)),"") | V5: =IFERROR(INDEX('Bibliothèque constats'!$M$5:$M$88,MATCH($M5,'Bibliothèque constats'!$A$5:$A$88,0)),"") | W5: =IFERROR(INDEX('Bibliothèque constats'!$E$5:$E$88,MATCH($M5,'Bibliothèque constats'!$A$5:$A$88,0)),"") | X5: =IF(AND(Q5>0,T5<>""),Q5*1000-ROW(),0) | Y5: =IF(P5="Force",1000-ROW(),0)
A6: Rayonnement | B6: ='Simulateur'!B5 | C6: Niveau de rayonnement | D6: ='Simulateur'!D5 | E6: Lecture croisée | F6: ='Simulateur'!B6 | M6: ='Simulateur'!D11 | N6: =IFERROR(INDEX('Bibliothèque constats'!$B$5:$B$88,MATCH($M6,'Bibliothèque constats'!$A$5:$A$88,0)),"") | O6: =IFERROR(INDEX('Bibliothèque constats'!$F$5:$F$88,MATCH($M6,'Bibliothèque constats'!$A$5:$A$88,0)),"") | P6: =IFERROR(INDEX('Bibliothèque constats'!$G$5:$G$88,MATCH($M6,'Bibliothèque constats'!$A$5:$A$88,0)),"") | Q6: =IFERROR(INDEX('Bibliothèque constats'!$H$5:$H$88,MATCH($M6,'Bibliothèque constats'!$A$5:$A$88,0)),"") | R6: =IFERROR(INDEX('Bibliothèque constats'!$I$5:$I$88,MATCH($M6,'Bibliothèque constats'!$A$5:$A$88,0)),"") | S6: =IFERROR(INDEX('Bibliothèque constats'!$J$5:$J$88,MATCH($M6,'Bibliothèque constats'!$A$5:$A$88,0)),"") | T6: =IFERROR(INDEX('Bibliothèque constats'!$K$5:$K$88,MATCH($M6,'Bibliothèque constats'!$A$5:$A$88,0)),"") | U6: =IFERROR(INDEX('Bibliothèque constats'!$L$5:$L$88,MATCH($M6,'Bibliothèque constats'!$A$5:$A$88,0)),"") | V6: =IFERROR(INDEX('Bibliothèque constats'!$M$5:$M$88,MATCH($M6,'Bibliothèque constats'!$A$5:$A$88,0)),"") | W6: =IFERROR(INDEX('Bibliothèque constats'!$E$5:$E$88,MATCH($M6,'Bibliothèque constats'!$A$5:$A$88,0)),"") | X6: =IF(AND(Q6>0,T6<>""),Q6*1000-ROW(),0) | Y6: =IF(P6="Force",1000-ROW(),0)
M7: ='Simulateur'!D12 | N7: =IFERROR(INDEX('Bibliothèque constats'!$B$5:$B$88,MATCH($M7,'Bibliothèque constats'!$A$5:$A$88,0)),"") | O7: =IFERROR(INDEX('Bibliothèque constats'!$F$5:$F$88,MATCH($M7,'Bibliothèque constats'!$A$5:$A$88,0)),"") | P7: =IFERROR(INDEX('Bibliothèque constats'!$G$5:$G$88,MATCH($M7,'Bibliothèque constats'!$A$5:$A$88,0)),"") | Q7: =IFERROR(INDEX('Bibliothèque constats'!$H$5:$H$88,MATCH($M7,'Bibliothèque constats'!$A$5:$A$88,0)),"") | R7: =IFERROR(INDEX('Bibliothèque constats'!$I$5:$I$88,MATCH($M7,'Bibliothèque constats'!$A$5:$A$88,0)),"") | S7: =IFERROR(INDEX('Bibliothèque constats'!$J$5:$J$88,MATCH($M7,'Bibliothèque constats'!$A$5:$A$88,0)),"") | T7: =IFERROR(INDEX('Bibliothèque constats'!$K$5:$K$88,MATCH($M7,'Bibliothèque constats'!$A$5:$A$88,0)),"") | U7: =IFERROR(INDEX('Bibliothèque constats'!$L$5:$L$88,MATCH($M7,'Bibliothèque constats'!$A$5:$A$88,0)),"") | V7: =IFERROR(INDEX('Bibliothèque constats'!$M$5:$M$88,MATCH($M7,'Bibliothèque constats'!$A$5:$A$88,0)),"") | W7: =IFERROR(INDEX('Bibliothèque constats'!$E$5:$E$88,MATCH($M7,'Bibliothèque constats'!$A$5:$A$88,0)),"") | X7: =IF(AND(Q7>0,T7<>""),Q7*1000-ROW(),0) | Y7: =IF(P7="Force",1000-ROW(),0)
A8: Difficultés prioritaires détectées | M8: ='Simulateur'!D13 | N8: =IFERROR(INDEX('Bibliothèque constats'!$B$5:$B$88,MATCH($M8,'Bibliothèque constats'!$A$5:$A$88,0)),"") | O8: =IFERROR(INDEX('Bibliothèque constats'!$F$5:$F$88,MATCH($M8,'Bibliothèque constats'!$A$5:$A$88,0)),"") | P8: =IFERROR(INDEX('Bibliothèque constats'!$G$5:$G$88,MATCH($M8,'Bibliothèque constats'!$A$5:$A$88,0)),"") | Q8: =IFERROR(INDEX('Bibliothèque constats'!$H$5:$H$88,MATCH($M8,'Bibliothèque constats'!$A$5:$A$88,0)),"") | R8: =IFERROR(INDEX('Bibliothèque constats'!$I$5:$I$88,MATCH($M8,'Bibliothèque constats'!$A$5:$A$88,0)),"") | S8: =IFERROR(INDEX('Bibliothèque constats'!$J$5:$J$88,MATCH($M8,'Bibliothèque constats'!$A$5:$A$88,0)),"") | T8: =IFERROR(INDEX('Bibliothèque constats'!$K$5:$K$88,MATCH($M8,'Bibliothèque constats'!$A$5:$A$88,0)),"") | U8: =IFERROR(INDEX('Bibliothèque constats'!$L$5:$L$88,MATCH($M8,'Bibliothèque constats'!$A$5:$A$88,0)),"") | V8: =IFERROR(INDEX('Bibliothèque constats'!$M$5:$M$88,MATCH($M8,'Bibliothèque constats'!$A$5:$A$88,0)),"") | W8: =IFERROR(INDEX('Bibliothèque constats'!$E$5:$E$88,MATCH($M8,'Bibliothèque constats'!$A$5:$A$88,0)),"") | X8: =IF(AND(Q8>0,T8<>""),Q8*1000-ROW(),0) | Y8: =IF(P8="Force",1000-ROW(),0)
A9: # | B9: Difficulté précise | C9: Gravité | D9: Constat factuel | E9: Réponse sélectionnée | F9: Question de relance | M9: ='Simulateur'!D14 | N9: =IFERROR(INDEX('Bibliothèque constats'!$B$5:$B$88,MATCH($M9,'Bibliothèque constats'!$A$5:$A$88,0)),"") | O9: =IFERROR(INDEX('Bibliothèque constats'!$F$5:$F$88,MATCH($M9,'Bibliothèque constats'!$A$5:$A$88,0)),"") | P9: =IFERROR(INDEX('Bibliothèque constats'!$G$5:$G$88,MATCH($M9,'Bibliothèque constats'!$A$5:$A$88,0)),"") | Q9: =IFERROR(INDEX('Bibliothèque constats'!$H$5:$H$88,MATCH($M9,'Bibliothèque constats'!$A$5:$A$88,0)),"") | R9: =IFERROR(INDEX('Bibliothèque constats'!$I$5:$I$88,MATCH($M9,'Bibliothèque constats'!$A$5:$A$88,0)),"") | S9: =IFERROR(INDEX('Bibliothèque constats'!$J$5:$J$88,MATCH($M9,'Bibliothèque constats'!$A$5:$A$88,0)),"") | T9: =IFERROR(INDEX('Bibliothèque constats'!$K$5:$K$88,MATCH($M9,'Bibliothèque constats'!$A$5:$A$88,0)),"") | U9: =IFERROR(INDEX('Bibliothèque constats'!$L$5:$L$88,MATCH($M9,'Bibliothèque constats'!$A$5:$A$88,0)),"") | V9: =IFERROR(INDEX('Bibliothèque constats'!$M$5:$M$88,MATCH($M9,'Bibliothèque constats'!$A$5:$A$88,0)),"") | W9: =IFERROR(INDEX('Bibliothèque constats'!$E$5:$E$88,MATCH($M9,'Bibliothèque constats'!$A$5:$A$88,0)),"") | X9: =IF(AND(Q9>0,T9<>""),Q9*1000-ROW(),0) | Y9: =IF(P9="Force",1000-ROW(),0)
A10: =IF(LARGE($X$5:$X$25,1)<=0,"",1) | B10: =IFERROR(IF(LARGE($X$5:$X$25,1)<=0,"",INDEX($T$5:$T$25,MATCH(LARGE($X$5:$X$25,1),$X$5:$X$25,0))),"") | C10: =IFERROR(IF(LARGE($X$5:$X$25,1)<=0,"",INDEX($R$5:$R$25,MATCH(LARGE($X$5:$X$25,1),$X$5:$X$25,0))),"") | D10: =IFERROR(IF(LARGE($X$5:$X$25,1)<=0,"",INDEX($S$5:$S$25,MATCH(LARGE($X$5:$X$25,1),$X$5:$X$25,0))),"") | E10: =IFERROR(IF(LARGE($X$5:$X$25,1)<=0,"",INDEX($W$5:$W$25,MATCH(LARGE($X$5:$X$25,1),$X$5:$X$25,0))),"") | F10: =IFERROR(IF(LARGE($X$5:$X$25,1)<=0,"",INDEX($V$5:$V$25,MATCH(LARGE($X$5:$X$25,1),$X$5:$X$25,0))),"") | M10: ='Simulateur'!D15 | N10: =IFERROR(INDEX('Bibliothèque constats'!$B$5:$B$88,MATCH($M10,'Bibliothèque constats'!$A$5:$A$88,0)),"") | O10: =IFERROR(INDEX('Bibliothèque constats'!$F$5:$F$88,MATCH($M10,'Bibliothèque constats'!$A$5:$A$88,0)),"") | P10: =IFERROR(INDEX('Bibliothèque constats'!$G$5:$G$88,MATCH($M10,'Bibliothèque constats'!$A$5:$A$88,0)),"") | Q10: =IFERROR(INDEX('Bibliothèque constats'!$H$5:$H$88,MATCH($M10,'Bibliothèque constats'!$A$5:$A$88,0)),"") | R10: =IFERROR(INDEX('Bibliothèque constats'!$I$5:$I$88,MATCH($M10,'Bibliothèque constats'!$A$5:$A$88,0)),"") | S10: =IFERROR(INDEX('Bibliothèque constats'!$J$5:$J$88,MATCH($M10,'Bibliothèque constats'!$A$5:$A$88,0)),"") | T10: =IFERROR(INDEX('Bibliothèque constats'!$K$5:$K$88,MATCH($M10,'Bibliothèque constats'!$A$5:$A$88,0)),"") | U10: =IFERROR(INDEX('Bibliothèque constats'!$L$5:$L$88,MATCH($M10,'Bibliothèque constats'!$A$5:$A$88,0)),"") | V10: =IFERROR(INDEX('Bibliothèque constats'!$M$5:$M$88,MATCH($M10,'Bibliothèque constats'!$A$5:$A$88,0)),"") | W10: =IFERROR(INDEX('Bibliothèque constats'!$E$5:$E$88,MATCH($M10,'Bibliothèque constats'!$A$5:$A$88,0)),"") | X10: =IF(AND(Q10>0,T10<>""),Q10*1000-ROW(),0) | Y10: =IF(P10="Force",1000-ROW(),0)
A11: =IF(LARGE($X$5:$X$25,2)<=0,"",2) | B11: =IFERROR(IF(LARGE($X$5:$X$25,2)<=0,"",INDEX($T$5:$T$25,MATCH(LARGE($X$5:$X$25,2),$X$5:$X$25,0))),"") | C11: =IFERROR(IF(LARGE($X$5:$X$25,2)<=0,"",INDEX($R$5:$R$25,MATCH(LARGE($X$5:$X$25,2),$X$5:$X$25,0))),"") | D11: =IFERROR(IF(LARGE($X$5:$X$25,2)<=0,"",INDEX($S$5:$S$25,MATCH(LARGE($X$5:$X$25,2),$X$5:$X$25,0))),"") | E11: =IFERROR(IF(LARGE($X$5:$X$25,2)<=0,"",INDEX($W$5:$W$25,MATCH(LARGE($X$5:$X$25,2),$X$5:$X$25,0))),"") | F11: =IFERROR(IF(LARGE($X$5:$X$25,2)<=0,"",INDEX($V$5:$V$25,MATCH(LARGE($X$5:$X$25,2),$X$5:$X$25,0))),"") | M11: ='Simulateur'!D16 | N11: =IFERROR(INDEX('Bibliothèque constats'!$B$5:$B$88,MATCH($M11,'Bibliothèque constats'!$A$5:$A$88,0)),"") | O11: =IFERROR(INDEX('Bibliothèque constats'!$F$5:$F$88,MATCH($M11,'Bibliothèque constats'!$A$5:$A$88,0)),"") | P11: =IFERROR(INDEX('Bibliothèque constats'!$G$5:$G$88,MATCH($M11,'Bibliothèque constats'!$A$5:$A$88,0)),"") | Q11: =IFERROR(INDEX('Bibliothèque constats'!$H$5:$H$88,MATCH($M11,'Bibliothèque constats'!$A$5:$A$88,0)),"") | R11: =IFERROR(INDEX('Bibliothèque constats'!$I$5:$I$88,MATCH($M11,'Bibliothèque constats'!$A$5:$A$88,0)),"") | S11: =IFERROR(INDEX('Bibliothèque constats'!$J$5:$J$88,MATCH($M11,'Bibliothèque constats'!$A$5:$A$88,0)),"") | T11: =IFERROR(INDEX('Bibliothèque constats'!$K$5:$K$88,MATCH($M11,'Bibliothèque constats'!$A$5:$A$88,0)),"") | U11: =IFERROR(INDEX('Bibliothèque constats'!$L$5:$L$88,MATCH($M11,'Bibliothèque constats'!$A$5:$A$88,0)),"") | V11: =IFERROR(INDEX('Bibliothèque constats'!$M$5:$M$88,MATCH($M11,'Bibliothèque constats'!$A$5:$A$88,0)),"") | W11: =IFERROR(INDEX('Bibliothèque constats'!$E$5:$E$88,MATCH($M11,'Bibliothèque constats'!$A$5:$A$88,0)),"") | X11: =IF(AND(Q11>0,T11<>""),Q11*1000-ROW(),0) | Y11: =IF(P11="Force",1000-ROW(),0)
A12: =IF(LARGE($X$5:$X$25,3)<=0,"",3) | B12: =IFERROR(IF(LARGE($X$5:$X$25,3)<=0,"",INDEX($T$5:$T$25,MATCH(LARGE($X$5:$X$25,3),$X$5:$X$25,0))),"") | C12: =IFERROR(IF(LARGE($X$5:$X$25,3)<=0,"",INDEX($R$5:$R$25,MATCH(LARGE($X$5:$X$25,3),$X$5:$X$25,0))),"") | D12: =IFERROR(IF(LARGE($X$5:$X$25,3)<=0,"",INDEX($S$5:$S$25,MATCH(LARGE($X$5:$X$25,3),$X$5:$X$25,0))),"") | E12: =IFERROR(IF(LARGE($X$5:$X$25,3)<=0,"",INDEX($W$5:$W$25,MATCH(LARGE($X$5:$X$25,3),$X$5:$X$25,0))),"") | F12: =IFERROR(IF(LARGE($X$5:$X$25,3)<=0,"",INDEX($V$5:$V$25,MATCH(LARGE($X$5:$X$25,3),$X$5:$X$25,0))),"") | M12: ='Simulateur'!D17 | N12: =IFERROR(INDEX('Bibliothèque constats'!$B$5:$B$88,MATCH($M12,'Bibliothèque constats'!$A$5:$A$88,0)),"") | O12: =IFERROR(INDEX('Bibliothèque constats'!$F$5:$F$88,MATCH($M12,'Bibliothèque constats'!$A$5:$A$88,0)),"") | P12: =IFERROR(INDEX('Bibliothèque constats'!$G$5:$G$88,MATCH($M12,'Bibliothèque constats'!$A$5:$A$88,0)),"") | Q12: =IFERROR(INDEX('Bibliothèque constats'!$H$5:$H$88,MATCH($M12,'Bibliothèque constats'!$A$5:$A$88,0)),"") | R12: =IFERROR(INDEX('Bibliothèque constats'!$I$5:$I$88,MATCH($M12,'Bibliothèque constats'!$A$5:$A$88,0)),"") | S12: =IFERROR(INDEX('Bibliothèque constats'!$J$5:$J$88,MATCH($M12,'Bibliothèque constats'!$A$5:$A$88,0)),"") | T12: =IFERROR(INDEX('Bibliothèque constats'!$K$5:$K$88,MATCH($M12,'Bibliothèque constats'!$A$5:$A$88,0)),"") | U12: =IFERROR(INDEX('Bibliothèque constats'!$L$5:$L$88,MATCH($M12,'Bibliothèque constats'!$A$5:$A$88,0)),"") | V12: =IFERROR(INDEX('Bibliothèque constats'!$M$5:$M$88,MATCH($M12,'Bibliothèque constats'!$A$5:$A$88,0)),"") | W12: =IFERROR(INDEX('Bibliothèque constats'!$E$5:$E$88,MATCH($M12,'Bibliothèque constats'!$A$5:$A$88,0)),"") | X12: =IF(AND(Q12>0,T12<>""),Q12*1000-ROW(),0) | Y12: =IF(P12="Force",1000-ROW(),0)
A13: =IF(LARGE($X$5:$X$25,4)<=0,"",4) | B13: =IFERROR(IF(LARGE($X$5:$X$25,4)<=0,"",INDEX($T$5:$T$25,MATCH(LARGE($X$5:$X$25,4),$X$5:$X$25,0))),"") | C13: =IFERROR(IF(LARGE($X$5:$X$25,4)<=0,"",INDEX($R$5:$R$25,MATCH(LARGE($X$5:$X$25,4),$X$5:$X$25,0))),"") | D13: =IFERROR(IF(LARGE($X$5:$X$25,4)<=0,"",INDEX($S$5:$S$25,MATCH(LARGE($X$5:$X$25,4),$X$5:$X$25,0))),"") | E13: =IFERROR(IF(LARGE($X$5:$X$25,4)<=0,"",INDEX($W$5:$W$25,MATCH(LARGE($X$5:$X$25,4),$X$5:$X$25,0))),"") | F13: =IFERROR(IF(LARGE($X$5:$X$25,4)<=0,"",INDEX($V$5:$V$25,MATCH(LARGE($X$5:$X$25,4),$X$5:$X$25,0))),"") | M13: ='Simulateur'!D18 | N13: =IFERROR(INDEX('Bibliothèque constats'!$B$5:$B$88,MATCH($M13,'Bibliothèque constats'!$A$5:$A$88,0)),"") | O13: =IFERROR(INDEX('Bibliothèque constats'!$F$5:$F$88,MATCH($M13,'Bibliothèque constats'!$A$5:$A$88,0)),"") | P13: =IFERROR(INDEX('Bibliothèque constats'!$G$5:$G$88,MATCH($M13,'Bibliothèque constats'!$A$5:$A$88,0)),"") | Q13: =IFERROR(INDEX('Bibliothèque constats'!$H$5:$H$88,MATCH($M13,'Bibliothèque constats'!$A$5:$A$88,0)),"") | R13: =IFERROR(INDEX('Bibliothèque constats'!$I$5:$I$88,MATCH($M13,'Bibliothèque constats'!$A$5:$A$88,0)),"") | S13: =IFERROR(INDEX('Bibliothèque constats'!$J$5:$J$88,MATCH($M13,'Bibliothèque constats'!$A$5:$A$88,0)),"") | T13: =IFERROR(INDEX('Bibliothèque constats'!$K$5:$K$88,MATCH($M13,'Bibliothèque constats'!$A$5:$A$88,0)),"") | U13: =IFERROR(INDEX('Bibliothèque constats'!$L$5:$L$88,MATCH($M13,'Bibliothèque constats'!$A$5:$A$88,0)),"") | V13: =IFERROR(INDEX('Bibliothèque constats'!$M$5:$M$88,MATCH($M13,'Bibliothèque constats'!$A$5:$A$88,0)),"") | W13: =IFERROR(INDEX('Bibliothèque constats'!$E$5:$E$88,MATCH($M13,'Bibliothèque constats'!$A$5:$A$88,0)),"") | X13: =IF(AND(Q13>0,T13<>""),Q13*1000-ROW(),0) | Y13: =IF(P13="Force",1000-ROW(),0)
A14: =IF(LARGE($X$5:$X$25,5)<=0,"",5) | B14: =IFERROR(IF(LARGE($X$5:$X$25,5)<=0,"",INDEX($T$5:$T$25,MATCH(LARGE($X$5:$X$25,5),$X$5:$X$25,0))),"") | C14: =IFERROR(IF(LARGE($X$5:$X$25,5)<=0,"",INDEX($R$5:$R$25,MATCH(LARGE($X$5:$X$25,5),$X$5:$X$25,0))),"") | D14: =IFERROR(IF(LARGE($X$5:$X$25,5)<=0,"",INDEX($S$5:$S$25,MATCH(LARGE($X$5:$X$25,5),$X$5:$X$25,0))),"") | E14: =IFERROR(IF(LARGE($X$5:$X$25,5)<=0,"",INDEX($W$5:$W$25,MATCH(LARGE($X$5:$X$25,5),$X$5:$X$25,0))),"") | F14: =IFERROR(IF(LARGE($X$5:$X$25,5)<=0,"",INDEX($V$5:$V$25,MATCH(LARGE($X$5:$X$25,5),$X$5:$X$25,0))),"") | M14: ='Simulateur'!D19 | N14: =IFERROR(INDEX('Bibliothèque constats'!$B$5:$B$88,MATCH($M14,'Bibliothèque constats'!$A$5:$A$88,0)),"") | O14: =IFERROR(INDEX('Bibliothèque constats'!$F$5:$F$88,MATCH($M14,'Bibliothèque constats'!$A$5:$A$88,0)),"") | P14: =IFERROR(INDEX('Bibliothèque constats'!$G$5:$G$88,MATCH($M14,'Bibliothèque constats'!$A$5:$A$88,0)),"") | Q14: =IFERROR(INDEX('Bibliothèque constats'!$H$5:$H$88,MATCH($M14,'Bibliothèque constats'!$A$5:$A$88,0)),"") | R14: =IFERROR(INDEX('Bibliothèque constats'!$I$5:$I$88,MATCH($M14,'Bibliothèque constats'!$A$5:$A$88,0)),"") | S14: =IFERROR(INDEX('Bibliothèque constats'!$J$5:$J$88,MATCH($M14,'Bibliothèque constats'!$A$5:$A$88,0)),"") | T14: =IFERROR(INDEX('Bibliothèque constats'!$K$5:$K$88,MATCH($M14,'Bibliothèque constats'!$A$5:$A$88,0)),"") | U14: =IFERROR(INDEX('Bibliothèque constats'!$L$5:$L$88,MATCH($M14,'Bibliothèque constats'!$A$5:$A$88,0)),"") | V14: =IFERROR(INDEX('Bibliothèque constats'!$M$5:$M$88,MATCH($M14,'Bibliothèque constats'!$A$5:$A$88,0)),"") | W14: =IFERROR(INDEX('Bibliothèque constats'!$E$5:$E$88,MATCH($M14,'Bibliothèque constats'!$A$5:$A$88,0)),"") | X14: =IF(AND(Q14>0,T14<>""),Q14*1000-ROW(),0) | Y14: =IF(P14="Force",1000-ROW(),0)
A15: =IF(LARGE($X$5:$X$25,6)<=0,"",6) | B15: =IFERROR(IF(LARGE($X$5:$X$25,6)<=0,"",INDEX($T$5:$T$25,MATCH(LARGE($X$5:$X$25,6),$X$5:$X$25,0))),"") | C15: =IFERROR(IF(LARGE($X$5:$X$25,6)<=0,"",INDEX($R$5:$R$25,MATCH(LARGE($X$5:$X$25,6),$X$5:$X$25,0))),"") | D15: =IFERROR(IF(LARGE($X$5:$X$25,6)<=0,"",INDEX($S$5:$S$25,MATCH(LARGE($X$5:$X$25,6),$X$5:$X$25,0))),"") | E15: =IFERROR(IF(LARGE($X$5:$X$25,6)<=0,"",INDEX($W$5:$W$25,MATCH(LARGE($X$5:$X$25,6),$X$5:$X$25,0))),"") | F15: =IFERROR(IF(LARGE($X$5:$X$25,6)<=0,"",INDEX($V$5:$V$25,MATCH(LARGE($X$5:$X$25,6),$X$5:$X$25,0))),"") | M15: ='Simulateur'!D20 | N15: =IFERROR(INDEX('Bibliothèque constats'!$B$5:$B$88,MATCH($M15,'Bibliothèque constats'!$A$5:$A$88,0)),"") | O15: =IFERROR(INDEX('Bibliothèque constats'!$F$5:$F$88,MATCH($M15,'Bibliothèque constats'!$A$5:$A$88,0)),"") | P15: =IFERROR(INDEX('Bibliothèque constats'!$G$5:$G$88,MATCH($M15,'Bibliothèque constats'!$A$5:$A$88,0)),"") | Q15: =IFERROR(INDEX('Bibliothèque constats'!$H$5:$H$88,MATCH($M15,'Bibliothèque constats'!$A$5:$A$88,0)),"") | R15: =IFERROR(INDEX('Bibliothèque constats'!$I$5:$I$88,MATCH($M15,'Bibliothèque constats'!$A$5:$A$88,0)),"") | S15: =IFERROR(INDEX('Bibliothèque constats'!$J$5:$J$88,MATCH($M15,'Bibliothèque constats'!$A$5:$A$88,0)),"") | T15: =IFERROR(INDEX('Bibliothèque constats'!$K$5:$K$88,MATCH($M15,'Bibliothèque constats'!$A$5:$A$88,0)),"") | U15: =IFERROR(INDEX('Bibliothèque constats'!$L$5:$L$88,MATCH($M15,'Bibliothèque constats'!$A$5:$A$88,0)),"") | V15: =IFERROR(INDEX('Bibliothèque constats'!$M$5:$M$88,MATCH($M15,'Bibliothèque constats'!$A$5:$A$88,0)),"") | W15: =IFERROR(INDEX('Bibliothèque constats'!$E$5:$E$88,MATCH($M15,'Bibliothèque constats'!$A$5:$A$88,0)),"") | X15: =IF(AND(Q15>0,T15<>""),Q15*1000-ROW(),0) | Y15: =IF(P15="Force",1000-ROW(),0)
M16: ='Simulateur'!D21 | N16: =IFERROR(INDEX('Bibliothèque constats'!$B$5:$B$88,MATCH($M16,'Bibliothèque constats'!$A$5:$A$88,0)),"") | O16: =IFERROR(INDEX('Bibliothèque constats'!$F$5:$F$88,MATCH($M16,'Bibliothèque constats'!$A$5:$A$88,0)),"") | P16: =IFERROR(INDEX('Bibliothèque constats'!$G$5:$G$88,MATCH($M16,'Bibliothèque constats'!$A$5:$A$88,0)),"") | Q16: =IFERROR(INDEX('Bibliothèque constats'!$H$5:$H$88,MATCH($M16,'Bibliothèque constats'!$A$5:$A$88,0)),"") | R16: =IFERROR(INDEX('Bibliothèque constats'!$I$5:$I$88,MATCH($M16,'Bibliothèque constats'!$A$5:$A$88,0)),"") | S16: =IFERROR(INDEX('Bibliothèque constats'!$J$5:$J$88,MATCH($M16,'Bibliothèque constats'!$A$5:$A$88,0)),"") | T16: =IFERROR(INDEX('Bibliothèque constats'!$K$5:$K$88,MATCH($M16,'Bibliothèque constats'!$A$5:$A$88,0)),"") | U16: =IFERROR(INDEX('Bibliothèque constats'!$L$5:$L$88,MATCH($M16,'Bibliothèque constats'!$A$5:$A$88,0)),"") | V16: =IFERROR(INDEX('Bibliothèque constats'!$M$5:$M$88,MATCH($M16,'Bibliothèque constats'!$A$5:$A$88,0)),"") | W16: =IFERROR(INDEX('Bibliothèque constats'!$E$5:$E$88,MATCH($M16,'Bibliothèque constats'!$A$5:$A$88,0)),"") | X16: =IF(AND(Q16>0,T16<>""),Q16*1000-ROW(),0) | Y16: =IF(P16="Force",1000-ROW(),0)
A17: Forces et pratiques déjà en place | M17: ='Simulateur'!D22 | N17: =IFERROR(INDEX('Bibliothèque constats'!$B$5:$B$88,MATCH($M17,'Bibliothèque constats'!$A$5:$A$88,0)),"") | O17: =IFERROR(INDEX('Bibliothèque constats'!$F$5:$F$88,MATCH($M17,'Bibliothèque constats'!$A$5:$A$88,0)),"") | P17: =IFERROR(INDEX('Bibliothèque constats'!$G$5:$G$88,MATCH($M17,'Bibliothèque constats'!$A$5:$A$88,0)),"") | Q17: =IFERROR(INDEX('Bibliothèque constats'!$H$5:$H$88,MATCH($M17,'Bibliothèque constats'!$A$5:$A$88,0)),"") | R17: =IFERROR(INDEX('Bibliothèque constats'!$I$5:$I$88,MATCH($M17,'Bibliothèque constats'!$A$5:$A$88,0)),"") | S17: =IFERROR(INDEX('Bibliothèque constats'!$J$5:$J$88,MATCH($M17,'Bibliothèque constats'!$A$5:$A$88,0)),"") | T17: =IFERROR(INDEX('Bibliothèque constats'!$K$5:$K$88,MATCH($M17,'Bibliothèque constats'!$A$5:$A$88,0)),"") | U17: =IFERROR(INDEX('Bibliothèque constats'!$L$5:$L$88,MATCH($M17,'Bibliothèque constats'!$A$5:$A$88,0)),"") | V17: =IFERROR(INDEX('Bibliothèque constats'!$M$5:$M$88,MATCH($M17,'Bibliothèque constats'!$A$5:$A$88,0)),"") | W17: =IFERROR(INDEX('Bibliothèque constats'!$E$5:$E$88,MATCH($M17,'Bibliothèque constats'!$A$5:$A$88,0)),"") | X17: =IF(AND(Q17>0,T17<>""),Q17*1000-ROW(),0) | Y17: =IF(P17="Force",1000-ROW(),0)
A18: # | B18: Force / pratique observée | C18: Dimension | D18: Réponse sélectionnée | E18: Question pour capitaliser | M18: ='Simulateur'!D23 | N18: =IFERROR(INDEX('Bibliothèque constats'!$B$5:$B$88,MATCH($M18,'Bibliothèque constats'!$A$5:$A$88,0)),"") | O18: =IFERROR(INDEX('Bibliothèque constats'!$F$5:$F$88,MATCH($M18,'Bibliothèque constats'!$A$5:$A$88,0)),"") | P18: =IFERROR(INDEX('Bibliothèque constats'!$G$5:$G$88,MATCH($M18,'Bibliothèque constats'!$A$5:$A$88,0)),"") | Q18: =IFERROR(INDEX('Bibliothèque constats'!$H$5:$H$88,MATCH($M18,'Bibliothèque constats'!$A$5:$A$88,0)),"") | R18: =IFERROR(INDEX('Bibliothèque constats'!$I$5:$I$88,MATCH($M18,'Bibliothèque constats'!$A$5:$A$88,0)),"") | S18: =IFERROR(INDEX('Bibliothèque constats'!$J$5:$J$88,MATCH($M18,'Bibliothèque constats'!$A$5:$A$88,0)),"") | T18: =IFERROR(INDEX('Bibliothèque constats'!$K$5:$K$88,MATCH($M18,'Bibliothèque constats'!$A$5:$A$88,0)),"") | U18: =IFERROR(INDEX('Bibliothèque constats'!$L$5:$L$88,MATCH($M18,'Bibliothèque constats'!$A$5:$A$88,0)),"") | V18: =IFERROR(INDEX('Bibliothèque constats'!$M$5:$M$88,MATCH($M18,'Bibliothèque constats'!$A$5:$A$88,0)),"") | W18: =IFERROR(INDEX('Bibliothèque constats'!$E$5:$E$88,MATCH($M18,'Bibliothèque constats'!$A$5:$A$88,0)),"") | X18: =IF(AND(Q18>0,T18<>""),Q18*1000-ROW(),0) | Y18: =IF(P18="Force",1000-ROW(),0)
A19: =IF(LARGE($Y$5:$Y$25,1)<=0,"",1) | B19: =IFERROR(IF(LARGE($Y$5:$Y$25,1)<=0,"",INDEX($S$5:$S$25,MATCH(LARGE($Y$5:$Y$25,1),$Y$5:$Y$25,0))),"") | C19: =IFERROR(IF(LARGE($Y$5:$Y$25,1)<=0,"",INDEX($O$5:$O$25,MATCH(LARGE($Y$5:$Y$25,1),$Y$5:$Y$25,0))),"") | D19: =IFERROR(IF(LARGE($Y$5:$Y$25,1)<=0,"",INDEX($W$5:$W$25,MATCH(LARGE($Y$5:$Y$25,1),$Y$5:$Y$25,0))),"") | E19: =IFERROR(IF(LARGE($Y$5:$Y$25,1)<=0,"",INDEX($V$5:$V$25,MATCH(LARGE($Y$5:$Y$25,1),$Y$5:$Y$25,0))),"") | M19: ='Simulateur'!D40 | N19: =IFERROR(INDEX('Bibliothèque constats'!$B$5:$B$88,MATCH($M19,'Bibliothèque constats'!$A$5:$A$88,0)),"") | O19: =IFERROR(INDEX('Bibliothèque constats'!$F$5:$F$88,MATCH($M19,'Bibliothèque constats'!$A$5:$A$88,0)),"") | P19: =IFERROR(INDEX('Bibliothèque constats'!$G$5:$G$88,MATCH($M19,'Bibliothèque constats'!$A$5:$A$88,0)),"") | Q19: =IFERROR(INDEX('Bibliothèque constats'!$H$5:$H$88,MATCH($M19,'Bibliothèque constats'!$A$5:$A$88,0)),"") | R19: =IFERROR(INDEX('Bibliothèque constats'!$I$5:$I$88,MATCH($M19,'Bibliothèque constats'!$A$5:$A$88,0)),"") | S19: =IFERROR(INDEX('Bibliothèque constats'!$J$5:$J$88,MATCH($M19,'Bibliothèque constats'!$A$5:$A$88,0)),"") | T19: =IFERROR(INDEX('Bibliothèque constats'!$K$5:$K$88,MATCH($M19,'Bibliothèque constats'!$A$5:$A$88,0)),"") | U19: =IFERROR(INDEX('Bibliothèque constats'!$L$5:$L$88,MATCH($M19,'Bibliothèque constats'!$A$5:$A$88,0)),"") | V19: =IFERROR(INDEX('Bibliothèque constats'!$M$5:$M$88,MATCH($M19,'Bibliothèque constats'!$A$5:$A$88,0)),"") | W19: =IFERROR(INDEX('Bibliothèque constats'!$E$5:$E$88,MATCH($M19,'Bibliothèque constats'!$A$5:$A$88,0)),"") | X19: =IF(AND(Q19>0,T19<>""),Q19*1000-ROW(),0) | Y19: =IF(P19="Force",1000-ROW(),0)
A20: =IF(LARGE($Y$5:$Y$25,2)<=0,"",2) | B20: =IFERROR(IF(LARGE($Y$5:$Y$25,2)<=0,"",INDEX($S$5:$S$25,MATCH(LARGE($Y$5:$Y$25,2),$Y$5:$Y$25,0))),"") | C20: =IFERROR(IF(LARGE($Y$5:$Y$25,2)<=0,"",INDEX($O$5:$O$25,MATCH(LARGE($Y$5:$Y$25,2),$Y$5:$Y$25,0))),"") | D20: =IFERROR(IF(LARGE($Y$5:$Y$25,2)<=0,"",INDEX($W$5:$W$25,MATCH(LARGE($Y$5:$Y$25,2),$Y$5:$Y$25,0))),"") | E20: =IFERROR(IF(LARGE($Y$5:$Y$25,2)<=0,"",INDEX($V$5:$V$25,MATCH(LARGE($Y$5:$Y$25,2),$Y$5:$Y$25,0))),"") | M20: ='Simulateur'!D41 | N20: =IFERROR(INDEX('Bibliothèque constats'!$B$5:$B$88,MATCH($M20,'Bibliothèque constats'!$A$5:$A$88,0)),"") | O20: =IFERROR(INDEX('Bibliothèque constats'!$F$5:$F$88,MATCH($M20,'Bibliothèque constats'!$A$5:$A$88,0)),"") | P20: =IFERROR(INDEX('Bibliothèque constats'!$G$5:$G$88,MATCH($M20,'Bibliothèque constats'!$A$5:$A$88,0)),"") | Q20: =IFERROR(INDEX('Bibliothèque constats'!$H$5:$H$88,MATCH($M20,'Bibliothèque constats'!$A$5:$A$88,0)),"") | R20: =IFERROR(INDEX('Bibliothèque constats'!$I$5:$I$88,MATCH($M20,'Bibliothèque constats'!$A$5:$A$88,0)),"") | S20: =IFERROR(INDEX('Bibliothèque constats'!$J$5:$J$88,MATCH($M20,'Bibliothèque constats'!$A$5:$A$88,0)),"") | T20: =IFERROR(INDEX('Bibliothèque constats'!$K$5:$K$88,MATCH($M20,'Bibliothèque constats'!$A$5:$A$88,0)),"") | U20: =IFERROR(INDEX('Bibliothèque constats'!$L$5:$L$88,MATCH($M20,'Bibliothèque constats'!$A$5:$A$88,0)),"") | V20: =IFERROR(INDEX('Bibliothèque constats'!$M$5:$M$88,MATCH($M20,'Bibliothèque constats'!$A$5:$A$88,0)),"") | W20: =IFERROR(INDEX('Bibliothèque constats'!$E$5:$E$88,MATCH($M20,'Bibliothèque constats'!$A$5:$A$88,0)),"") | X20: =IF(AND(Q20>0,T20<>""),Q20*1000-ROW(),0) | Y20: =IF(P20="Force",1000-ROW(),0)
A21: =IF(LARGE($Y$5:$Y$25,3)<=0,"",3) | B21: =IFERROR(IF(LARGE($Y$5:$Y$25,3)<=0,"",INDEX($S$5:$S$25,MATCH(LARGE($Y$5:$Y$25,3),$Y$5:$Y$25,0))),"") | C21: =IFERROR(IF(LARGE($Y$5:$Y$25,3)<=0,"",INDEX($O$5:$O$25,MATCH(LARGE($Y$5:$Y$25,3),$Y$5:$Y$25,0))),"") | D21: =IFERROR(IF(LARGE($Y$5:$Y$25,3)<=0,"",INDEX($W$5:$W$25,MATCH(LARGE($Y$5:$Y$25,3),$Y$5:$Y$25,0))),"") | E21: =IFERROR(IF(LARGE($Y$5:$Y$25,3)<=0,"",INDEX($V$5:$V$25,MATCH(LARGE($Y$5:$Y$25,3),$Y$5:$Y$25,0))),"") | M21: ='Simulateur'!D42 | N21: =IFERROR(INDEX('Bibliothèque constats'!$B$5:$B$88,MATCH($M21,'Bibliothèque constats'!$A$5:$A$88,0)),"") | O21: =IFERROR(INDEX('Bibliothèque constats'!$F$5:$F$88,MATCH($M21,'Bibliothèque constats'!$A$5:$A$88,0)),"") | P21: =IFERROR(INDEX('Bibliothèque constats'!$G$5:$G$88,MATCH($M21,'Bibliothèque constats'!$A$5:$A$88,0)),"") | Q21: =IFERROR(INDEX('Bibliothèque constats'!$H$5:$H$88,MATCH($M21,'Bibliothèque constats'!$A$5:$A$88,0)),"") | R21: =IFERROR(INDEX('Bibliothèque constats'!$I$5:$I$88,MATCH($M21,'Bibliothèque constats'!$A$5:$A$88,0)),"") | S21: =IFERROR(INDEX('Bibliothèque constats'!$J$5:$J$88,MATCH($M21,'Bibliothèque constats'!$A$5:$A$88,0)),"") | T21: =IFERROR(INDEX('Bibliothèque constats'!$K$5:$K$88,MATCH($M21,'Bibliothèque constats'!$A$5:$A$88,0)),"") | U21: =IFERROR(INDEX('Bibliothèque constats'!$L$5:$L$88,MATCH($M21,'Bibliothèque constats'!$A$5:$A$88,0)),"") | V21: =IFERROR(INDEX('Bibliothèque constats'!$M$5:$M$88,MATCH($M21,'Bibliothèque constats'!$A$5:$A$88,0)),"") | W21: =IFERROR(INDEX('Bibliothèque constats'!$E$5:$E$88,MATCH($M21,'Bibliothèque constats'!$A$5:$A$88,0)),"") | X21: =IF(AND(Q21>0,T21<>""),Q21*1000-ROW(),0) | Y21: =IF(P21="Force",1000-ROW(),0)
A22: =IF(LARGE($Y$5:$Y$25,4)<=0,"",4) | B22: =IFERROR(IF(LARGE($Y$5:$Y$25,4)<=0,"",INDEX($S$5:$S$25,MATCH(LARGE($Y$5:$Y$25,4),$Y$5:$Y$25,0))),"") | C22: =IFERROR(IF(LARGE($Y$5:$Y$25,4)<=0,"",INDEX($O$5:$O$25,MATCH(LARGE($Y$5:$Y$25,4),$Y$5:$Y$25,0))),"") | D22: =IFERROR(IF(LARGE($Y$5:$Y$25,4)<=0,"",INDEX($W$5:$W$25,MATCH(LARGE($Y$5:$Y$25,4),$Y$5:$Y$25,0))),"") | E22: =IFERROR(IF(LARGE($Y$5:$Y$25,4)<=0,"",INDEX($V$5:$V$25,MATCH(LARGE($Y$5:$Y$25,4),$Y$5:$Y$25,0))),"") | M22: ='Simulateur'!D43 | N22: =IFERROR(INDEX('Bibliothèque constats'!$B$5:$B$88,MATCH($M22,'Bibliothèque constats'!$A$5:$A$88,0)),"") | O22: =IFERROR(INDEX('Bibliothèque constats'!$F$5:$F$88,MATCH($M22,'Bibliothèque constats'!$A$5:$A$88,0)),"") | P22: =IFERROR(INDEX('Bibliothèque constats'!$G$5:$G$88,MATCH($M22,'Bibliothèque constats'!$A$5:$A$88,0)),"") | Q22: =IFERROR(INDEX('Bibliothèque constats'!$H$5:$H$88,MATCH($M22,'Bibliothèque constats'!$A$5:$A$88,0)),"") | R22: =IFERROR(INDEX('Bibliothèque constats'!$I$5:$I$88,MATCH($M22,'Bibliothèque constats'!$A$5:$A$88,0)),"") | S22: =IFERROR(INDEX('Bibliothèque constats'!$J$5:$J$88,MATCH($M22,'Bibliothèque constats'!$A$5:$A$88,0)),"") | T22: =IFERROR(INDEX('Bibliothèque constats'!$K$5:$K$88,MATCH($M22,'Bibliothèque constats'!$A$5:$A$88,0)),"") | U22: =IFERROR(INDEX('Bibliothèque constats'!$L$5:$L$88,MATCH($M22,'Bibliothèque constats'!$A$5:$A$88,0)),"") | V22: =IFERROR(INDEX('Bibliothèque constats'!$M$5:$M$88,MATCH($M22,'Bibliothèque constats'!$A$5:$A$88,0)),"") | W22: =IFERROR(INDEX('Bibliothèque constats'!$E$5:$E$88,MATCH($M22,'Bibliothèque constats'!$A$5:$A$88,0)),"") | X22: =IF(AND(Q22>0,T22<>""),Q22*1000-ROW(),0) | Y22: =IF(P22="Force",1000-ROW(),0)
M23: ='Simulateur'!D44 | N23: =IFERROR(INDEX('Bibliothèque constats'!$B$5:$B$88,MATCH($M23,'Bibliothèque constats'!$A$5:$A$88,0)),"") | O23: =IFERROR(INDEX('Bibliothèque constats'!$F$5:$F$88,MATCH($M23,'Bibliothèque constats'!$A$5:$A$88,0)),"") | P23: =IFERROR(INDEX('Bibliothèque constats'!$G$5:$G$88,MATCH($M23,'Bibliothèque constats'!$A$5:$A$88,0)),"") | Q23: =IFERROR(INDEX('Bibliothèque constats'!$H$5:$H$88,MATCH($M23,'Bibliothèque constats'!$A$5:$A$88,0)),"") | R23: =IFERROR(INDEX('Bibliothèque constats'!$I$5:$I$88,MATCH($M23,'Bibliothèque constats'!$A$5:$A$88,0)),"") | S23: =IFERROR(INDEX('Bibliothèque constats'!$J$5:$J$88,MATCH($M23,'Bibliothèque constats'!$A$5:$A$88,0)),"") | T23: =IFERROR(INDEX('Bibliothèque constats'!$K$5:$K$88,MATCH($M23,'Bibliothèque constats'!$A$5:$A$88,0)),"") | U23: =IFERROR(INDEX('Bibliothèque constats'!$L$5:$L$88,MATCH($M23,'Bibliothèque constats'!$A$5:$A$88,0)),"") | V23: =IFERROR(INDEX('Bibliothèque constats'!$M$5:$M$88,MATCH($M23,'Bibliothèque constats'!$A$5:$A$88,0)),"") | W23: =IFERROR(INDEX('Bibliothèque constats'!$E$5:$E$88,MATCH($M23,'Bibliothèque constats'!$A$5:$A$88,0)),"") | X23: =IF(AND(Q23>0,T23<>""),Q23*1000-ROW(),0) | Y23: =IF(P23="Force",1000-ROW(),0)
A24: Informations utiles pour préparer l’échange | M24: ='Simulateur'!D45 | N24: =IFERROR(INDEX('Bibliothèque constats'!$B$5:$B$88,MATCH($M24,'Bibliothèque constats'!$A$5:$A$88,0)),"") | O24: =IFERROR(INDEX('Bibliothèque constats'!$F$5:$F$88,MATCH($M24,'Bibliothèque constats'!$A$5:$A$88,0)),"") | P24: =IFERROR(INDEX('Bibliothèque constats'!$G$5:$G$88,MATCH($M24,'Bibliothèque constats'!$A$5:$A$88,0)),"") | Q24: =IFERROR(INDEX('Bibliothèque constats'!$H$5:$H$88,MATCH($M24,'Bibliothèque constats'!$A$5:$A$88,0)),"") | R24: =IFERROR(INDEX('Bibliothèque constats'!$I$5:$I$88,MATCH($M24,'Bibliothèque constats'!$A$5:$A$88,0)),"") | S24: =IFERROR(INDEX('Bibliothèque constats'!$J$5:$J$88,MATCH($M24,'Bibliothèque constats'!$A$5:$A$88,0)),"") | T24: =IFERROR(INDEX('Bibliothèque constats'!$K$5:$K$88,MATCH($M24,'Bibliothèque constats'!$A$5:$A$88,0)),"") | U24: =IFERROR(INDEX('Bibliothèque constats'!$L$5:$L$88,MATCH($M24,'Bibliothèque constats'!$A$5:$A$88,0)),"") | V24: =IFERROR(INDEX('Bibliothèque constats'!$M$5:$M$88,MATCH($M24,'Bibliothèque constats'!$A$5:$A$88,0)),"") | W24: =IFERROR(INDEX('Bibliothèque constats'!$E$5:$E$88,MATCH($M24,'Bibliothèque constats'!$A$5:$A$88,0)),"") | X24: =IF(AND(Q24>0,T24<>""),Q24*1000-ROW(),0) | Y24: =IF(P24="Force",1000-ROW(),0)
A25: Canal de vente déclaré | C25: =IF(S15="","",S15&" Réponse : "&W15) | M25: ='Simulateur'!D46 | N25: =IFERROR(INDEX('Bibliothèque constats'!$B$5:$B$88,MATCH($M25,'Bibliothèque constats'!$A$5:$A$88,0)),"") | O25: =IFERROR(INDEX('Bibliothèque constats'!$F$5:$F$88,MATCH($M25,'Bibliothèque constats'!$A$5:$A$88,0)),"") | P25: =IFERROR(INDEX('Bibliothèque constats'!$G$5:$G$88,MATCH($M25,'Bibliothèque constats'!$A$5:$A$88,0)),"") | Q25: =IFERROR(INDEX('Bibliothèque constats'!$H$5:$H$88,MATCH($M25,'Bibliothèque constats'!$A$5:$A$88,0)),"") | R25: =IFERROR(INDEX('Bibliothèque constats'!$I$5:$I$88,MATCH($M25,'Bibliothèque constats'!$A$5:$A$88,0)),"") | S25: =IFERROR(INDEX('Bibliothèque constats'!$J$5:$J$88,MATCH($M25,'Bibliothèque constats'!$A$5:$A$88,0)),"") | T25: =IFERROR(INDEX('Bibliothèque constats'!$K$5:$K$88,MATCH($M25,'Bibliothèque constats'!$A$5:$A$88,0)),"") | U25: =IFERROR(INDEX('Bibliothèque constats'!$L$5:$L$88,MATCH($M25,'Bibliothèque constats'!$A$5:$A$88,0)),"") | V25: =IFERROR(INDEX('Bibliothèque constats'!$M$5:$M$88,MATCH($M25,'Bibliothèque constats'!$A$5:$A$88,0)),"") | W25: =IFERROR(INDEX('Bibliothèque constats'!$E$5:$E$88,MATCH($M25,'Bibliothèque constats'!$A$5:$A$88,0)),"") | X25: =IF(AND(Q25>0,T25<>""),Q25*1000-ROW(),0) | Y25: =IF(P25="Force",1000-ROW(),0)
A26: Condition d’adoption déclarée | C26: =IF(S17="","",S17&" Réponse : "&W17)
A27: Progrès prioritaire déclaré | C27: =IF(S18="","",S18&" Réponse : "&W18)
A28: Nature de différenciation déclarée | C28: =IF(S21="","",S21&" Réponse : "&W21)
M29: ID | N29: Thème | O29: Gravité | P29: Niveau | Q29: Signaux | R29: Hypothèse | S29: Relance | T29: Détectée | U29: Rang
A30: Hypothèses issues du croisement des réponses | M30: RC01 | N30: Parcours social fragmenté | O30: 2 | P30: Modérée | Q30: Les ventes passent par les réseaux sociaux, mais le passage des interactions ou demandes numériques à des ventes mesurées reste à clarifier. | R30: Le parcours entre découverte, conversation, commande et paiement pourrait être fragmenté. | S30: Après une demande reçue sur les réseaux sociaux, quelles étapes le client suit-il jusqu’au paiement ? | T30: =IF(AND(COUNTIF('Simulateur'!$D$10:$D$23,"Q11C")>0,OR(COUNTIF('Simulateur'!$D$40:$D$46,"R6A")>0,COUNTIF('Simulateur'!$D$40:$D$46,"R6B")>0,COUNTIF('Simulateur'!$D$40:$D$46,"R6C")>0)),"Oui","") | U30: =IF(T30="Oui",O30*1000-ROW(),0)
A31: À présenter comme des questions à confirmer avec le prospect, jamais comme des faits établis. | M31: RC02 | N31: Site vitrine déconnecté | O31: 2 | P31: Modérée | Q31: Le site présente l’offre, mais la commande se finalise ailleurs et le digital produit peu d’opportunités. | R31: Le passage du site vers la commande ou le paiement pourrait provoquer des abandons. | S31: Que doit faire un visiteur intéressé après avoir consulté une offre sur votre site ? | T31: =IF(AND(COUNTIF('Simulateur'!$D$10:$D$23,"Q11B")>0,OR(COUNTIF('Simulateur'!$D$40:$D$46,"R6A")>0,COUNTIF('Simulateur'!$D$40:$D$46,"R6B")>0)),"Oui","") | U31: =IF(T31="Oui",O31*1000-ROW(),0)
A32: # | B32: Thème | C32: Gravité | D32: Signaux croisés | E32: Hypothèse à confirmer | F32: Question de relance | M32: RC03 | N32: Site transactionnel peu performant | O32: 2 | P32: Modérée | Q32: Le site permet de commander et payer, mais les effets numériques restent faibles ou non mesurés. | R32: La difficulté pourrait se situer dans l’acquisition, la conversion ou la mesure du parcours. | S32: À quelle étape du site perdez-vous le plus de visiteurs ou de commandes ? | T32: =IF(AND(COUNTIF('Simulateur'!$D$10:$D$23,"Q11A")>0,OR(COUNTIF('Simulateur'!$D$40:$D$46,"R6A")>0,COUNTIF('Simulateur'!$D$40:$D$46,"R6B")>0)),"Oui","") | U32: =IF(T32="Oui",O32*1000-ROW(),0)
A33: =IF(LARGE($U$30:$U$45,1)<=0,"",1) | B33: =IFERROR(IF(LARGE($U$30:$U$45,1)<=0,"",INDEX($N$30:$N$45,MATCH(LARGE($U$30:$U$45,1),$U$30:$U$45,0))),"") | C33: =IFERROR(IF(LARGE($U$30:$U$45,1)<=0,"",INDEX($P$30:$P$45,MATCH(LARGE($U$30:$U$45,1),$U$30:$U$45,0))),"") | D33: =IFERROR(IF(LARGE($U$30:$U$45,1)<=0,"",INDEX($Q$30:$Q$45,MATCH(LARGE($U$30:$U$45,1),$U$30:$U$45,0))),"") | E33: =IFERROR(IF(LARGE($U$30:$U$45,1)<=0,"",INDEX($R$30:$R$45,MATCH(LARGE($U$30:$U$45,1),$U$30:$U$45,0))),"") | F33: =IFERROR(IF(LARGE($U$30:$U$45,1)<=0,"",INDEX($S$30:$S$45,MATCH(LARGE($U$30:$U$45,1),$U$30:$U$45,0))),"") | M33: RC04 | N33: Encaissement à distance incomplet | O33: 3 | P33: Élevée | Q33: L’activité possède un canal de vente digital, mais ne dispose pas d’un parcours organisé pour encaisser à distance. | R33: La finalisation du paiement pourrait interrompre certaines ventes digitales. | S33: Combien de demandes à distance restent sans suite au moment de payer ? | T33: =IF(AND(OR(COUNTIF('Simulateur'!$D$10:$D$23,"Q10C")>0,COUNTIF('Simulateur'!$D$10:$D$23,"Q10D")>0),OR(COUNTIF('Simulateur'!$D$10:$D$23,"Q11A")>0,COUNTIF('Simulateur'!$D$10:$D$23,"Q11B")>0,COUNTIF('Simulateur'!$D$10:$D$23,"Q11C")>0)),"Oui","") | U33: =IF(T33="Oui",O33*1000-ROW(),0)
A34: =IF(LARGE($U$30:$U$45,2)<=0,"",2) | B34: =IFERROR(IF(LARGE($U$30:$U$45,2)<=0,"",INDEX($N$30:$N$45,MATCH(LARGE($U$30:$U$45,2),$U$30:$U$45,0))),"") | C34: =IFERROR(IF(LARGE($U$30:$U$45,2)<=0,"",INDEX($P$30:$P$45,MATCH(LARGE($U$30:$U$45,2),$U$30:$U$45,0))),"") | D34: =IFERROR(IF(LARGE($U$30:$U$45,2)<=0,"",INDEX($Q$30:$Q$45,MATCH(LARGE($U$30:$U$45,2),$U$30:$U$45,0))),"") | E34: =IFERROR(IF(LARGE($U$30:$U$45,2)<=0,"",INDEX($R$30:$R$45,MATCH(LARGE($U$30:$U$45,2),$U$30:$U$45,0))),"") | F34: =IFERROR(IF(LARGE($U$30:$U$45,2)<=0,"",INDEX($S$30:$S$45,MATCH(LARGE($U$30:$U$45,2),$U$30:$U$45,0))),"") | M34: RC05 | N34: Dispersion des paiements et trésorerie | O34: 3 | P34: Élevée | Q34: Les paiements sont dispersés et la trésorerie est évaluée à partir des soldes ou au moment des dépenses. | R34: La fragmentation des encaissements pourrait empêcher une lecture fiable de la trésorerie. | S34: Comment obtenez-vous un montant unique et fiable avant de décider d’une dépense ? | T34: =IF(AND(OR(COUNTIF('Simulateur'!$D$10:$D$23,"Q6B")>0,COUNTIF('Simulateur'!$D$10:$D$23,"Q6C")>0,COUNTIF('Simulateur'!$D$10:$D$23,"Q6D")>0),OR(COUNTIF('Simulateur'!$D$10:$D$23,"Q7C")>0,COUNTIF('Simulateur'!$D$10:$D$23,"Q7D")>0)),"Oui","") | U34: =IF(T34="Oui",O34*1000-ROW(),0)
A35: =IF(LARGE($U$30:$U$45,3)<=0,"",3) | B35: =IFERROR(IF(LARGE($U$30:$U$45,3)<=0,"",INDEX($N$30:$N$45,MATCH(LARGE($U$30:$U$45,3),$U$30:$U$45,0))),"") | C35: =IFERROR(IF(LARGE($U$30:$U$45,3)<=0,"",INDEX($P$30:$P$45,MATCH(LARGE($U$30:$U$45,3),$U$30:$U$45,0))),"") | D35: =IFERROR(IF(LARGE($U$30:$U$45,3)<=0,"",INDEX($Q$30:$Q$45,MATCH(LARGE($U$30:$U$45,3),$U$30:$U$45,0))),"") | E35: =IFERROR(IF(LARGE($U$30:$U$45,3)<=0,"",INDEX($R$30:$R$45,MATCH(LARGE($U$30:$U$45,3),$U$30:$U$45,0))),"") | F35: =IFERROR(IF(LARGE($U$30:$U$45,3)<=0,"",INDEX($S$30:$S$45,MATCH(LARGE($U$30:$U$45,3),$U$30:$U$45,0))),"") | M35: RC06 | N35: Écarts impossibles à expliquer rapidement | O35: 3 | P35: Élevée | Q35: Le suivi des ventes est reconstitué ou informel et les écarts dépendent d’explications ou restent sans preuve. | R35: L’entreprise pourrait manquer des éléments nécessaires pour distinguer erreur, oubli et vente non déclarée. | S35: Pouvez-vous retracer une vente précise depuis la commande jusqu’au paiement reçu ? | T35: =IF(AND(OR(COUNTIF('Simulateur'!$D$10:$D$23,"Q4C")>0,COUNTIF('Simulateur'!$D$10:$D$23,"Q4D")>0),OR(COUNTIF('Simulateur'!$D$10:$D$23,"Q5C")>0,COUNTIF('Simulateur'!$D$10:$D$23,"Q5D")>0)),"Oui","") | U35: =IF(T35="Oui",O35*1000-ROW(),0)
A36: =IF(LARGE($U$30:$U$45,4)<=0,"",4) | B36: =IFERROR(IF(LARGE($U$30:$U$45,4)<=0,"",INDEX($N$30:$N$45,MATCH(LARGE($U$30:$U$45,4),$U$30:$U$45,0))),"") | C36: =IFERROR(IF(LARGE($U$30:$U$45,4)<=0,"",INDEX($P$30:$P$45,MATCH(LARGE($U$30:$U$45,4),$U$30:$U$45,0))),"") | D36: =IFERROR(IF(LARGE($U$30:$U$45,4)<=0,"",INDEX($Q$30:$Q$45,MATCH(LARGE($U$30:$U$45,4),$U$30:$U$45,0))),"") | E36: =IFERROR(IF(LARGE($U$30:$U$45,4)<=0,"",INDEX($R$30:$R$45,MATCH(LARGE($U$30:$U$45,4),$U$30:$U$45,0))),"") | F36: =IFERROR(IF(LARGE($U$30:$U$45,4)<=0,"",INDEX($S$30:$S$45,MATCH(LARGE($U$30:$U$45,4),$U$30:$U$45,0))),"") | M36: RC07 | N36: Délégation insuffisamment traçable | O36: 3 | P36: Élevée | Q36: Des collaborateurs encaissent, mais le contrôle repose sur un support partagé, un point oral ou un montant global. | R36: Les responsabilités individuelles pourraient être difficiles à établir en cas d’écart. | S36: Comment attribuez-vous précisément un écart à une vente et à la personne concernée ? | T36: =IF(AND(OR(COUNTIF('Simulateur'!$D$10:$D$23,"Q9B")>0,COUNTIF('Simulateur'!$D$10:$D$23,"Q9C")>0),OR(COUNTIF('Simulateur'!$D$10:$D$23,"Q5C")>0,COUNTIF('Simulateur'!$D$10:$D$23,"Q5D")>0)),"Oui","") | U36: =IF(T36="Oui",O36*1000-ROW(),0)
A37: =IF(LARGE($U$30:$U$45,5)<=0,"",5) | B37: =IFERROR(IF(LARGE($U$30:$U$45,5)<=0,"",INDEX($N$30:$N$45,MATCH(LARGE($U$30:$U$45,5),$U$30:$U$45,0))),"") | C37: =IFERROR(IF(LARGE($U$30:$U$45,5)<=0,"",INDEX($P$30:$P$45,MATCH(LARGE($U$30:$U$45,5),$U$30:$U$45,0))),"") | D37: =IFERROR(IF(LARGE($U$30:$U$45,5)<=0,"",INDEX($Q$30:$Q$45,MATCH(LARGE($U$30:$U$45,5),$U$30:$U$45,0))),"") | E37: =IFERROR(IF(LARGE($U$30:$U$45,5)<=0,"",INDEX($R$30:$R$45,MATCH(LARGE($U$30:$U$45,5),$U$30:$U$45,0))),"") | F37: =IFERROR(IF(LARGE($U$30:$U$45,5)<=0,"",INDEX($S$30:$S$45,MATCH(LARGE($U$30:$U$45,5),$U$30:$U$45,0))),"") | M37: RC08 | N37: Comptabilité dépendante des reconstitutions | O37: 3 | P37: Élevée | Q37: Les ventes et opérations doivent être rassemblées ou reconstituées avant la comptabilité. | R37: La préparation comptable pourrait consommer beaucoup de temps et laisser des opérations mal documentées. | S37: Quelles informations vous manquent le plus souvent au moment de préparer la comptabilité ? | T37: =IF(AND(OR(COUNTIF('Simulateur'!$D$10:$D$23,"Q8C")>0,COUNTIF('Simulateur'!$D$10:$D$23,"Q8D")>0),OR(COUNTIF('Simulateur'!$D$10:$D$23,"Q4C")>0,COUNTIF('Simulateur'!$D$10:$D$23,"Q4D")>0)),"Oui","") | U37: =IF(T37="Oui",O37*1000-ROW(),0)
A38: =IF(LARGE($U$30:$U$45,6)<=0,"",6) | B38: =IFERROR(IF(LARGE($U$30:$U$45,6)<=0,"",INDEX($N$30:$N$45,MATCH(LARGE($U$30:$U$45,6),$U$30:$U$45,0))),"") | C38: =IFERROR(IF(LARGE($U$30:$U$45,6)<=0,"",INDEX($P$30:$P$45,MATCH(LARGE($U$30:$U$45,6),$U$30:$U$45,0))),"") | D38: =IFERROR(IF(LARGE($U$30:$U$45,6)<=0,"",INDEX($Q$30:$Q$45,MATCH(LARGE($U$30:$U$45,6),$U$30:$U$45,0))),"") | E38: =IFERROR(IF(LARGE($U$30:$U$45,6)<=0,"",INDEX($R$30:$R$45,MATCH(LARGE($U$30:$U$45,6),$U$30:$U$45,0))),"") | F38: =IFERROR(IF(LARGE($U$30:$U$45,6)<=0,"",INDEX($S$30:$S$45,MATCH(LARGE($U$30:$U$45,6),$U$30:$U$45,0))),"") | M38: RC09 | N38: Présence irrégulière sans conversion | O38: 2 | P38: Modérée | Q38: La présence numérique est faible ou irrégulière et produit peu de résultats commerciaux identifiables. | R38: Le problème pourrait combiner manque de régularité, absence de parcours et faible mesure. | S38: Quel résultat précis attendez-vous de votre présence numérique aujourd’hui ? | T38: =IF(AND(OR(COUNTIF('Simulateur'!$D$40:$D$46,"R5A")>0,COUNTIF('Simulateur'!$D$40:$D$46,"R5B")>0),OR(COUNTIF('Simulateur'!$D$40:$D$46,"R6A")>0,COUNTIF('Simulateur'!$D$40:$D$46,"R6B")>0)),"Oui","") | U38: =IF(T38="Oui",O38*1000-ROW(),0)
M39: RC10 | N39: Faible notoriété et faible présence | O39: 2 | P39: Modérée | Q39: La notoriété reste limitée et la présence numérique est faible ou irrégulière. | R39: La faible exposition de l’entreprise pourrait contribuer directement à son rayonnement limité. | S39: Comment de nouveaux prospects qui ne vous connaissent pas découvrent-ils actuellement l’entreprise ? | T39: =IF(AND(OR(COUNTIF('Simulateur'!$D$40:$D$46,"R1A")>0,COUNTIF('Simulateur'!$D$40:$D$46,"R1B")>0),OR(COUNTIF('Simulateur'!$D$40:$D$46,"R5A")>0,COUNTIF('Simulateur'!$D$40:$D$46,"R5B")>0)),"Oui","") | U39: =IF(T39="Oui",O39*1000-ROW(),0)
A40: Mode d’emploi commercial | M40: RC11 | N40: Lecture du marché et différence peu claires | O40: 3 | P40: Élevée | Q40: L’entreprise comprend peu les choix en faveur des concurrents et sa différence reste difficile à percevoir sans explication. | R40: La proposition de valeur pourrait être construite sans suffisamment de retours du marché. | S40: Quelles raisons vos prospects donnent-ils lorsqu’ils choisissent une autre offre ? | T40: =IF(AND(OR(COUNTIF('Simulateur'!$D$40:$D$46,"R2A")>0,COUNTIF('Simulateur'!$D$40:$D$46,"R2B")>0),OR(COUNTIF('Simulateur'!$D$40:$D$46,"R4A")>0,COUNTIF('Simulateur'!$D$40:$D$46,"R4B")>0)),"Oui","") | U40: =IF(T40="Oui",O40*1000-ROW(),0)
A41: 1. Partir du constat factuel et reprendre la réponse exacte du prospect. | M41: RC12 | N41: Différence peu convertie | O41: 2 | P41: Modérée | Q41: La différence est visible ou reconnue, mais sa transformation en ventes numériques mesurées n’est pas établie. | R41: La difficulté pourrait se situer dans la transformation de la différence en action commerciale. | S41: Quel appel à l’action permet aujourd’hui à un prospect convaincu de passer à l’étape suivante ? | T41: =IF(AND(OR(COUNTIF('Simulateur'!$D$40:$D$46,"R4C")>0,COUNTIF('Simulateur'!$D$40:$D$46,"R4D")>0),OR(COUNTIF('Simulateur'!$D$40:$D$46,"R6A")>0,COUNTIF('Simulateur'!$D$40:$D$46,"R6B")>0,COUNTIF('Simulateur'!$D$40:$D$46,"R6C")>0)),"Oui","") | U41: =IF(T41="Oui",O41*1000-ROW(),0)
A42: 2. Utiliser la difficulté comme angle d’exploration, en demandant un exemple récent et son impact. | M42: RC13 | N42: Besoin de visibilité de trésorerie confirmé | O42: 3 | P42: Élevée | Q42: Le manque de visibilité sur la trésorerie apparaît dans la pratique et dans le progrès prioritaire déclaré. | R42: Le besoin est cohérent et mérite d’être quantifié pendant l’échange. | S42: Quelles décisions sont aujourd’hui retardées par ce manque de visibilité ? | T42: =IF(AND(OR(COUNTIF('Simulateur'!$D$10:$D$23,"Q7C")>0,COUNTIF('Simulateur'!$D$10:$D$23,"Q7D")>0),COUNTIF('Simulateur'!$D$10:$D$23,"Q14A")>0),"Oui","") | U42: =IF(T42="Oui",O42*1000-ROW(),0)
A43: 3. Formuler les hypothèses sous forme de questions ; ne conclure ni sur le besoin ni sur une offre avant l’échange. | M43: RC14 | N43: Besoin de traçabilité confirmé | O43: 3 | P43: Élevée | Q43: La difficulté à expliquer ou retrouver les mouvements est cohérente avec le besoin prioritaire déclaré. | R43: La traçabilité constitue probablement un enjeu central du prospect. | S43: Quels mouvements de fonds vous préoccupent le plus aujourd’hui ? | T43: =IF(AND(OR(COUNTIF('Simulateur'!$D$10:$D$23,"Q5C")>0,COUNTIF('Simulateur'!$D$10:$D$23,"Q5D")>0,COUNTIF('Simulateur'!$D$10:$D$23,"Q12C")>0,COUNTIF('Simulateur'!$D$10:$D$23,"Q12D")>0),COUNTIF('Simulateur'!$D$10:$D$23,"Q14B")>0),"Oui","") | U43: =IF(T43="Oui",O43*1000-ROW(),0)
M44: RC15 | N44: Besoin d’encaissement omnicanal confirmé | O44: 2 | P44: Modérée | Q44: Les limites actuelles d’encaissement concordent avec la volonté d’encaisser sur tous les canaux. | R44: Le besoin d’élargir ou unifier les parcours d’encaissement paraît cohérent. | S44: Sur quel canal perdez-vous actuellement le plus de ventes au moment du paiement ? | T44: =IF(AND(OR(COUNTIF('Simulateur'!$D$10:$D$23,"Q10C")>0,COUNTIF('Simulateur'!$D$10:$D$23,"Q10D")>0,COUNTIF('Simulateur'!$D$10:$D$23,"Q6B")>0,COUNTIF('Simulateur'!$D$10:$D$23,"Q6C")>0,COUNTIF('Simulateur'!$D$10:$D$23,"Q6D")>0),COUNTIF('Simulateur'!$D$10:$D$23,"Q14C")>0),"Oui","") | U44: =IF(T44="Oui",O44*1000-ROW(),0)
M45: RC16 | N45: Besoin de contrôle dans la délégation confirmé | O45: 3 | P45: Élevée | Q45: La manière actuelle de suivre les collaborateurs concorde avec le besoin de déléguer sans perdre le contrôle. | R45: La sécurisation de la délégation semble être un enjeu concret. | S45: Quel contrôle aimeriez-vous conserver lorsque d’autres personnes encaissent ? | T45: =IF(AND(OR(COUNTIF('Simulateur'!$D$10:$D$23,"Q9B")>0,COUNTIF('Simulateur'!$D$10:$D$23,"Q9C")>0),COUNTIF('Simulateur'!$D$10:$D$23,"Q14D")>0),"Oui","") | U45: =IF(T45="Oui",O45*1000-ROW(),0)

Sheet Dirigeant - Matrice
A1: Parcours Profil du dirigeant — matrice option par option
A2: Lecture publique équilibrée sur 8 dimensions • Lecture interne FeexPay sur 8 indicateurs opérationnels • Les tags n’entrent pas dans le score de pilotage.
A4: Code | B4: N° | C4: Question validée | D4: Option validée | E4: Dim. +2 | F4: Pts | G4: Dim. +1 | H4: Pts | I4: Dimension de qualification | J4: Points /3 | K4: Poids | L4: Applicable | M4: Tag 1 | N4: Valeur 1 | O4: Tag 2 | P4: Valeur 2 | Q4: Justification
A5: Q1A | B5: 1 | C5: Une nouvelle opportunité se présente. Qu’est-ce qui vous pousse le plus à avancer ? | D5: Je me projette d’abord sur ce qu’elle pourrait apporter à mon entreprise. | E5: VIS | F5: 2 | G5: AUD | H5: 1 | K5: 0 | L5: 0 | M5: Moteur de décision | N5: Projection | Q5: Lecture publique : VIS en dimension principale et AUD en nuance. Lecture interne : tag de qualification uniquement.
A6: Q1B | B6: 1 | C6: Une nouvelle opportunité se présente. Qu’est-ce qui vous pousse le plus à avancer ? | D6: Je vérifie les chiffres avant de décider si elle mérite mon investissement. | E6: STR | F6: 2 | G6: AUD | H6: 1 | K6: 0 | L6: 0 | M6: Moteur de décision | N6: Chiffres | Q6: Lecture publique : STR en dimension principale et AUD en nuance. Lecture interne : tag de qualification uniquement.
A7: Q1C | B7: 1 | C7: Une nouvelle opportunité se présente. Qu’est-ce qui vous pousse le plus à avancer ? | D7: J’observe si elle répond à une demande réelle de mes clients. | E7: INF | F7: 2 | G7: ADA | H7: 1 | K7: 0 | L7: 0 | M7: Moteur de décision | N7: Demande client | Q7: Lecture publique : INF en dimension principale et ADA en nuance. Lecture interne : tag de qualification uniquement.
A8: Q1D | B8: 1 | C8: Une nouvelle opportunité se présente. Qu’est-ce qui vous pousse le plus à avancer ? | D8: Je préfère la tester à petite échelle avant de m’engager davantage. | E8: AUD | F8: 2 | G8: VIS | H8: 1 | K8: 0 | L8: 0 | M8: Moteur de décision | N8: Test limité | Q8: Lecture publique : AUD en dimension principale et VIS en nuance. Lecture interne : tag de qualification uniquement.
A9: Q2A | B9: 2 | C9: Vos ventes augmentent brusquement. Quelle devient votre première priorité ? | D9: Je cherche d’abord à sécuriser les nouveaux encaissements. | E9: ORG | F9: 2 | G9: TRA | H9: 1 | K9: 0 | L9: 0 | M9: Priorité en croissance | N9: Sécuriser les encaissements | Q9: Lecture publique : ORG en dimension principale et TRA en nuance. Lecture interne : tag de qualification uniquement.
A10: Q2B | B10: 2 | C10: Vos ventes augmentent brusquement. Quelle devient votre première priorité ? | D10: Je m’assure que mon organisation peut absorber cette augmentation. | E10: TRA | F10: 2 | G10: INF | H10: 1 | K10: 0 | L10: 0 | M10: Priorité en croissance | N10: Structurer les opérations | Q10: Lecture publique : TRA en dimension principale et INF en nuance. Lecture interne : tag de qualification uniquement.
A11: Q2C | B11: 2 | C11: Vos ventes augmentent brusquement. Quelle devient votre première priorité ? | D11: Je veille surtout à maintenir une bonne expérience pour mes clients. | E11: INF | F11: 2 | G11: VIS | H11: 1 | K11: 0 | L11: 0 | M11: Priorité en croissance | N11: Préserver l’expérience client | Q11: Lecture publique : INF en dimension principale et VIS en nuance. Lecture interne : tag de qualification uniquement.
A12: Q2D | B12: 2 | C12: Vos ventes augmentent brusquement. Quelle devient votre première priorité ? | D12: Je prépare immédiatement la prochaine étape de développement. | E12: VIS | F12: 2 | G12: AUD | H12: 1 | K12: 0 | L12: 0 | M12: Priorité en croissance | N12: Accélérer le développement | Q12: Lecture publique : VIS en dimension principale et AUD en nuance. Lecture interne : tag de qualification uniquement.
A13: Q3A | B13: 3 | C13: Vous devez prendre une décision sans avoir toutes les informations. Que faites-vous ? | D13: Je m’appuie sur mon expérience pour choisir la direction qui me paraît juste. | E13: AUD | F13: 2 | G13: VIS | H13: 1 | K13: 0 | L13: 0 | M13: Style de décision | N13: Expérience | Q13: Lecture publique : AUD en dimension principale et VIS en nuance. Lecture interne : tag de qualification uniquement.
A14: Q3B | B14: 3 | C14: Vous devez prendre une décision sans avoir toutes les informations. Que faites-vous ? | D14: Je préfère attendre d’avoir des données plus fiables avant de me prononcer. | E14: STR | F14: 2 | G14: ORG | H14: 1 | K14: 0 | L14: 0 | M14: Style de décision | N14: Données | Q14: Lecture publique : STR en dimension principale et ORG en nuance. Lecture interne : tag de qualification uniquement.
A15: Q3C | B15: 3 | C15: Vous devez prendre une décision sans avoir toutes les informations. Que faites-vous ? | D15: Je demande l’avis de personnes capables de compléter ma lecture. | E15: INF | F15: 2 | G15: STR | H15: 1 | K15: 0 | L15: 0 | M15: Style de décision | N15: Consultation | Q15: Lecture publique : INF en dimension principale et STR en nuance. Lecture interne : tag de qualification uniquement.
A16: Q3D | B16: 3 | C16: Vous devez prendre une décision sans avoir toutes les informations. Que faites-vous ? | D16: Je lance un test limité pour observer ce qui fonctionne réellement. | E16: AUD | F16: 2 | G16: EXE | H16: 1 | K16: 0 | L16: 0 | M16: Style de décision | N16: Expérimentation | Q16: Lecture publique : AUD en dimension principale et EXE en nuance. Lecture interne : tag de qualification uniquement.
A17: Q4A | B17: 4 | C17: Comment suivez-vous généralement les ventes réalisées au cours d’une semaine ? | D17: Je consulte régulièrement un outil qui centralise toutes mes ventes. | E17: TRA | F17: 2 | G17: STR | H17: 1 | I17: Suivi des ventes | J17: 3 | K17: 10 | L17: 1 | M17: Mode opérationnel | N17: Outil centralisé | Q17: Lecture publique : TRA en dimension principale et STR en nuance. Lecture interne : Suivi des ventes.
A18: Q4B | B18: 4 | C18: Comment suivez-vous généralement les ventes réalisées au cours d’une semaine ? | D18: Je note les ventes dans un fichier ou un cahier lorsque j’en ai le temps. | E18: EXE | F18: 2 | G18: ORG | H18: 1 | I18: Suivi des ventes | J18: 2 | K18: 10 | L18: 1 | M18: Mode opérationnel | N18: Fichier ou cahier irrégulier | Q18: Lecture publique : EXE en dimension principale et ORG en nuance. Lecture interne : Suivi des ventes.
A19: Q4C | B19: 4 | C19: Comment suivez-vous généralement les ventes réalisées au cours d’une semaine ? | D19: Je reconstitue les ventes à partir des messages et des paiements reçus. | E19: ADA | F19: 2 | G19: EXE | H19: 1 | I19: Suivi des ventes | J19: 1 | K19: 10 | L19: 1 | M19: Mode opérationnel | N19: Reconstitution manuelle | Q19: Lecture publique : ADA en dimension principale et EXE en nuance. Lecture interne : Suivi des ventes.
A20: Q4D | B20: 4 | C20: Comment suivez-vous généralement les ventes réalisées au cours d’une semaine ? | D20: Je me fie surtout à ce que j’ai vendu et à l’argent encore disponible. | E20: AUD | F20: 2 | G20: ADA | H20: 1 | I20: Suivi des ventes | J20: 0 | K20: 10 | L20: 1 | M20: Mode opérationnel | N20: Estimation informelle | Q20: Lecture publique : AUD en dimension principale et ADA en nuance. Lecture interne : Suivi des ventes.
A21: Q5A | B21: 5 | C21: Le montant encaissé ne correspond pas aux ventes réalisées. Quel est votre premier réflexe ? | D21: Je consulte l’historique des transactions pour retrouver l’origine de l’écart. | E21: STR | F21: 2 | G21: TRA | H21: 1 | I21: Gestion des écarts | J21: 3 | K21: 15 | L21: 1 | M21: Mode opérationnel | N21: Historique transactionnel | Q21: Lecture publique : STR en dimension principale et TRA en nuance. Lecture interne : Gestion des écarts.
A22: Q5B | B22: 5 | C22: Le montant encaissé ne correspond pas aux ventes réalisées. Quel est votre premier réflexe ? | D22: Je reprends mon registre de ventes pour identifier ce qui manque. | E22: ORG | F22: 2 | G22: EXE | H22: 1 | I22: Gestion des écarts | J22: 2 | K22: 15 | L22: 1 | M22: Mode opérationnel | N22: Registre de ventes | Q22: Lecture publique : ORG en dimension principale et EXE en nuance. Lecture interne : Gestion des écarts.
A23: Q5C | B23: 5 | C23: Le montant encaissé ne correspond pas aux ventes réalisées. Quel est votre premier réflexe ? | D23: Je demande des explications aux personnes qui ont encaissé. | E23: INF | F23: 2 | G23: EXE | H23: 1 | I23: Gestion des écarts | J23: 1 | K23: 15 | L23: 1 | M23: Mode opérationnel | N23: Explication de l’équipe | Q23: Lecture publique : INF en dimension principale et EXE en nuance. Lecture interne : Gestion des écarts.
A24: Q5D | B24: 5 | C24: Le montant encaissé ne correspond pas aux ventes réalisées. Quel est votre premier réflexe ? | D24: Je n’ai pas toujours les éléments nécessaires pour expliquer immédiatement l’écart. | E24: ADA | F24: 2 | G24: AUD | H24: 1 | I24: Gestion des écarts | J24: 0 | K24: 15 | L24: 1 | M24: Mode opérationnel | N24: Écart difficile à expliquer | Q24: Lecture publique : ADA en dimension principale et AUD en nuance. Lecture interne : Gestion des écarts.
A25: Q6A | B25: 6 | C25: Vos clients utilisent plusieurs moyens de paiement. Comment gardez-vous une vue d’ensemble ? | D25: Je consulte un tableau de bord qui regroupe tous les paiements reçus. | E25: TRA | F25: 2 | G25: STR | H25: 1 | I25: Centralisation des paiements | J25: 3 | K25: 15 | L25: 1 | M25: Mode opérationnel | N25: Tableau de bord unique | Q25: Lecture publique : TRA en dimension principale et STR en nuance. Lecture interne : Centralisation des paiements.
A26: Q6B | B26: 6 | C26: Vos clients utilisent plusieurs moyens de paiement. Comment gardez-vous une vue d’ensemble ? | D26: Je vérifie séparément le solde de chaque moyen de paiement. | E26: STR | F26: 2 | G26: ORG | H26: 1 | I26: Centralisation des paiements | J26: 2 | K26: 15 | L26: 1 | M26: Mode opérationnel | N26: Consultation séparée | Q26: Lecture publique : STR en dimension principale et ORG en nuance. Lecture interne : Centralisation des paiements.
A27: Q6C | B27: 6 | C27: Vos clients utilisent plusieurs moyens de paiement. Comment gardez-vous une vue d’ensemble ? | D27: Je regroupe manuellement les différents montants à certains moments. | E27: EXE | F27: 2 | G27: ADA | H27: 1 | I27: Centralisation des paiements | J27: 1 | K27: 15 | L27: 1 | M27: Mode opérationnel | N27: Consolidation manuelle | Q27: Lecture publique : EXE en dimension principale et ADA en nuance. Lecture interne : Centralisation des paiements.
A28: Q6D | B28: 6 | C28: Vos clients utilisent plusieurs moyens de paiement. Comment gardez-vous une vue d’ensemble ? | D28: Je me base principalement sur les notifications reçues au fil des paiements. | E28: ADA | F28: 2 | G28: AUD | H28: 1 | I28: Centralisation des paiements | J28: 0 | K28: 15 | L28: 1 | M28: Mode opérationnel | N28: Suivi par notifications | Q28: Lecture publique : ADA en dimension principale et AUD en nuance. Lecture interne : Centralisation des paiements.
... A36: Q8D | B36: 8 | C36: Lorsque vient le moment de faire la comptabilité, dans quel état se trouvent vos informations ? | D36: Je dois souvent reconstituer certaines opérations après leur réalisation. | E36: ADA | F36: 2 | G36: AUD | H36: 1 | I36: Préparation comptable | J36: 0 | K36: 10 | L36: 1 | M36: Mode opérationnel | N36: Reconstitution après coup | Q36: Lecture publique : ADA en dimension principale et AUD en nuance. Lecture interne : Préparation comptable.
A37: Q9A | B37: 9 | C37: Lorsque d’autres personnes encaissent pour votre entreprise, comment suivez-vous leur activité ? | D37: Chaque encaissement peut être rattaché à une vente et à la personne concernée. | E37: ORG | F37: 2 | G37: INF | H37: 1 | I37: Contrôle des encaissements délégués | J37: 3 | K37: 10 | L37: 1 | M37: Mode opérationnel | N37: Traçabilité par personne | O37: Configuration d’encaissement | P37: Équipe | Q37: Lecture publique : ORG en dimension principale et INF en nuance. Lecture interne : Contrôle des encaissements délégués.
A38: Q9B | B38: 9 | C38: Lorsque d’autres personnes encaissent pour votre entreprise, comment suivez-vous leur activité ? | D38: Les personnes concernées enregistrent leurs encaissements dans un support commun. | E38: EXE | F38: 2 | G38: INF | H38: 1 | I38: Contrôle des encaissements délégués | J38: 2 | K38: 10 | L38: 1 | M38: Mode opérationnel | N38: Support commun | O38: Configuration d’encaissement | P38: Équipe | Q38: Lecture publique : EXE en dimension principale et INF en nuance. Lecture interne : Contrôle des encaissements délégués.
A39: Q9C | B39: 9 | C39: Lorsque d’autres personnes encaissent pour votre entreprise, comment suivez-vous leur activité ? | D39: Je reçois principalement un point oral ou un montant global en fin de journée. | E39: INF | F39: 2 | G39: ADA | H39: 1 | I39: Contrôle des encaissements délégués | J39: 1 | K39: 10 | L39: 1 | M39: Mode opérationnel | N39: Point oral ou global | O39: Configuration d’encaissement | P39: Équipe | Q39: Lecture publique : INF en dimension principale et ADA en nuance. Lecture interne : Contrôle des encaissements délégués.
A40: Q9D | B40: 9 | C40: Lorsque d’autres personnes encaissent pour votre entreprise, comment suivez-vous leur activité ? | D40: Pour le moment, je suis la seule personne à encaisser dans mon entreprise. | E40: AUD | F40: 2 | G40: EXE | H40: 1 | I40: Contrôle des encaissements délégués | K40: 10 | L40: 0 | M40: Mode opérationnel | N40: Encaissement en solo | O40: Configuration d’encaissement | P40: Solo | Q40: Lecture publique : AUD en dimension principale et EXE en nuance. Lecture interne : Contrôle des encaissements délégués.
A41: Q10A | B41: 10 | C41: Lorsqu’un client souhaite vous payer à distance, comment procédez-vous généralement ? | D41: Je lui transmets un lien ou une page de paiement prévue à cet effet. | E41: TRA | F41: 2 | G41: INF | H41: 1 | I41: Paiement à distance | J41: 3 | K41: 10 | L41: 1 | M41: Mode opérationnel | N41: Lien ou page de paiement | Q41: Lecture publique : TRA en dimension principale et INF en nuance. Lecture interne : Paiement à distance.
A42: Q10B | B42: 10 | C42: Lorsqu’un client souhaite vous payer à distance, comment procédez-vous généralement ? | D42: Je lui communique un numéro après avoir échangé avec lui. | E42: ADA | F42: 2 | G42: INF | H42: 1 | I42: Paiement à distance | J42: 2 | K42: 10 | L42: 1 | M42: Mode opérationnel | N42: Numéro communiqué | Q42: Lecture publique : ADA en dimension principale et INF en nuance. Lecture interne : Paiement à distance.
A43: Q10C | B43: 10 | C43: Lorsqu’un client souhaite vous payer à distance, comment procédez-vous généralement ? | D43: Je privilégie encore le paiement à la livraison ou lors d’une rencontre. | E43: ORG | F43: 2 | G43: ADA | H43: 1 | I43: Paiement à distance | J43: 1 | K43: 10 | L43: 1 | M43: Mode opérationnel | N43: Paiement à la livraison | Q43: Lecture publique : ORG en dimension principale et ADA en nuance. Lecture interne : Paiement à distance.
A44: Q10D | B44: 10 | C44: Lorsqu’un client souhaite vous payer à distance, comment procédez-vous généralement ? | D44: Je ne propose pas encore de moyen de paiement à distance. | E44: ORG | F44: 2 | G44: TRA | H44: 1 | I44: Paiement à distance | J44: 0 | K44: 10 | L44: 1 | M44: Mode opérationnel | N44: Aucune solution à distance | Q44: Lecture publique : ORG en dimension principale et TRA en nuance. Lecture interne : Paiement à distance.
A45: Q11A | B45: 11 | C45: Quelle place le digital occupe-t-il actuellement dans vos ventes ? | D45: Mon site permet aux clients de commander et de payer directement. | E45: VIS | F45: 2 | G45: TRA | H45: 1 | K45: 0 | L45: 0 | M45: Canal de vente | N45: E-commerce intégré | O45: Niveau digital | P45: Transactionnel | Q45: Lecture publique : VIS en dimension principale et TRA en nuance. Lecture interne : tag de qualification uniquement.
A46: Q11B | B46: 11 | C46: Quelle place le digital occupe-t-il actuellement dans vos ventes ? | D46: Mon site présente mes offres, mais les commandes se finalisent ailleurs. | E46: TRA | F46: 2 | G46: VIS | H46: 1 | K46: 0 | L46: 0 | M46: Canal de vente | N46: Site vitrine | O46: Niveau digital | P46: Non transactionnel | Q46: Lecture publique : TRA en dimension principale et VIS en nuance. Lecture interne : tag de qualification uniquement.
A47: Q11C | B47: 11 | C47: Quelle place le digital occupe-t-il actuellement dans vos ventes ? | D47: Je vends principalement à travers les réseaux sociaux et les messageries. | E47: ADA | F47: 2 | G47: INF | H47: 1 | K47: 0 | L47: 0 | M47: Canal de vente | N47: Social commerce | O47: Niveau digital | P47: Conversationnel | Q47: Lecture publique : ADA en dimension principale et INF en nuance. Lecture interne : tag de qualification uniquement.
A48: Q11D | B48: 11 | C48: Quelle place le digital occupe-t-il actuellement dans vos ventes ? | D48: Mes ventes se font encore essentiellement en présentiel. | E48: EXE | F48: 2 | G48: ORG | H48: 1 | K48: 0 | L48: 0 | M48: Canal de vente | N48: Présentiel | O48: Niveau digital | P48: Physique | Q48: Lecture publique : EXE en dimension principale et ORG en nuance. Lecture interne : tag de qualification uniquement.
A49: Q12A | B49: 12 | C49: Un client affirme avoir payé, mais vous ne retrouvez pas immédiatement son paiement. Que faites-vous ? | D49: Je recherche la transaction à partir de sa référence. | E49: STR | F49: 2 | G49: TRA | H49: 1 | I49: Recherche d’un paiement | J49: 3 | K49: 15 | L49: 1 | M49: Mode opérationnel | N49: Recherche par référence | Q49: Lecture publique : STR en dimension principale et TRA en nuance. Lecture interne : Recherche d’un paiement.
A50: Q12B | B50: 12 | C50: Un client affirme avoir payé, mais vous ne retrouvez pas immédiatement son paiement. Que faites-vous ? | D50: Je lui demande une preuve de paiement pour poursuivre la vérification. | E50: INF | F50: 2 | G50: STR | H50: 1 | I50: Recherche d’un paiement | J50: 2 | K50: 15 | L50: 1 | M50: Mode opérationnel | N50: Preuve demandée au client | Q50: Lecture publique : INF en dimension principale et STR en nuance. Lecture interne : Recherche d’un paiement.
A51: Q12C | B51: 12 | C51: Un client affirme avoir payé, mais vous ne retrouvez pas immédiatement son paiement. Que faites-vous ? | D51: Je consulte mes différents soldes pour voir si le montant apparaît. | E51: EXE | F51: 2 | G51: STR | H51: 1 | I51: Recherche d’un paiement | J51: 1 | K51: 15 | L51: 1 | M51: Mode opérationnel | N51: Vérification des soldes | Q51: Lecture publique : EXE en dimension principale et STR en nuance. Lecture interne : Recherche d’un paiement.
A52: Q12D | B52: 12 | C52: Un client affirme avoir payé, mais vous ne retrouvez pas immédiatement son paiement. Que faites-vous ? | D52: J’attends la notification ou la confirmation de mon opérateur de paiement. | E52: ORG | F52: 2 | G52: ADA | H52: 1 | I52: Recherche d’un paiement | J52: 0 | K52: 15 | L52: 1 | M52: Mode opérationnel | N52: Attente de confirmation | Q52: Lecture publique : ORG en dimension principale et ADA en nuance. Lecture interne : Recherche d’un paiement.
A53: Q13A | B53: 13 | C53: Avant d’adopter un nouvel outil pour votre entreprise, qu’est-ce qui compte le plus pour vous ? | D53: Je veux savoir s’il peut s’intégrer facilement à mon fonctionnement actuel. | E53: TRA | F53: 2 | G53: VIS | H53: 1 | K53: 0 | L53: 0 | M53: Déclencheur d’adoption | N53: Intégration | O53: Disposition au changement | P53: Ouvert sous condition | Q53: Lecture publique : TRA en dimension principale et VIS en nuance. Lecture interne : tag de qualification uniquement.
A54: Q13B | B54: 13 | C54: Avant d’adopter un nouvel outil pour votre entreprise, qu’est-ce qui compte le plus pour vous ? | D54: Je veux vérifier s’il me permettra de gagner du temps dans le suivi. | E54: EXE | F54: 2 | G54: STR | H54: 1 | K54: 0 | L54: 0 | M54: Déclencheur d’adoption | N54: Gain de temps | O54: Disposition au changement | P54: Ouvert sous condition | Q54: Lecture publique : EXE en dimension principale et STR en nuance. Lecture interne : tag de qualification uniquement.
A55: Q13C | B55: 13 | C55: Avant d’adopter un nouvel outil pour votre entreprise, qu’est-ce qui compte le plus pour vous ? | D55: Je veux m’assurer que mon équipe pourra l’utiliser sans difficulté. | E55: INF | F55: 2 | G55: ORG | H55: 1 | K55: 0 | L55: 0 | M55: Déclencheur d’adoption | N55: Facilité pour l’équipe | O55: Disposition au changement | P55: Ouvert sous condition | Q55: Lecture publique : INF en dimension principale et ORG en nuance. Lecture interne : tag de qualification uniquement.
A56: Q13D | B56: 13 | C56: Avant d’adopter un nouvel outil pour votre entreprise, qu’est-ce qui compte le plus pour vous ? | D56: Je préfère attendre que le besoin devienne vraiment urgent avant de changer. | E56: STR | F56: 2 | G56: ORG | H56: 1 | K56: 0 | L56: 0 | M56: Déclencheur d’adoption | N56: Urgence | O56: Disposition au changement | P56: Attentiste | Q56: Lecture publique : STR en dimension principale et ORG en nuance. Lecture interne : tag de qualification uniquement.
A57: Q14A | B57: 14 | C57: Dans un an, quel progrès vous donnerait le plus le sentiment de mieux piloter votre entreprise ? | D57: Je pourrais connaître l’état de ma trésorerie sans attendre la fin du mois. | E57: VIS | F57: 2 | G57: TRA | H57: 1 | K57: 0 | L57: 0 | M57: Besoin prioritaire | N57: Visibilité sur la trésorerie | O57: Produit FeexPay | P57: Dashboard et reporting | Q57: Lecture publique : VIS en dimension principale et TRA en nuance. Lecture interne : tag de qualification uniquement.
A58: Q14B | B58: 14 | C58: Dans un an, quel progrès vous donnerait le plus le sentiment de mieux piloter votre entreprise ? | D58: Je pourrais retrouver facilement l’origine de chaque mouvement de fonds. | E58: VIS | F58: 2 | G58: TRA | H58: 1 | K58: 0 | L58: 0 | M58: Besoin prioritaire | N58: Traçabilité des fonds | O58: Produit FeexPay | P58: Historique et rapprochement | Q58: Lecture publique : VIS en dimension principale et TRA en nuance. Lecture interne : tag de qualification uniquement.
A59: Q14C | B59: 14 | C59: Dans un an, quel progrès vous donnerait le plus le sentiment de mieux piloter votre entreprise ? | D59: Je pourrais encaisser mes clients sur tous mes canaux de vente. | E59: VIS | F59: 2 | G59: AUD | H59: 1 | K59: 0 | L59: 0 | M59: Besoin prioritaire | N59: Encaissement omnicanal | O59: Produit FeexPay | P59: Lien, QR et intégration | Q59: Lecture publique : VIS en dimension principale et AUD en nuance. Lecture interne : tag de qualification uniquement.
A60: Q14D | B60: 14 | C60: Dans un an, quel progrès vous donnerait le plus le sentiment de mieux piloter votre entreprise ? | D60: Je pourrais déléguer davantage sans perdre le contrôle de mon activité. | E60: VIS | F60: 2 | G60: INF | H60: 1 | K60: 0 | L60: 0 | M60: Besoin prioritaire | N60: Délégation et contrôle | O60: Produit FeexPay | P60: Gestion des collaborateurs | Q60: Lecture publique : VIS en dimension principale et INF en nuance. Lecture interne : tag de qualification uniquement.

Sheet Rayonnement - Matrice
A1: Parcours Rayonnement — matrice option par option
A2: Six questions progressives scorées de 0 à 3. La question 3 identifie la nature de la différenciation et ne crée aucune hiérarchie entre les réponses.
A4: Code | B4: N° | C4: Question validée | D4: Option validée | E4: Dimension | F4: Points | G4: Maximum | H4: Tag | I4: Valeur | J4: Règle d’interprétation
A5: R1A | B5: 1 | C5: En dehors de vos clients actuels, jusqu’où votre entreprise est-elle connue ? | D5: Elle est principalement connue par mon entourage et mes contacts directs. | E5: Notoriété | F5: 0 | G5: 3 | H5: Niveau déclaré | I5: Faible | J5: Échelle progressive 0/3.
A6: R1B | B6: 1 | C6: En dehors de vos clients actuels, jusqu’où votre entreprise est-elle connue ? | D6: Elle commence à être connue par des personnes situées dans ma zone. | E6: Notoriété | F6: 1 | G6: 3 | H6: Niveau déclaré | I6: Émergent | J6: Échelle progressive 1/3.
A7: R1C | B7: 1 | C7: En dehors de vos clients actuels, jusqu’où votre entreprise est-elle connue ? | D7: Elle est régulièrement identifiée par des prospects de mon secteur. | E7: Notoriété | F7: 2 | G7: 3 | H7: Niveau déclaré | I7: Installé | J7: Échelle progressive 2/3.
A8: R1D | B8: 1 | C8: En dehors de vos clients actuels, jusqu’où votre entreprise est-elle connue ? | D8: Elle est reconnue par une partie importante du marché que je vise. | E8: Notoriété | F8: 3 | G8: 3 | H8: Niveau déclaré | I8: Fort | J8: Échelle progressive 3/3.
A9: R2A | B9: 2 | C9: Lorsqu’un prospect choisit un concurrent, savez-vous généralement pourquoi ? | D9: Je reçois rarement des informations sur les raisons de son choix. | E9: Lecture concurrentielle | F9: 0 | G9: 3 | H9: Niveau déclaré | I9: Faible | J9: Échelle progressive 0/3.
A10: R2B | B10: 2 | C10: Lorsqu’un prospect choisit un concurrent, savez-vous généralement pourquoi ? | D10: J’essaie de comprendre sa décision à partir de ce que j’observe. | E10: Lecture concurrentielle | F10: 1 | G10: 3 | H10: Niveau déclaré | I10: Émergent | J10: Échelle progressive 1/3.
A11: R2C | B11: 2 | C11: Lorsqu’un prospect choisit un concurrent, savez-vous généralement pourquoi ? | D11: Il m’arrive de lui demander ce qui a motivé son choix. | E11: Lecture concurrentielle | F11: 2 | G11: 3 | H11: Niveau déclaré | I11: Installé | J11: Échelle progressive 2/3.
A12: R2D | B12: 2 | C12: Lorsqu’un prospect choisit un concurrent, savez-vous généralement pourquoi ? | D12: Je recueille régulièrement ces raisons pour mieux comprendre mon marché. | E12: Lecture concurrentielle | F12: 3 | G12: 3 | H12: Niveau déclaré | I12: Fort | J12: Échelle progressive 3/3.
A13: R3A | B13: 3 | C13: Pour quelle raison vos clients vous choisissent-ils principalement ? | D13: Ils viennent souvent vers moi parce que mes prix leur conviennent. | E13: Tag de différenciation | G13: 3 | H13: Nature de la différenciation | I13: Prix | J13: Tag uniquement : aucune hiérarchie entre prix, proximité, qualité et avantage distinctif.
A14: R3B | B14: 3 | C14: Pour quelle raison vos clients vous choisissent-ils principalement ? | D14: Ils me choisissent parce que je suis proche d’eux et facilement accessible. | E14: Tag de différenciation | G14: 3 | H14: Nature de la différenciation | I14: Proximité | J14: Tag uniquement : aucune hiérarchie entre prix, proximité, qualité et avantage distinctif.
A15: R3C | B15: 3 | C15: Pour quelle raison vos clients vous choisissent-ils principalement ? | D15: Ils reviennent parce qu’ils font confiance à la qualité de ce que je propose. | E15: Tag de différenciation | G15: 3 | H15: Nature de la différenciation | I15: Qualité | J15: Tag uniquement : aucune hiérarchie entre prix, proximité, qualité et avantage distinctif.
A16: R3D | B16: 3 | C16: Pour quelle raison vos clients vous choisissent-ils principalement ? | D16: Ils trouvent chez moi un avantage qu’ils retrouvent difficilement ailleurs. | E16: Tag de différenciation | G16: 3 | H16: Nature de la différenciation | I16: Avantage distinctif | J16: Tag uniquement : aucune hiérarchie entre prix, proximité, qualité et avantage distinctif.
A17: R4A | B17: 4 | C17: Une personne qui découvre votre entreprise comprend-elle facilement ce qui vous distingue ? | D17: Je ne saurais pas encore expliquer clairement ce qui me différencie. | E17: Différenciation | F17: 0 | G17: 3 | H17: Niveau déclaré | I17: Faible | J17: Échelle progressive 0/3.
A18: R4B | B18: 4 | C18: Une personne qui découvre votre entreprise comprend-elle facilement ce qui vous distingue ? | D18: J’arrive à l’expliquer lorsque je présente personnellement mon activité. | E18: Différenciation | F18: 1 | G18: 3 | H18: Niveau déclaré | I18: Émergent | J18: Échelle progressive 1/3.
A19: R4C | B19: 4 | C19: Une personne qui découvre votre entreprise comprend-elle facilement ce qui vous distingue ? | D19: Ma différence apparaît déjà dans mes offres et ma communication. | E19: Différenciation | F19: 2 | G19: 3 | H19: Niveau déclaré | I19: Installé | J19: Échelle progressive 2/3.
A20: R4D | B20: 4 | C20: Une personne qui découvre votre entreprise comprend-elle facilement ce qui vous distingue ? | D20: Mes clients citent spontanément ce qui rend mon entreprise particulière. | E20: Différenciation | F20: 3 | G20: 3 | H20: Niveau déclaré | I20: Fort | J20: Échelle progressive 3/3.
A21: R5A | B21: 5 | C21: Comment votre entreprise est-elle actuellement présente sur les canaux numériques ? | D21: Mon entreprise y est peu présente ou ne dispose pas encore de page active. | E21: Présence digitale | F21: 0 | G21: 3 | H21: Niveau déclaré | I21: Faible | J21: Échelle progressive 0/3.
A22: R5B | B22: 5 | C22: Comment votre entreprise est-elle actuellement présente sur les canaux numériques ? | D22: Je publie principalement lorsque j’ai une actualité ou du temps disponible. | E22: Présence digitale | F22: 1 | G22: 3 | H22: Niveau déclaré | I22: Émergent | J22: Échelle progressive 1/3.
A23: R5C | B23: 5 | C23: Comment votre entreprise est-elle actuellement présente sur les canaux numériques ? | D23: Je communique régulièrement sur le canal que j’utilise le plus. | E23: Présence digitale | F23: 2 | G23: 3 | H23: Niveau déclaré | I23: Installé | J23: Échelle progressive 2/3.
A24: R5D | B24: 5 | C24: Comment votre entreprise est-elle actuellement présente sur les canaux numériques ? | D24: Je maintiens une présence continue sur les canaux utiles à mon activité. | E24: Présence digitale | F24: 3 | G24: 3 | H24: Niveau déclaré | I24: Fort | J24: Échelle progressive 3/3.
A25: R6A | B25: 6 | C25: Que produit concrètement votre présence numérique pour votre entreprise ? | D25: Je ne mesure pas encore réellement ce qu’elle apporte à mon activité. | E25: Performance digitale | F25: 0 | G25: 3 | H25: Niveau déclaré | I25: Faible | J25: Échelle progressive 0/3.
A26: R6B | B26: 6 | C26: Que produit concrètement votre présence numérique pour votre entreprise ? | D26: Elle me permet surtout d’obtenir de la visibilité et des réactions. | E26: Performance digitale | F26: 1 | G26: 3 | H26: Niveau déclaré | I26: Émergent | J26: Échelle progressive 1/3.
A27: R6C | B27: 6 | C27: Que produit concrètement votre présence numérique pour votre entreprise ? | D27: Elle génère régulièrement des demandes d’information ou de devis. | E27: Performance digitale | F27: 2 | G27: 3 | H27: Niveau déclaré | I27: Installé | J27: Échelle progressive 2/3.
A28: R6D | B28: 6 | C28: Que produit concrètement votre présence numérique pour votre entreprise ? | D28: Je peux identifier des ventes directement issues de mes actions numériques. | E28: Performance digitale | F28: 3 | G28: 3 | H28: Niveau déclaré | I28: Fort | J28: Échelle progressive 3/3.
... A32: R7D | B32: 7 | C32: Si votre entreprise arrêtait ses activités demain, qui le remarquerait rapidement ? | D32: Une partie de mon marché constaterait clairement la disparition de mon offre. | E32: Empreinte dans l’écosystème | F32: 3 | G32: 3 | H32: Niveau déclaré | I32: Fort | J32: Échelle progressive 3/3.

Sheet Bibliothèque constats
A1: Bibliothèque de constats — lecture commerciale option par option
A2: Chaque option est traduite en fait déclaré, difficulté éventuelle et hypothèse à confirmer. Une hypothèse n’est jamais présentée comme un fait et aucune ligne ne recommande un produit.
A4: Code | B4: Parcours | C4: N° | D4: Question validée | E4: Option validée | F4: Dimension | G4: Nature | H4: Gravité | I4: Niveau | J4: Constat factuel | K4: Difficulté précise | L4: Hypothèse à approfondir | M4: Question de relance | N4: Utilisation commerciale
A5: Q1A | B5: Dirigeant | C5: 1 | D5: Une nouvelle opportunité se présente. Qu’est-ce qui vous pousse le plus à avancer ? | E5: Je me projette d’abord sur ce qu’elle pourrait apporter à mon entreprise. | F5: Décision | G5: Signal déclaré | H5: 0 | I5: Aucune alerte | J5: Le prospect se projette d’abord sur l’impact futur d’une opportunité. | L5: Sa décision semble sensible à la perspective de développement. | M5: Quels résultats attendez-vous généralement avant de considérer une opportunité comme intéressante ? | N5: Comprendre son moteur de décision.
A6: Q1B | B6: Dirigeant | C6: 1 | D6: Une nouvelle opportunité se présente. Qu’est-ce qui vous pousse le plus à avancer ? | E6: Je vérifie les chiffres avant de décider si elle mérite mon investissement. | F6: Décision | G6: Signal déclaré | H6: 0 | I6: Aucune alerte | J6: Le prospect examine les chiffres avant d’investir. | L6: Il cherchera probablement des éléments quantifiables avant d’avancer. | M6: Quels chiffres vous permettent aujourd’hui de juger qu’une décision est rentable ? | N6: Préparer un échange fondé sur des données.
A7: Q1C | B7: Dirigeant | C7: 1 | D7: Une nouvelle opportunité se présente. Qu’est-ce qui vous pousse le plus à avancer ? | E7: J’observe si elle répond à une demande réelle de mes clients. | F7: Décision | G7: Signal déclaré | H7: 0 | I7: Aucune alerte | J7: Le prospect observe d’abord la demande réelle de ses clients. | L7: La preuve par l’usage client semble déterminante dans ses choix. | M7: Comment recueillez-vous aujourd’hui les demandes ou objections de vos clients ? | N7: Comprendre la place du retour client.
A8: Q1D | B8: Dirigeant | C8: 1 | D8: Une nouvelle opportunité se présente. Qu’est-ce qui vous pousse le plus à avancer ? | E8: Je préfère la tester à petite échelle avant de m’engager davantage. | F8: Décision | G8: Signal déclaré | H8: 0 | I8: Aucune alerte | J8: Le prospect préfère tester une opportunité à petite échelle. | L8: Une démarche pilote peut faciliter son engagement. | M8: À quoi ressemble, pour vous, un test suffisamment concluant pour poursuivre ? | N8: Comprendre son mode d’expérimentation.
A9: Q2A | B9: Dirigeant | C9: 2 | D9: Vos ventes augmentent brusquement. Quelle devient votre première priorité ? | E9: Je cherche d’abord à sécuriser les nouveaux encaissements. | F9: Croissance | G9: Signal déclaré | H9: 0 | I9: Aucune alerte | J9: En période de croissance, sa priorité est de sécuriser les encaissements. | L9: Il associe l’augmentation des ventes à un risque opérationnel sur les paiements. | M9: Qu’est-ce qui devient le plus difficile à contrôler lorsque vos ventes augmentent ? | N9: Identifier les tensions créées par la croissance.
A10: Q2B | B10: Dirigeant | C10: 2 | D10: Vos ventes augmentent brusquement. Quelle devient votre première priorité ? | E10: Je m’assure que mon organisation peut absorber cette augmentation. | F10: Croissance | G10: Signal déclaré | H10: 0 | I10: Aucune alerte | J10: En période de croissance, sa priorité est la capacité de l’organisation à suivre. | L10: La charge opérationnelle peut constituer son principal frein à l’accélération. | M10: Quels processus sont les premiers à être débordés lorsque l’activité augmente ? | N10: Identifier les limites opérationnelles.
A11: Q2C | B11: Dirigeant | C11: 2 | D11: Vos ventes augmentent brusquement. Quelle devient votre première priorité ? | E11: Je veille surtout à maintenir une bonne expérience pour mes clients. | F11: Croissance | G11: Signal déclaré | H11: 0 | I11: Aucune alerte | J11: En période de croissance, sa priorité est de préserver l’expérience client. | L11: Il pourrait arbitrer les outils et processus selon leur impact sur le client. | M11: À quel moment l’augmentation des commandes commence-t-elle à affecter vos clients ? | N11: Identifier les frictions côté client.
A12: Q2D | B12: Dirigeant | C12: 2 | D12: Vos ventes augmentent brusquement. Quelle devient votre première priorité ? | E12: Je prépare immédiatement la prochaine étape de développement. | F12: Croissance | G12: Signal déclaré | H12: 0 | I12: Aucune alerte | J12: En période de croissance, sa priorité est de préparer l’étape suivante. | L12: Il peut être davantage orienté accélération que consolidation. | M12: Quels éléments doivent être sécurisés avant votre prochaine phase de développement ? | N12: Comprendre son rythme d’expansion.
A13: Q3A | B13: Dirigeant | C13: 3 | D13: Vous devez prendre une décision sans avoir toutes les informations. Que faites-vous ? | E13: Je m’appuie sur mon expérience pour choisir la direction qui me paraît juste. | F13: Décision | G13: Signal déclaré | H13: 0 | I13: Aucune alerte | J13: En situation d’incertitude, il s’appuie d’abord sur son expérience. | L13: Certaines décisions peuvent dépendre d’informations détenues principalement par le dirigeant. | M13: Quelles informations restent aujourd’hui difficiles à obtenir sans votre expérience personnelle ? | N13: Comprendre la dépendance au dirigeant.
A14: Q3B | B14: Dirigeant | C14: 3 | D14: Vous devez prendre une décision sans avoir toutes les informations. Que faites-vous ? | E14: Je préfère attendre d’avoir des données plus fiables avant de me prononcer. | F14: Décision | G14: Signal déclaré | H14: 0 | I14: Aucune alerte | J14: En situation d’incertitude, il attend des données plus fiables. | L14: L’accès ou la qualité des données peut ralentir certaines décisions. | M14: Quelles données vous manquent le plus souvent au moment de décider ? | N14: Identifier les données critiques.
A15: Q3C | B15: Dirigeant | C15: 3 | D15: Vous devez prendre une décision sans avoir toutes les informations. Que faites-vous ? | E15: Je demande l’avis de personnes capables de compléter ma lecture. | F15: Décision | G15: Signal déclaré | H15: 0 | I15: Aucune alerte | J15: En situation d’incertitude, il consulte des personnes capables de compléter sa lecture. | L15: La décision repose sur la disponibilité et la fiabilité de plusieurs interlocuteurs. | M15: Comment consolidez-vous les informations reçues de plusieurs personnes ? | N15: Comprendre la circulation de l’information.
A16: Q3D | B16: Dirigeant | C16: 3 | D16: Vous devez prendre une décision sans avoir toutes les informations. Que faites-vous ? | E16: Je lance un test limité pour observer ce qui fonctionne réellement. | F16: Décision | G16: Signal déclaré | H16: 0 | I16: Aucune alerte | J16: En situation d’incertitude, il lance un test limité. | L16: Il privilégie l’apprentissage par l’action. | M16: Comment mesurez-vous les résultats d’un test avant de généraliser ? | N16: Comprendre sa méthode de validation.
A17: Q4A | B17: Dirigeant | C17: 4 | D17: Comment suivez-vous généralement les ventes réalisées au cours d’une semaine ? | E17: Je consulte régulièrement un outil qui centralise toutes mes ventes. | F17: Suivi des ventes | G17: Force | H17: 0 | I17: Aucune alerte | J17: Les ventes sont suivies régulièrement dans un outil centralisé. | M17: Quelles informations consultez-vous le plus souvent dans cet outil ? | N17: Confirmer la qualité du suivi existant.
A18: Q4B | B18: Dirigeant | C18: 4 | D18: Comment suivez-vous généralement les ventes réalisées au cours d’une semaine ? | E18: Je note les ventes dans un fichier ou un cahier lorsque j’en ai le temps. | F18: Suivi des ventes | G18: Difficulté | H18: 2 | I18: Modérée | J18: Les ventes sont notées dans un fichier ou un cahier, mais sans rythme fixe. | K18: Le suivi des ventes est irrégulier. | L18: Certaines ventes peuvent être enregistrées tardivement ou être oubliées. | M18: À quelle fréquence ce fichier ou ce cahier est-il réellement mis à jour ? | N18: Qualifier la régularité du suivi.
A19: Q4C | B19: Dirigeant | C19: 4 | D19: Comment suivez-vous généralement les ventes réalisées au cours d’une semaine ? | E19: Je reconstitue les ventes à partir des messages et des paiements reçus. | F19: Suivi des ventes | G19: Difficulté | H19: 3 | I19: Élevée | J19: Les ventes sont reconstituées à partir des messages et des paiements reçus. | K19: Il n’existe pas de registre consolidé des ventes disponible immédiatement. | L19: Le chiffre d’affaires réel d’une période peut être difficile à établir rapidement. | M19: Combien de temps vous faut-il pour reconstituer une semaine complète de ventes ? | N19: Mesurer le coût de la reconstitution.
A20: Q4D | B20: Dirigeant | C20: 4 | D20: Comment suivez-vous généralement les ventes réalisées au cours d’une semaine ? | E20: Je me fie surtout à ce que j’ai vendu et à l’argent encore disponible. | F20: Suivi des ventes | G20: Difficulté | H20: 3 | I20: Élevée | J20: Le suivi repose principalement sur la mémoire des ventes et l’argent encore disponible. | K20: Les ventes ne sont pas suivies dans un système formalisé. | L20: Les ventes réalisées, les encaissements et la trésorerie disponible peuvent être confondus. | M20: Comment vérifiez-vous qu’aucune vente n’a été oubliée dans votre estimation ? | N20: Faire préciser la méthode réelle de suivi.
A21: Q5A | B21: Dirigeant | C21: 5 | D21: Le montant encaissé ne correspond pas aux ventes réalisées. Quel est votre premier réflexe ? | E21: Je consulte l’historique des transactions pour retrouver l’origine de l’écart. | F21: Écarts d’encaissement | G21: Force | H21: 0 | I21: Aucune alerte | J21: Un écart peut être recherché dans l’historique des transactions. | M21: Combien de temps faut-il généralement pour retrouver l’origine d’un écart ? | N21: Confirmer la profondeur de la traçabilité.
A22: Q5B | B22: Dirigeant | C22: 5 | D22: Le montant encaissé ne correspond pas aux ventes réalisées. Quel est votre premier réflexe ? | E22: Je reprends mon registre de ventes pour identifier ce qui manque. | F22: Écarts d’encaissement | G22: Difficulté | H22: 1 | I22: Légère | J22: L’écart est recherché manuellement dans le registre des ventes. | K22: L’explication des écarts dépend d’un rapprochement manuel. | L22: La recherche peut devenir lente lorsque le volume de ventes augmente. | M22: Quelles informations rapprochez-vous pour identifier ce qui manque ? | N22: Comprendre le rapprochement existant.
A23: Q5C | B23: Dirigeant | C23: 5 | D23: Le montant encaissé ne correspond pas aux ventes réalisées. Quel est votre premier réflexe ? | E23: Je demande des explications aux personnes qui ont encaissé. | F23: Écarts d’encaissement | G23: Difficulté | H23: 2 | I23: Modérée | J23: L’explication d’un écart dépend d’abord des personnes ayant encaissé. | K23: La traçabilité dépend des explications de l’équipe. | L23: Il peut être difficile de distinguer une erreur, un oubli ou un encaissement non déclaré. | M23: Quelles preuves pouvez-vous consulter lorsque les explications ne concordent pas ? | N23: Tester la traçabilité indépendante de l’équipe.
A24: Q5D | B24: Dirigeant | C24: 5 | D24: Le montant encaissé ne correspond pas aux ventes réalisées. Quel est votre premier réflexe ? | E24: Je n’ai pas toujours les éléments nécessaires pour expliquer immédiatement l’écart. | F24: Écarts d’encaissement | G24: Difficulté | H24: 3 | I24: Élevée | J24: Les éléments disponibles ne permettent pas d’expliquer immédiatement un écart. | K24: Certains écarts d’encaissement restent difficiles à retracer. | L24: Des ventes ou paiements peuvent rester sans explication fiable. | M24: Quel est le dernier écart que vous n’avez pas pu expliquer complètement ? | N24: Obtenir un exemple concret d’écart.
A25: Q6A | B25: Dirigeant | C25: 6 | D25: Vos clients utilisent plusieurs moyens de paiement. Comment gardez-vous une vue d’ensemble ? | E25: Je consulte un tableau de bord qui regroupe tous les paiements reçus. | F25: Centralisation des paiements | G25: Force | H25: 0 | I25: Aucune alerte | J25: Tous les paiements reçus sont visibles dans un tableau de bord unique. | M25: Quels moyens de paiement sont effectivement couverts par cette vue ? | N25: Confirmer le périmètre de centralisation.
A26: Q6B | B26: Dirigeant | C26: 6 | D26: Vos clients utilisent plusieurs moyens de paiement. Comment gardez-vous une vue d’ensemble ? | E26: Je vérifie séparément le solde de chaque moyen de paiement. | F26: Centralisation des paiements | G26: Difficulté | H26: 1 | I26: Légère | J26: Chaque moyen de paiement est consulté séparément. | K26: La vue des encaissements est fragmentée entre plusieurs canaux. | L26: Obtenir un total fiable nécessite plusieurs vérifications. | M26: Combien de comptes ou d’interfaces devez-vous consulter pour faire un point complet ? | N26: Mesurer la dispersion des paiements.
A27: Q6C | B27: Dirigeant | C27: 6 | D27: Vos clients utilisent plusieurs moyens de paiement. Comment gardez-vous une vue d’ensemble ? | E27: Je regroupe manuellement les différents montants à certains moments. | F27: Centralisation des paiements | G27: Difficulté | H27: 2 | I27: Modérée | J27: Les montants des différents moyens de paiement sont regroupés manuellement. | K27: La consolidation des encaissements dépend d’un travail manuel. | L27: Le point global peut être tardif et exposé aux erreurs de saisie. | M27: Qui réalise cette consolidation et à quelle fréquence ? | N27: Qualifier le coût de consolidation.
A28: Q6D | B28: Dirigeant | C28: 6 | D28: Vos clients utilisent plusieurs moyens de paiement. Comment gardez-vous une vue d’ensemble ? | E28: Je me base principalement sur les notifications reçues au fil des paiements. | F28: Centralisation des paiements | G28: Difficulté | H28: 3 | I28: Élevée | J28: La vue d’ensemble repose surtout sur les notifications reçues. | K28: Il n’existe pas de suivi consolidé fiable des paiements. | L28: Des notifications manquées ou difficiles à rapprocher peuvent fausser la lecture des encaissements. | M28: Comment faites-vous lorsqu’une notification n’arrive pas ou n’est plus disponible ? | N28: Identifier la dépendance aux notifications.
A29: Q7A | B29: Dirigeant | C29: 7 | D29: À quel moment savez-vous réellement ce que votre entreprise peut dépenser ? | E29: Je peux consulter ma trésorerie disponible à tout moment. | F29: Trésorerie | G29: Force | H29: 0 | I29: Aucune alerte | J29: La trésorerie disponible peut être consultée à tout moment. | M29: Cette vue tient-elle compte des dépenses engagées et des paiements attendus ? | N29: Confirmer la qualité de la visibilité.
A30: Q7B | B30: Dirigeant | C30: 7 | D30: À quel moment savez-vous réellement ce que votre entreprise peut dépenser ? | E30: Je le sais après avoir fait un point périodique sur mes entrées et mes sorties. | F30: Trésorerie | G30: Difficulté | H30: 1 | I30: Légère | J30: La trésorerie est connue après un point périodique sur les entrées et sorties. | K30: La visibilité sur la trésorerie n’est pas continue. | L30: Une décision prise entre deux points peut reposer sur une information ancienne. | M30: À quelle fréquence réalisez-vous ce point et que se passe-t-il entre deux contrôles ? | N30: Mesurer le délai d’information.
A31: Q7C | B31: Dirigeant | C31: 7 | D31: À quel moment savez-vous réellement ce que votre entreprise peut dépenser ? | E31: Je me fie au solde visible sur mes comptes au moment de décider. | F31: Trésorerie | G31: Difficulté | H31: 2 | I31: Modérée | J31: La décision de dépenser repose sur le solde visible des comptes. | K31: Le solde des comptes sert de principale mesure de trésorerie disponible. | L31: Les charges à venir ou les montants déjà engagés peuvent ne pas être pris en compte. | M31: Comment tenez-vous compte des dépenses déjà engagées mais pas encore débitées ? | N31: Distinguer solde et trésorerie réellement disponible.
A32: Q7D | B32: Dirigeant | C32: 7 | D32: À quel moment savez-vous réellement ce que votre entreprise peut dépenser ? | E32: Je le découvre surtout lorsqu’une dépense importante doit être réglée. | F32: Trésorerie | G32: Difficulté | H32: 3 | I32: Élevée | J32: La capacité à dépenser est découverte lorsqu’une dépense importante arrive. | K32: La trésorerie n’est pas anticipée. | L32: Certaines échéances peuvent créer des tensions inattendues. | M32: Quelle dépense vous a récemment obligé à reconstituer votre situation financière en urgence ? | N32: Faire émerger les tensions de trésorerie.
A33: Q8A | B33: Dirigeant | C33: 8 | D33: Lorsque vient le moment de faire la comptabilité, dans quel état se trouvent vos informations ? | E33: Mes opérations sont déjà enregistrées et peuvent être consultées rapidement. | F33: Comptabilité | G33: Force | H33: 0 | I33: Aucune alerte | J33: Les opérations sont déjà enregistrées et rapidement consultables au moment de la comptabilité. | M33: À quelle fréquence ces opérations sont-elles mises à jour ? | N33: Confirmer la disponibilité des données.
A34: Q8B | B34: Dirigeant | C34: 8 | D34: Lorsque vient le moment de faire la comptabilité, dans quel état se trouvent vos informations ? | E34: Mes justificatifs sont conservés, mais je dois encore les organiser. | F34: Comptabilité | G34: Difficulté | H34: 1 | I34: Légère | J34: Les justificatifs existent, mais doivent encore être organisés. | K34: La préparation comptable nécessite un travail de classement. | L34: Des justificatifs peuvent être difficiles à rattacher aux bonnes opérations. | M34: Comment reliez-vous chaque justificatif au paiement ou à la vente correspondante ? | N34: Comprendre l’organisation documentaire.
A35: Q8C | B35: Dirigeant | C35: 8 | D35: Lorsque vient le moment de faire la comptabilité, dans quel état se trouvent vos informations ? | E35: Je rassemble les informations nécessaires à l’approche de l’échéance. | F35: Comptabilité | G35: Difficulté | H35: 2 | I35: Modérée | J35: Les informations sont rassemblées à l’approche de l’échéance comptable. | K35: La préparation comptable est tardive. | L35: Les erreurs ou informations manquantes sont découvertes au dernier moment. | M35: Combien de jours sont consacrés à rassembler les informations avant l’échéance ? | N35: Mesurer la charge de préparation.
A36: Q8D | B36: Dirigeant | C36: 8 | D36: Lorsque vient le moment de faire la comptabilité, dans quel état se trouvent vos informations ? | E36: Je dois souvent reconstituer certaines opérations après leur réalisation. | F36: Comptabilité | G36: Difficulté | H36: 3 | I36: Élevée | J36: Certaines opérations doivent être reconstituées après leur réalisation. | K36: La comptabilité dépend de reconstitutions a posteriori. | L36: Des opérations peuvent rester mal documentées ou être enregistrées avec retard. | M36: Quelles opérations sont les plus difficiles à reconstituer en fin de période ? | N36: Identifier les principales pertes d’information.
A37: Q9A | B37: Dirigeant | C37: 9 | D37: Lorsque d’autres personnes encaissent pour votre entreprise, comment suivez-vous leur activité ? | E37: Chaque encaissement peut être rattaché à une vente et à la personne concernée. | F37: Délégation des encaissements | G37: Force | H37: 0 | I37: Aucune alerte | J37: Chaque encaissement peut être relié à une vente et à la personne concernée. | M37: Comment contrôlez-vous les écarts par personne ou par point de vente ? | N37: Confirmer le niveau de contrôle.
A38: Q9B | B38: Dirigeant | C38: 9 | D38: Lorsque d’autres personnes encaissent pour votre entreprise, comment suivez-vous leur activité ? | E38: Les personnes concernées enregistrent leurs encaissements dans un support commun. | F38: Délégation des encaissements | G38: Difficulté | H38: 1 | I38: Légère | J38: Les collaborateurs enregistrent leurs encaissements dans un support commun. | K38: Le contrôle dépend de la qualité de mise à jour d’un support partagé. | L38: Un encaissement mal saisi peut être difficile à attribuer ensuite. | M38: Le support permet-il d’identifier automatiquement la personne, l’heure et la vente concernée ? | N38: Vérifier la granularité du suivi.
A39: Q9C | B39: Dirigeant | C39: 9 | D39: Lorsque d’autres personnes encaissent pour votre entreprise, comment suivez-vous leur activité ? | E39: Je reçois principalement un point oral ou un montant global en fin de journée. | F39: Délégation des encaissements | G39: Difficulté | H39: 3 | I39: Élevée | J39: Le suivi repose surtout sur un point oral ou un montant global en fin de journée. | K39: Les encaissements délégués manquent de traçabilité détaillée. | L39: Des ventes non déclarées, erreurs ou détournements peuvent être difficiles à identifier. | M39: Comment vérifiez-vous le montant annoncé lorsqu’il ne correspond pas aux ventes ? | N39: Faire préciser les contrôles réels.
A40: Q9D | B40: Dirigeant | C40: 9 | D40: Lorsque d’autres personnes encaissent pour votre entreprise, comment suivez-vous leur activité ? | E40: Pour le moment, je suis la seule personne à encaisser dans mon entreprise. | F40: Délégation des encaissements | G40: Contexte | H40: 0 | I40: Aucune alerte | J40: Le dirigeant est actuellement la seule personne à encaisser. | L40: La délégation n’est pas encore un sujet observable dans la situation actuelle. | M40: Prévoyez-vous que d’autres personnes encaissent prochainement ? | N40: Identifier un éventuel besoin futur sans pénaliser le score.
A41: Q10A | B41: Dirigeant | C41: 10 | D41: Lorsqu’un client souhaite vous payer à distance, comment procédez-vous généralement ? | E41: Je lui transmets un lien ou une page de paiement prévue à cet effet. | F41: Paiement à distance | G41: Force | H41: 0 | I41: Aucune alerte | J41: Un lien ou une page de paiement est déjà utilisé pour encaisser à distance. | M41: Comment rapprochez-vous ces paiements des commandes correspondantes ? | N41: Confirmer la qualité du parcours à distance.
A42: Q10B | B42: Dirigeant | C42: 10 | D42: Lorsqu’un client souhaite vous payer à distance, comment procédez-vous généralement ? | E42: Je lui communique un numéro après avoir échangé avec lui. | F42: Paiement à distance | G42: Difficulté | H42: 1 | I42: Légère | J42: Le paiement à distance nécessite de communiquer manuellement un numéro au client. | K42: Le parcours de paiement dépend d’un échange manuel. | L42: La vérification et le rapprochement peuvent être plus longs lorsque les demandes augmentent. | M42: Que se passe-t-il entre la demande du client et la confirmation définitive du paiement ? | N42: Cartographier le parcours manuel.
A43: Q10C | B43: Dirigeant | C43: 10 | D43: Lorsqu’un client souhaite vous payer à distance, comment procédez-vous généralement ? | E43: Je privilégie encore le paiement à la livraison ou lors d’une rencontre. | F43: Paiement à distance | G43: Difficulté | H43: 2 | I43: Modérée | J43: Le paiement est encore privilégié à la livraison ou lors d’une rencontre. | K43: Les ventes à distance dépendent d’une présence physique ou de la livraison. | L43: Certains clients peuvent abandonner avant la finalisation de la vente. | M43: Combien de commandes n’aboutissent pas parce que le paiement doit attendre la livraison ou une rencontre ? | N43: Évaluer les pertes liées au paiement tardif.
A44: Q10D | B44: Dirigeant | C44: 10 | D44: Lorsqu’un client souhaite vous payer à distance, comment procédez-vous généralement ? | E44: Je ne propose pas encore de moyen de paiement à distance. | F44: Paiement à distance | G44: Difficulté | H44: 3 | I44: Élevée | J44: Aucun moyen de paiement à distance n’est proposé. | K44: L’entreprise ne peut pas encaisser un client à distance de manière organisée. | L44: La zone de vente et les possibilités de finalisation immédiate sont limitées. | M44: Que faites-vous lorsqu’un client éloigné veut acheter immédiatement ? | N44: Mesurer l’impact commercial de l’absence de paiement à distance.
A45: Q11A | B45: Dirigeant | C45: 11 | D45: Quelle place le digital occupe-t-il actuellement dans vos ventes ? | E45: Mon site permet aux clients de commander et de payer directement. | F45: Parcours de vente digital | G45: Force | H45: 0 | I45: Aucune alerte | J45: Le site permet déjà de commander et de payer directement. | M45: À quel endroit du parcours observez-vous le plus d’abandons ? | N45: Comprendre la performance du parcours existant.
A46: Q11B | B46: Dirigeant | C46: 11 | D46: Quelle place le digital occupe-t-il actuellement dans vos ventes ? | E46: Mon site présente mes offres, mais les commandes se finalisent ailleurs. | F46: Parcours de vente digital | G46: Difficulté | H46: 1 | I46: Légère | J46: Le site présente les offres, mais la commande se termine ailleurs. | K46: Le parcours entre consultation, commande et paiement est fragmenté. | L46: Le passage vers un autre canal peut créer des abandons ou compliquer le suivi des ventes. | M46: Que doit faire exactement un visiteur après avoir choisi une offre sur le site ? | N46: Cartographier la rupture du parcours.
A47: Q11C | B47: Dirigeant | C47: 11 | D47: Quelle place le digital occupe-t-il actuellement dans vos ventes ? | E47: Je vends principalement à travers les réseaux sociaux et les messageries. | F47: Parcours de vente digital | G47: Point de vigilance | H47: 1 | I47: Légère | J47: Les ventes passent principalement par les réseaux sociaux et les messageries. | K47: Le parcours de vente dépend fortement des échanges conversationnels. | L47: Les demandes, commandes et paiements peuvent être difficiles à suivre dans un même parcours. | M47: Comment suivez-vous une demande reçue sur les réseaux sociaux jusqu’au paiement ? | N47: Explorer la continuité du parcours de vente.
A48: Q11D | B48: Dirigeant | C48: 11 | D48: Quelle place le digital occupe-t-il actuellement dans vos ventes ? | E48: Mes ventes se font encore essentiellement en présentiel. | F48: Parcours de vente digital | G48: Contexte | H48: 0 | I48: Aucune alerte | J48: Les ventes sont encore principalement réalisées en présentiel. | L48: Le besoin digital dépendra du projet de développement de l’entreprise. | M48: Souhaitez-vous développer la vente à distance ou rester principalement en présentiel ? | N48: Comprendre l’ambition digitale.
A49: Q12A | B49: Dirigeant | C49: 12 | D49: Un client affirme avoir payé, mais vous ne retrouvez pas immédiatement son paiement. Que faites-vous ? | E49: Je recherche la transaction à partir de sa référence. | F49: Traçabilité d’un paiement | G49: Force | H49: 0 | I49: Aucune alerte | J49: Un paiement peut être recherché à partir de sa référence. | M49: La référence permet-elle aussi de retrouver la commande et le client concernés ? | N49: Confirmer la profondeur du rapprochement.
A50: Q12B | B50: Dirigeant | C50: 12 | D50: Un client affirme avoir payé, mais vous ne retrouvez pas immédiatement son paiement. Que faites-vous ? | E50: Je lui demande une preuve de paiement pour poursuivre la vérification. | F50: Traçabilité d’un paiement | G50: Difficulté | H50: 1 | I50: Légère | J50: La vérification dépend d’une preuve envoyée par le client. | K50: L’entreprise ne retrouve pas toujours un paiement depuis ses propres données. | L50: La résolution dépend de la disponibilité et de la qualité de la preuve du client. | M50: Que pouvez-vous vérifier lorsque le client ne retrouve plus sa preuve ? | N50: Tester l’autonomie de vérification.
A51: Q12C | B51: Dirigeant | C51: 12 | D51: Un client affirme avoir payé, mais vous ne retrouvez pas immédiatement son paiement. Que faites-vous ? | E51: Je consulte mes différents soldes pour voir si le montant apparaît. | F51: Traçabilité d’un paiement | G51: Difficulté | H51: 2 | I51: Modérée | J51: La recherche oblige à consulter plusieurs soldes. | K51: Un paiement ne peut pas être retrouvé rapidement dans une vue unique. | L51: Le délai de confirmation peut dégrader l’expérience client et mobiliser plusieurs vérifications. | M51: Combien de comptes devez-vous vérifier avant de confirmer un paiement ? | N51: Mesurer la complexité de recherche.
A52: Q12D | B52: Dirigeant | C52: 12 | D52: Un client affirme avoir payé, mais vous ne retrouvez pas immédiatement son paiement. Que faites-vous ? | E52: J’attends la notification ou la confirmation de mon opérateur de paiement. | F52: Traçabilité d’un paiement | G52: Difficulté | H52: 3 | I52: Élevée | J52: La confirmation dépend de l’arrivée d’une notification ou de l’opérateur. | K52: L’entreprise ne maîtrise pas le délai de vérification d’un paiement. | L52: Une commande peut rester bloquée malgré la déclaration du client. | M52: Combien de temps une commande peut-elle rester en attente dans cette situation ? | N52: Évaluer l’impact opérationnel du délai.
A53: Q13A | B53: Dirigeant | C53: 13 | D53: Avant d’adopter un nouvel outil pour votre entreprise, qu’est-ce qui compte le plus pour vous ? | E53: Je veux savoir s’il peut s’intégrer facilement à mon fonctionnement actuel. | F53: Adoption | G53: Condition déclarée | H53: 0 | I53: Aucune alerte | J53: L’intégration au fonctionnement actuel est la première condition d’adoption. | L53: Une solution trop éloignée des habitudes existantes peut être rejetée. | M53: Quelles habitudes ou outils doivent absolument être préservés ? | N53: Comprendre les conditions d’adoption.
A54: Q13B | B54: Dirigeant | C54: 13 | D54: Avant d’adopter un nouvel outil pour votre entreprise, qu’est-ce qui compte le plus pour vous ? | E54: Je veux vérifier s’il me permettra de gagner du temps dans le suivi. | F54: Adoption | G54: Condition déclarée | H54: 0 | I54: Aucune alerte | J54: Le gain de temps est la première condition d’adoption. | L54: La valeur attendue devra être observable dans les tâches quotidiennes. | M54: Quelles tâches de suivi vous prennent aujourd’hui le plus de temps ? | N54: Identifier les gains attendus.
A55: Q13C | B55: Dirigeant | C55: 13 | D55: Avant d’adopter un nouvel outil pour votre entreprise, qu’est-ce qui compte le plus pour vous ? | E55: Je veux m’assurer que mon équipe pourra l’utiliser sans difficulté. | F55: Adoption | G55: Condition déclarée | H55: 0 | I55: Aucune alerte | J55: La facilité d’utilisation par l’équipe est la première condition d’adoption. | L55: La capacité de l’équipe à adopter un nouvel outil sera déterminante. | M55: Quelles difficultés votre équipe rencontre-t-elle habituellement avec de nouveaux outils ? | N55: Comprendre le risque d’adoption.
A56: Q13D | B56: Dirigeant | C56: 13 | D56: Avant d’adopter un nouvel outil pour votre entreprise, qu’est-ce qui compte le plus pour vous ? | E56: Je préfère attendre que le besoin devienne vraiment urgent avant de changer. | F56: Adoption | G56: Point de vigilance | H56: 2 | I56: Modérée | J56: Le changement est envisagé seulement lorsque le besoin devient urgent. | K56: Les améliorations peuvent être reportées jusqu’à l’apparition d’un problème critique. | L56: Le prospect peut reconnaître la difficulté sans être encore prêt à agir. | M56: Quel événement rendrait ce sujet suffisamment urgent pour agir maintenant ? | N56: Évaluer la maturité du besoin.
A57: Q14A | B57: Dirigeant | C57: 14 | D57: Dans un an, quel progrès vous donnerait le plus le sentiment de mieux piloter votre entreprise ? | E57: Je pourrais connaître l’état de ma trésorerie sans attendre la fin du mois. | F57: Besoin déclaré | G57: Besoin déclaré | H57: 0 | I57: Aucune alerte | J57: Le progrès prioritaire déclaré est de connaître la trésorerie sans attendre la fin du mois. | L57: Le besoin de visibilité financière est explicitement reconnu. | M57: Qu’est-ce que cette visibilité vous permettrait de décider plus rapidement ? | N57: Approfondir le besoin déclaré.
A58: Q14B | B58: Dirigeant | C58: 14 | D58: Dans un an, quel progrès vous donnerait le plus le sentiment de mieux piloter votre entreprise ? | E58: Je pourrais retrouver facilement l’origine de chaque mouvement de fonds. | F58: Besoin déclaré | G58: Besoin déclaré | H58: 0 | I58: Aucune alerte | J58: Le progrès prioritaire déclaré est de retrouver l’origine de chaque mouvement de fonds. | L58: Le besoin de traçabilité est explicitement reconnu. | M58: Quels mouvements sont aujourd’hui les plus difficiles à expliquer ? | N58: Approfondir le besoin déclaré.
A59: Q14C | B59: Dirigeant | C59: 14 | D59: Dans un an, quel progrès vous donnerait le plus le sentiment de mieux piloter votre entreprise ? | E59: Je pourrais encaisser mes clients sur tous mes canaux de vente. | F59: Besoin déclaré | G59: Besoin déclaré | H59: 0 | I59: Aucune alerte | J59: Le progrès prioritaire déclaré est d’encaisser sur tous les canaux de vente. | L59: Le besoin d’un parcours d’encaissement plus large est explicitement reconnu. | M59: Quel canal vous empêche aujourd’hui de finaliser certaines ventes ? | N59: Approfondir le besoin déclaré.
A60: Q14D | B60: Dirigeant | C60: 14 | D60: Dans un an, quel progrès vous donnerait le plus le sentiment de mieux piloter votre entreprise ? | E60: Je pourrais déléguer davantage sans perdre le contrôle de mon activité. | F60: Besoin déclaré | G60: Besoin déclaré | H60: 0 | I60: Aucune alerte | J60: Le progrès prioritaire déclaré est de déléguer sans perdre le contrôle. | L60: Le besoin de contrôle dans la délégation est explicitement reconnu. | M60: Qu’aimeriez-vous pouvoir déléguer tout en continuant à vérifier ? | N60: Approfondir le besoin déclaré.
A61: R1A | B61: Rayonnement | C61: 1 | D61: En dehors de vos clients actuels, jusqu’où votre entreprise est-elle connue ? | E61: Elle est principalement connue par mon entourage et mes contacts directs. | F61: Notoriété | G61: Difficulté | H61: 3 | I61: Élevée | J61: L’entreprise est principalement connue de l’entourage et des contacts directs. | K61: La notoriété dépasse peu le réseau immédiat. | L61: L’acquisition peut dépendre fortement des relations personnelles. | M61: Quelle part de vos nouveaux clients vient de personnes qui ne vous connaissaient pas auparavant ? | N61: Mesurer l’ouverture au marché.
A62: R1B | B62: Rayonnement | C62: 1 | D62: En dehors de vos clients actuels, jusqu’où votre entreprise est-elle connue ? | E62: Elle commence à être connue par des personnes situées dans ma zone. | F62: Notoriété | G62: Difficulté | H62: 2 | I62: Modérée | J62: L’entreprise commence à être connue dans sa zone. | K62: La reconnaissance reste principalement locale. | L62: Le développement hors de la zone actuelle peut être limité. | M62: Qu’est-ce qui vous empêche aujourd’hui d’être connu au-delà de votre zone ? | N62: Comprendre la limite de portée.
A63: R1C | B63: Rayonnement | C63: 1 | D63: En dehors de vos clients actuels, jusqu’où votre entreprise est-elle connue ? | E63: Elle est régulièrement identifiée par des prospects de mon secteur. | F63: Notoriété | G63: Point de vigilance | H63: 1 | I63: Légère | J63: L’entreprise est identifiée par des prospects de son secteur. | K63: La reconnaissance existe, mais n’est pas encore large sur le marché visé. | L63: La marque peut devoir convertir cette reconnaissance en préférence. | M63: Les prospects qui vous connaissent comprennent-ils clairement pourquoi vous choisir ? | N63: Passer de la reconnaissance à la préférence.
A64: R1D | B64: Rayonnement | C64: 1 | D64: En dehors de vos clients actuels, jusqu’où votre entreprise est-elle connue ? | E64: Elle est reconnue par une partie importante du marché que je vise. | F64: Notoriété | G64: Force | H64: 0 | I64: Aucune alerte | J64: L’entreprise est reconnue par une partie importante de son marché cible. | M64: Quels éléments ont le plus contribué à cette reconnaissance ? | N64: Identifier les actifs de notoriété.
A65: R2A | B65: Rayonnement | C65: 2 | D65: Lorsqu’un prospect choisit un concurrent, savez-vous généralement pourquoi ? | E65: Je reçois rarement des informations sur les raisons de son choix. | F65: Lecture concurrentielle | G65: Difficulté | H65: 3 | I65: Élevée | J65: Les raisons qui conduisent un prospect chez un concurrent sont rarement connues. | K65: Les pertes commerciales ne produisent presque aucune information exploitable. | L65: Les décisions commerciales peuvent être prises sans comprendre les arbitrages du marché. | M65: Comment analysez-vous aujourd’hui une opportunité commerciale perdue ? | N65: Évaluer la connaissance des pertes.
A66: R2B | B66: Rayonnement | C66: 2 | D66: Lorsqu’un prospect choisit un concurrent, savez-vous généralement pourquoi ? | E66: J’essaie de comprendre sa décision à partir de ce que j’observe. | F66: Lecture concurrentielle | G66: Difficulté | H66: 2 | I66: Modérée | J66: Les raisons du choix d’un concurrent sont principalement déduites par observation. | K66: La lecture des pertes repose surtout sur des suppositions. | L66: Certaines causes réelles de perte peuvent être mal interprétées. | M66: Quand avez-vous demandé pour la dernière fois à un prospect pourquoi il n’a pas choisi votre offre ? | N66: Tester l’accès au retour direct.
A67: R2C | B67: Rayonnement | C67: 2 | D67: Lorsqu’un prospect choisit un concurrent, savez-vous généralement pourquoi ? | E67: Il m’arrive de lui demander ce qui a motivé son choix. | F67: Lecture concurrentielle | G67: Point de vigilance | H67: 1 | I67: Légère | J67: Les raisons du choix d’un concurrent sont parfois demandées au prospect. | K67: Le retour sur les pertes existe, mais n’est pas systématique. | L67: Les enseignements peuvent rester anecdotiques et difficiles à comparer. | M67: Où conservez-vous les raisons recueillies auprès des prospects perdus ? | N67: Vérifier la capitalisation des retours.
A68: R2D | B68: Rayonnement | C68: 2 | D68: Lorsqu’un prospect choisit un concurrent, savez-vous généralement pourquoi ? | E68: Je recueille régulièrement ces raisons pour mieux comprendre mon marché. | F68: Lecture concurrentielle | G68: Force | H68: 0 | I68: Aucune alerte | J68: Les raisons de perte sont recueillies régulièrement pour comprendre le marché. | M68: Quelles raisons reviennent le plus souvent dans vos pertes commerciales ? | N68: Exploiter la connaissance existante.
A69: R3A | B69: Rayonnement | C69: 3 | D69: Pour quelle raison vos clients vous choisissent-ils principalement ? | E69: Ils viennent souvent vers moi parce que mes prix leur conviennent. | F69: Différenciation | G69: Contexte | H69: 0 | I69: Aucune alerte | J69: La principale raison de choix déclarée est le prix. | L69: La solidité de cet avantage dépend de la capacité à le maintenir sans fragiliser la marge. | M69: Que se passe-t-il lorsqu’un concurrent propose un prix inférieur ? | N69: Comprendre la solidité de la différenciation.
A70: R3B | B70: Rayonnement | C70: 3 | D70: Pour quelle raison vos clients vous choisissent-ils principalement ? | E70: Ils me choisissent parce que je suis proche d’eux et facilement accessible. | F70: Différenciation | G70: Contexte | H70: 0 | I70: Aucune alerte | J70: La principale raison de choix déclarée est la proximité. | L70: L’avantage peut dépendre de la présence personnelle ou géographique. | M70: Cette proximité reste-t-elle perceptible lorsque le volume de clients augmente ? | N70: Comprendre la capacité à maintenir l’avantage.
A71: R3C | B71: Rayonnement | C71: 3 | D71: Pour quelle raison vos clients vous choisissent-ils principalement ? | E71: Ils reviennent parce qu’ils font confiance à la qualité de ce que je propose. | F71: Différenciation | G71: Contexte | H71: 0 | I71: Aucune alerte | J71: La principale raison de choix déclarée est la qualité. | L71: La qualité doit être rendue visible et prouvée avant l’achat. | M71: Comment un nouveau prospect peut-il vérifier votre niveau de qualité avant de vous choisir ? | N71: Rechercher les preuves de qualité.
A72: R3D | B72: Rayonnement | C72: 3 | D72: Pour quelle raison vos clients vous choisissent-ils principalement ? | E72: Ils trouvent chez moi un avantage qu’ils retrouvent difficilement ailleurs. | F72: Différenciation | G72: Contexte | H72: 0 | I72: Aucune alerte | J72: La principale raison de choix déclarée est un avantage difficile à retrouver ailleurs. | L72: Cet avantage doit être formulé et protégé pour rester distinctif. | M72: Pouvez-vous expliquer cet avantage en une phrase et apporter une preuve ? | N72: Tester la clarté de l’avantage.
A73: R4A | B73: Rayonnement | C73: 4 | D73: Une personne qui découvre votre entreprise comprend-elle facilement ce qui vous distingue ? | E73: Je ne saurais pas encore expliquer clairement ce qui me différencie. | F73: Différenciation | G73: Difficulté | H73: 3 | I73: Élevée | J73: Le dirigeant ne peut pas encore expliquer clairement ce qui différencie l’entreprise. | K73: La proposition de valeur n’est pas clairement définie. | L73: Les prospects peuvent comparer l’entreprise principalement sur le prix ou la proximité. | M73: Quelle phrase utilisez-vous aujourd’hui pour expliquer pourquoi vous choisir ? | N73: Faire émerger la promesse actuelle.
A74: R4B | B74: Rayonnement | C74: 4 | D74: Une personne qui découvre votre entreprise comprend-elle facilement ce qui vous distingue ? | E74: J’arrive à l’expliquer lorsque je présente personnellement mon activité. | F74: Différenciation | G74: Difficulté | H74: 2 | I74: Modérée | J74: La différence est comprise lorsque le dirigeant présente personnellement l’activité. | K74: La proposition de valeur dépend encore de l’explication orale du dirigeant. | L74: La communication autonome peut ne pas transmettre ce qui rend l’offre particulière. | M74: Un prospect qui ne vous parle pas directement comprend-il la même chose ? | N74: Tester l’autonomie de la communication.
A75: R4C | B75: Rayonnement | C75: 4 | D75: Une personne qui découvre votre entreprise comprend-elle facilement ce qui vous distingue ? | E75: Ma différence apparaît déjà dans mes offres et ma communication. | F75: Différenciation | G75: Point de vigilance | H75: 1 | I75: Légère | J75: La différence apparaît déjà dans les offres et la communication. | K75: La différenciation est formulée, mais sa reconnaissance spontanée n’est pas encore établie. | L75: Le marché peut voir la différence sans encore l’associer fortement à la marque. | M75: Quelles preuves montrent que les prospects perçoivent réellement cette différence ? | N75: Rechercher une preuve de perception.
A76: R4D | B76: Rayonnement | C76: 4 | D76: Une personne qui découvre votre entreprise comprend-elle facilement ce qui vous distingue ? | E76: Mes clients citent spontanément ce qui rend mon entreprise particulière. | F76: Différenciation | G76: Force | H76: 0 | I76: Aucune alerte | J76: Les clients citent spontanément ce qui rend l’entreprise particulière. | M76: Quels mots utilisent-ils le plus souvent pour décrire cette différence ? | N76: Capitaliser sur la perception du marché.
A77: R5A | B77: Rayonnement | C77: 5 | D77: Comment votre entreprise est-elle actuellement présente sur les canaux numériques ? | E77: Mon entreprise y est peu présente ou ne dispose pas encore de page active. | F77: Présence digitale | G77: Difficulté | H77: 3 | I77: Élevée | J77: L’entreprise est peu présente ou ne dispose pas de page active. | K77: La présence numérique est insuffisante pour installer une visibilité continue. | L77: Les prospects qui recherchent l’entreprise en ligne peuvent trouver peu d’informations récentes. | M77: Que trouve aujourd’hui un prospect qui recherche votre entreprise sur internet ? | N77: Évaluer la visibilité disponible.
A78: R5B | B78: Rayonnement | C78: 5 | D78: Comment votre entreprise est-elle actuellement présente sur les canaux numériques ? | E78: Je publie principalement lorsque j’ai une actualité ou du temps disponible. | F78: Présence digitale | G78: Difficulté | H78: 2 | I78: Modérée | J78: La publication dépend principalement des actualités ou du temps disponible. | K78: La présence numérique est irrégulière. | L78: La marque peut disparaître de l’attention du marché entre deux publications. | M78: Quelle est la principale raison des périodes sans communication ? | N78: Identifier la cause de l’irrégularité.
A79: R5C | B79: Rayonnement | C79: 5 | D79: Comment votre entreprise est-elle actuellement présente sur les canaux numériques ? | E79: Je communique régulièrement sur le canal que j’utilise le plus. | F79: Présence digitale | G79: Point de vigilance | H79: 1 | I79: Légère | J79: La communication est régulière sur un canal principal. | K79: La présence numérique repose essentiellement sur un seul canal. | L79: La portée et l’acquisition peuvent dépendre fortement de ce canal. | M79: Que se passerait-il si ce canal produisait soudainement moins de résultats ? | N79: Évaluer la dépendance au canal.
A80: R5D | B80: Rayonnement | C80: 5 | D80: Comment votre entreprise est-elle actuellement présente sur les canaux numériques ? | E80: Je maintiens une présence continue sur les canaux utiles à mon activité. | F80: Présence digitale | G80: Force | H80: 0 | I80: Aucune alerte | J80: L’entreprise maintient une présence continue sur les canaux utiles à son activité. | M80: Quels canaux contribuent réellement aux demandes commerciales ? | N80: Identifier les canaux les plus utiles.
A81: R6A | B81: Rayonnement | C81: 6 | D81: Que produit concrètement votre présence numérique pour votre entreprise ? | E81: Je ne mesure pas encore réellement ce qu’elle apporte à mon activité. | F81: Performance digitale | G81: Difficulté | H81: 3 | I81: Élevée | J81: L’apport réel de la présence numérique n’est pas mesuré. | K81: L’entreprise ne sait pas ce que le digital produit pour l’activité. | L81: Il est difficile d’identifier les actions qui méritent d’être maintenues ou corrigées. | M81: Quelles données relient aujourd’hui vos actions numériques à vos résultats commerciaux ? | N81: Identifier le niveau de mesure.
A82: R6B | B82: Rayonnement | C82: 6 | D82: Que produit concrètement votre présence numérique pour votre entreprise ? | E82: Elle me permet surtout d’obtenir de la visibilité et des réactions. | F82: Performance digitale | G82: Difficulté | H82: 2 | I82: Modérée | J82: La présence numérique produit surtout de la visibilité et des réactions. | K82: La visibilité numérique se transforme peu en opportunités commerciales identifiables. | L82: Le passage entre attention, demande et vente peut être insuffisamment structuré. | M82: Que doit faire une personne intéressée après avoir vu l’un de vos contenus ? | N82: Explorer le parcours de conversion.
A83: R6C | B83: Rayonnement | C83: 6 | D83: Que produit concrètement votre présence numérique pour votre entreprise ? | E83: Elle génère régulièrement des demandes d’information ou de devis. | F83: Performance digitale | G83: Point de vigilance | H83: 1 | I83: Légère | J83: La présence numérique génère régulièrement des demandes ou des devis. | K83: Les opportunités existent, mais leur transformation en ventes n’est pas encore démontrée. | L83: Le suivi entre la demande initiale et la vente peut manquer de mesure. | M83: Quelle proportion de ces demandes devient réellement cliente ? | N83: Mesurer la conversion commerciale.
A84: R6D | B84: Rayonnement | C84: 6 | D84: Que produit concrètement votre présence numérique pour votre entreprise ? | E84: Je peux identifier des ventes directement issues de mes actions numériques. | F84: Performance digitale | G84: Force | H84: 0 | I84: Aucune alerte | J84: Des ventes issues des actions numériques peuvent être identifiées. | M84: Quelles actions numériques génèrent le plus de ventes mesurables ? | N84: Capitaliser sur les actions performantes.
A85: R7A | B85: Rayonnement | C85: 7 | D85: Si votre entreprise arrêtait ses activités demain, qui le remarquerait rapidement ? | E85: Les personnes directement impliquées dans mon activité le remarqueraient. | F85: Empreinte marché | G85: Difficulté | H85: 3 | I85: Élevée | J85: L’arrêt de l’activité serait surtout remarqué par les personnes directement impliquées. | K85: L’empreinte de l’entreprise reste très limitée au-delà de son fonctionnement interne. | L85: Le marché pourrait remplacer facilement l’offre actuelle. | M85: Qu’est-ce que vos clients perdraient réellement si votre entreprise disparaissait ? | N85: Faire préciser la valeur irremplaçable.
A86: R7B | B86: Rayonnement | C86: 7 | D86: Si votre entreprise arrêtait ses activités demain, qui le remarquerait rapidement ? | E86: Mes clients réguliers ressentiraient rapidement mon absence. | F86: Empreinte marché | G86: Difficulté | H86: 2 | I86: Modérée | J86: L’arrêt de l’activité serait principalement ressenti par les clients réguliers. | K86: L’empreinte existe auprès de la clientèle actuelle, mais reste peu visible dans l’écosystème. | L86: Le développement dépend encore fortement de la base de clients existante. | M86: Qui, en dehors de vos clients réguliers, défendrait spontanément votre importance ? | N86: Mesurer l’empreinte élargie.
A87: R7C | B87: Rayonnement | C87: 7 | D87: Si votre entreprise arrêtait ses activités demain, qui le remarquerait rapidement ? | E87: Certains partenaires ou professionnels de mon secteur le remarqueraient. | F87: Empreinte marché | G87: Point de vigilance | H87: 1 | I87: Légère | J87: Certains partenaires ou professionnels remarqueraient l’arrêt de l’activité. | K87: L’entreprise compte dans son réseau, mais son absence ne serait pas encore largement ressentie par le marché. | L87: L’autorité professionnelle peut être plus avancée que la préférence du marché. | M87: Comment cette reconnaissance professionnelle se transforme-t-elle en nouvelles opportunités ? | N87: Relier réseau et développement.
A88: R7D | B88: Rayonnement | C88: 7 | D88: Si votre entreprise arrêtait ses activités demain, qui le remarquerait rapidement ? | E88: Une partie de mon marché constaterait clairement la disparition de mon offre. | F88: Empreinte marché | G88: Force | H88: 0 | I88: Aucune alerte | J88: Une partie du marché constaterait clairement la disparition de l’offre. | M88: Qu’est-ce qui rend aujourd’hui votre entreprise difficile à remplacer ? | N88: Identifier les actifs différenciants.

Sheet Règles combinées
A1: Règles combinées — hypothèses à confirmer en entretien
A2: Ces règles croisent plusieurs réponses pour suggérer un angle d’investigation. Elles ne constituent ni un diagnostic confirmé ni une recommandation de produit.
A4: ID | B4: Thème | C4: Gravité | D4: Condition de détection | E4: Signaux croisés | F4: Hypothèse à approfondir | G4: Question de relance
A5: RC01 | B5: Parcours social fragmenté | C5: 2 | D5: Q11C + R6A, R6B ou R6C | E5: Les ventes passent par les réseaux sociaux, mais le passage des interactions ou demandes numériques à des ventes mesurées reste à clarifier. | F5: Le parcours entre découverte, conversation, commande et paiement pourrait être fragmenté. | G5: Après une demande reçue sur les réseaux sociaux, quelles étapes le client suit-il jusqu’au paiement ?
A6: RC02 | B6: Site vitrine déconnecté | C6: 2 | D6: Q11B + R6A ou R6B | E6: Le site présente l’offre, mais la commande se finalise ailleurs et le digital produit peu d’opportunités. | F6: Le passage du site vers la commande ou le paiement pourrait provoquer des abandons. | G6: Que doit faire un visiteur intéressé après avoir consulté une offre sur votre site ?
A7: RC03 | B7: Site transactionnel peu performant | C7: 2 | D7: Q11A + R6A ou R6B | E7: Le site permet de commander et payer, mais les effets numériques restent faibles ou non mesurés. | F7: La difficulté pourrait se situer dans l’acquisition, la conversion ou la mesure du parcours. | G7: À quelle étape du site perdez-vous le plus de visiteurs ou de commandes ?
A8: RC04 | B8: Encaissement à distance incomplet | C8: 3 | D8: Q10C ou Q10D + Q11A, Q11B ou Q11C | E8: L’activité possède un canal de vente digital, mais ne dispose pas d’un parcours organisé pour encaisser à distance. | F8: La finalisation du paiement pourrait interrompre certaines ventes digitales. | G8: Combien de demandes à distance restent sans suite au moment de payer ?
A9: RC05 | B9: Dispersion des paiements et trésorerie | C9: 3 | D9: Q6B, Q6C ou Q6D + Q7C ou Q7D | E9: Les paiements sont dispersés et la trésorerie est évaluée à partir des soldes ou au moment des dépenses. | F9: La fragmentation des encaissements pourrait empêcher une lecture fiable de la trésorerie. | G9: Comment obtenez-vous un montant unique et fiable avant de décider d’une dépense ?
A10: RC06 | B10: Écarts impossibles à expliquer rapidement | C10: 3 | D10: Q4C ou Q4D + Q5C ou Q5D | E10: Le suivi des ventes est reconstitué ou informel et les écarts dépendent d’explications ou restent sans preuve. | F10: L’entreprise pourrait manquer des éléments nécessaires pour distinguer erreur, oubli et vente non déclarée. | G10: Pouvez-vous retracer une vente précise depuis la commande jusqu’au paiement reçu ?
A11: RC07 | B11: Délégation insuffisamment traçable | C11: 3 | D11: Q9B ou Q9C + Q5C ou Q5D | E11: Des collaborateurs encaissent, mais le contrôle repose sur un support partagé, un point oral ou un montant global. | F11: Les responsabilités individuelles pourraient être difficiles à établir en cas d’écart. | G11: Comment attribuez-vous précisément un écart à une vente et à la personne concernée ?
A12: RC08 | B12: Comptabilité dépendante des reconstitutions | C12: 3 | D12: Q8C ou Q8D + Q4C ou Q4D | E12: Les ventes et opérations doivent être rassemblées ou reconstituées avant la comptabilité. | F12: La préparation comptable pourrait consommer beaucoup de temps et laisser des opérations mal documentées. | G12: Quelles informations vous manquent le plus souvent au moment de préparer la comptabilité ?
A13: RC09 | B13: Présence irrégulière sans conversion | C13: 2 | D13: R5A ou R5B + R6A ou R6B | E13: La présence numérique est faible ou irrégulière et produit peu de résultats commerciaux identifiables. | F13: Le problème pourrait combiner manque de régularité, absence de parcours et faible mesure. | G13: Quel résultat précis attendez-vous de votre présence numérique aujourd’hui ?
A14: RC10 | B14: Faible notoriété et faible présence | C14: 2 | D14: R1A ou R1B + R5A ou R5B | E14: La notoriété reste limitée et la présence numérique est faible ou irrégulière. | F14: La faible exposition de l’entreprise pourrait contribuer directement à son rayonnement limité. | G14: Comment de nouveaux prospects qui ne vous connaissent pas découvrent-ils actuellement l’entreprise ?
A15: RC11 | B15: Lecture du marché et différence peu claires | C15: 3 | D15: R2A ou R2B + R4A ou R4B | E15: L’entreprise comprend peu les choix en faveur des concurrents et sa différence reste difficile à percevoir sans explication. | F15: La proposition de valeur pourrait être construite sans suffisamment de retours du marché. | G15: Quelles raisons vos prospects donnent-ils lorsqu’ils choisissent une autre offre ?
A16: RC12 | B16: Différence peu convertie | C16: 2 | D16: R4C ou R4D + R6A, R6B ou R6C | E16: La différence est visible ou reconnue, mais sa transformation en ventes numériques mesurées n’est pas établie. | F16: La difficulté pourrait se situer dans la transformation de la différence en action commerciale. | G16: Quel appel à l’action permet aujourd’hui à un prospect convaincu de passer à l’étape suivante ?
... A20: RC16 | B20: Besoin de contrôle dans la délégation confirmé | C20: 3 | D20: Q9B ou Q9C + Q14D | E20: La manière actuelle de suivre les collaborateurs concorde avec le besoin de déléguer sans perdre le contrôle. | F20: La sécurisation de la délégation semble être un enjeu concret. | G20: Quel contrôle aimeriez-vous conserver lorsque d’autres personnes encaissent ?

Sheet Archétypes & règles
A1: Archétypes, dimensions et règles de résultat
A3: Empreintes des 8 archétypes
A4: Archétype | B4: Inspiré par | C4: Centrale | D4: 2e dimension | E4: 3e dimension | F4: Poids 1 | G4: Poids 2 | H4: Poids 3 | I4: Traits dominants | J4: Forces | K4: Risque
A5: Stratège | B5: Samory Touré | C5: STR | D5: ADA | E5: ORG | F5: 0.5 | G5: 0.3 | H5: 0.2 | I5: Analytique, patient, observateur et anticipateur | J5: Anticipation, lecture stratégique, allocation des ressources | K5: Suranalyse et lenteur dans la décision
A6: Visionnaire | B6: Kwame Nkrumah | C6: VIS | D6: INF | E6: TRA | F6: 0.5 | G6: 0.3 | H6: 0.2 | I6: Ambitieux, intuitif, tourné vers l’avenir et inspirant | J6: Projection, ambition et mobilisation autour d’une vision | K6: Sous-estimation des contraintes opérationnelles
A7: Bâtisseur | B7: Aliko Dangote | C7: EXE | D7: ORG | E7: STR | F7: 0.5 | G7: 0.35 | H7: 0.15 | I7: Structuré, constant, méthodique et pragmatique | J7: Exécution, structuration et croissance progressive | K7: Stabilité privilégiée au détriment de l’agilité
A8: Conquérant | B8: Shaka Zulu | C8: AUD | D8: EXE | E8: VIS | F8: 0.5 | G8: 0.35 | H8: 0.15 | I8: Audacieux, compétitif, rapide et déterminé | J8: Expansion, accélération et courage décisionnel | K8: Prise de risque excessive ou dispersion
A9: Fédérateur | B9: Nelson Mandela | C9: INF | D9: ADA | E9: VIS | F9: 0.5 | G9: 0.3 | H9: 0.2 | I9: Relationnel, rassembleur, diplomate et empathique | J9: Mobilisation, adhésion, alliances et intelligence relationnelle | K9: Recherche excessive du consensus
A10: Résilient | B10: Béhanzin | C10: ADA | D10: EXE | E10: AUD | F10: 0.5 | G10: 0.3 | H10: 0.2 | I10: Endurant, persévérant, adaptable et combatif | J10: Rebond, endurance, adaptation et persévérance | K10: Persistance dans une situation devenue défavorable
A11: Gestionnaire | B11: Tidjane Thiam | C11: ORG | D11: STR | E11: EXE | F11: 0.45 | G11: 0.3 | H11: 0.25 | I11: Discipliné, organisé, rationnel et précis | J11: Organisation, maîtrise des ressources et pilotage | K11: Optimisation privilégiée au détriment de l’audace
A12: Réformateur | B12: Thomas Sankara | C12: TRA | D12: AUD | E12: VIS | F12: 0.5 | G12: 0.3 | H12: 0.2 | I12: Critique, indépendant, innovant et orienté transformation | J12: Remise en question, transformation et évolution des systèmes | K12: Multiplication des changements ou adoption insuffisamment accompagnée
A14: Définition des dimensions
A15: Code | B15: Dimension | C15: Définition fonctionnelle
A16: VIS | B16: Vision | C16: Capacité à projeter une direction future et à relier les décisions à une ambition.
A17: STR | B17: Stratégie | C17: Capacité à lire le terrain, comparer des options, choisir et anticiper.
A18: EXE | B18: Exécution | C18: Capacité à transformer une intention en actions et résultats.
A19: ORG | B19: Organisation | C19: Capacité à structurer ressources, rôles, processus et contrôles.
A20: INF | B20: Influence | C20: Capacité à mobiliser, convaincre, fédérer et construire des alliances.
A21: AUD | B21: Audace | C21: Capacité à décider dans l’incertitude et à créer du mouvement.
A22: ADA | B22: Adaptabilité | C22: Capacité à ajuster la trajectoire et apprendre du contexte.
A23: TRA | B23: Transformation | C23: Capacité à remettre en question un système et conduire son évolution.
A25: Règles du profil public
A26: Calcul brut | B26: Chaque réponse attribue +2 à la dimension principale et +1 à la secondaire.
A27: Normalisation | B27: Score dimension = score brut / maximum réellement atteignable × 100.
A28: Affinité | B28: Somme pondérée des trois dimensions de l’empreinte de l’archétype.
A29: Profil principal | B29: Archétype ayant l’affinité la plus élevée, calculée à deux décimales.
A30: Profil secondaire | B30: Affinité ≥55, ≥90 % de la principale et écart ≤8 points.
A31: Égalité | B31: Dimension centrale, puis nombre de +2, puis somme brute de l’empreinte, puis ordre technique.
A32: Ordre technique | B32: Stratège, Visionnaire, Bâtisseur, Conquérant, Fédérateur, Résilient, Gestionnaire, Réformateur.
A34: Niveaux du score interne de pilotage
A35: Score | B35: Niveau interne | C35: Lecture | K35: Visibilité
A36: 75–100 | B36: Pilotage structuré | C36: Les opérations sont suivies avec des données et des points de contrôle. | K36: Interne
A37: 50–74 | B37: Pilotage partiellement structuré | C37: Des outils existent, mais la régularité ou la centralisation restent incomplètes. | K37: Interne
A38: 25–49 | B38: Pilotage réactif | C38: Le suivi se déclenche surtout lorsqu’une échéance ou un problème apparaît. | K38: Interne
A39: 0–24 | B39: Pilotage informel | C39: La visibilité repose principalement sur des estimations, notifications ou reconstitutions. | K39: Interne

Sheet Lecture croisée
A1: Lecture causale — Pilotage interne × Rayonnement
A2: Le score de pilotage décrit les fondations déclarées. Le Rayonnement mesure leurs manifestations visibles. La comparaison ne juge pas la sincérité du participant : elle identifie une cohérence ou un décalage à investiguer.
A5: Matrice principale — seuil de solidité : 60/100
A6: Pilotage | B6: Rayonnement | C6: Lecture | D6: Interprétation causale | E6: Priorité FeexPay | F6: Priorité marketing | G6: Formulation rapport | H6: Code
A7: ≥ 60 | B7: ≥ 60 | C7: Cohérence consolidée | D7: Les fondations internes se matérialisent dans le rayonnement. | E7: Optimiser et industrialiser | F7: Consolider le leadership | G7: Votre organisation soutient déjà la place que votre entreprise occupe. | H7: CC
A8: ≥ 60 | B8: < 60 | C8: Potentiel sous-exploité | D8: Le business est mieux structuré qu’il n’est perçu par son marché. | E8: Connecter les données aux parcours de croissance | F8: Accroître visibilité, preuve et acquisition | G8: Vos fondations sont plus solides que votre rayonnement actuel. | H8: PS
A9: < 60 | B9: ≥ 60 | C9: Rayonnement sous tension | D9: La visibilité dépasse la capacité interne à tracer, suivre et absorber l’activité. | E9: Sécuriser encaissements, trésorerie et contrôle | F9: Éviter d’accélérer sans structurer | G9: Votre rayonnement avance plus vite que vos systèmes de pilotage. | H9: RT
A10: < 60 | B10: < 60 | C10: Fondations à renforcer | D10: Les fragilités internes se reflètent dans un rayonnement encore limité. | E10: Structurer les fondamentaux prioritaires | F10: Clarifier l’offre et installer une présence régulière | G10: Le renforcement du pilotage peut devenir le premier levier de rayonnement. | H10: FR
A12: Lecture complémentaire de l’écart
A13: Écart = Rayonnement − Pilotage | B13: Qualificatif | C13: Lecture | D13: Action
A14: De −15 à +15 | B14: Cohérence relative | C14: Les deux scores racontent une situation globalement cohérente. | D14: Travailler le levier le plus faible sans remettre en cause l’ensemble.
A15: ≤ −16 | B15: Fondations sous-exploitées | C15: Le pilotage est plus avancé que la perception du marché. | D15: Transformer l’organisation interne en preuves, visibilité et acquisition.
A16: ≥ +16 | B16: Rayonnement exposé | C16: Le marché perçoit davantage que ce que les systèmes internes semblent pouvoir soutenir. | D16: Sécuriser la traçabilité, la trésorerie et la délégation avant l’accélération.
A18: Règles du score de Rayonnement
A19: Dimension | B19: Calcul | C19: Poids global | D19: Source
A20: Notoriété | B20: R1 / 3 × 100 | C20: 0.2 | D20: Question 1
A21: Lecture concurrentielle | B21: R2 / 3 × 100 | C21: 0.15 | D21: Question 2
A22: Différenciation | B22: R4 / 3 × 100 | C22: 0.25 | D22: Question 4 ; la question 3 fournit uniquement le tag
A23: Digital | B23: (R5 / 3 × 100 × 60 %) + (R6 / 3 × 100 × 40 %) | C23: 0.2 | D23: Questions 5 et 6
A24: Empreinte | B24: R7 / 3 × 100 | C24: 0.2 | D24: Question 7
A26: Niveaux et météo
A27: Score | B27: Niveau | C27: Météo | D27: Lecture synthétique
A28: 80–100 | B28: Dominant | C28: Soleil | D28: La marque rayonne et doit défendre puis renouveler son leadership.
A29: 60–79 | B29: Challenger fort | C29: Éclaircies | D29: La marque devient difficile à ignorer, mais doit consolider certains leviers.
A30: 40–59 | B30: Acteur silencieux | C30: Nuageux | D30: La valeur existe, mais le marché ne la perçoit pas encore à sa juste mesure.
A31: 20–39 | B31: Marque fragile | C31: Pluie | D31: La présence et la différence restent insuffisamment installées.
A32: 0–19 | B32: Zone de disparition | C32: Tempête | D32: L’empreinte est très faible et plusieurs fondamentaux doivent être retravaillés.
A34: Nuance météo | B34: « avec potentiel d’éclaircie » si le score est à 5 points ou moins du niveau supérieur, si au moins deux dimensions atteignent déjà ce seuil et si aucune dimension n’est sous 20.
A35: Bornes | B35: Les bornes sont inclusives ; 60 appartient à Challenger fort et 59 à Acteur silencieux.
A36: Arrondi | B36: Le moteur stocke le score non arrondi ; l’interface affiche l’entier arrondi.

Sheet Contrôles
A1: Contrôles d’équilibrage et cas de recette
A3: Équilibrage de la matrice dirigeant
A4: Dimension | B4: Code | C4: Occurrences +2 | D4: Occurrences +1 | E4: Maximum atteignable | F4: Contrôle
A5: Vision | B5: VIS | C5: =COUNTIF('Dirigeant - Matrice'!$E$5:$E$60,B5) | D5: =COUNTIF('Dirigeant - Matrice'!$G$5:$G$60,B5) | E5: 12 | F5: =IF(AND(C5=7,D5=7),"OK","À vérifier")
A6: Stratégie | B6: STR | C6: =COUNTIF('Dirigeant - Matrice'!$E$5:$E$60,B6) | D6: =COUNTIF('Dirigeant - Matrice'!$G$5:$G$60,B6) | E6: 15 | F6: =IF(AND(C6=7,D6=7),"OK","À vérifier")
A7: Exécution | B7: EXE | C7: =COUNTIF('Dirigeant - Matrice'!$E$5:$E$60,B7) | D7: =COUNTIF('Dirigeant - Matrice'!$G$5:$G$60,B7) | E7: 17 | F7: =IF(AND(C7=7,D7=7),"OK","À vérifier")
A8: Organisation | B8: ORG | C8: =COUNTIF('Dirigeant - Matrice'!$E$5:$E$60,B8) | D8: =COUNTIF('Dirigeant - Matrice'!$G$5:$G$60,B8) | E8: 18 | F8: =IF(AND(C8=7,D8=7),"OK","À vérifier")
A9: Influence | B9: INF | C9: =COUNTIF('Dirigeant - Matrice'!$E$5:$E$60,B9) | D9: =COUNTIF('Dirigeant - Matrice'!$G$5:$G$60,B9) | E9: 17 | F9: =IF(AND(C9=7,D9=7),"OK","À vérifier")
A10: Audace | B10: AUD | C10: =COUNTIF('Dirigeant - Matrice'!$E$5:$E$60,B10) | D10: =COUNTIF('Dirigeant - Matrice'!$G$5:$G$60,B10) | E10: 15 | F10: =IF(AND(C10=7,D10=7),"OK","À vérifier")
A11: Adaptabilité | B11: ADA | C11: =COUNTIF('Dirigeant - Matrice'!$E$5:$E$60,B11) | D11: =COUNTIF('Dirigeant - Matrice'!$G$5:$G$60,B11) | E11: 16 | F11: =IF(AND(C11=7,D11=7),"OK","À vérifier")
A12: Transformation | B12: TRA | C12: =COUNTIF('Dirigeant - Matrice'!$E$5:$E$60,B12) | D12: =COUNTIF('Dirigeant - Matrice'!$G$5:$G$60,B12) | E12: 17 | F12: =IF(AND(C12=7,D12=7),"OK","À vérifier")
A14: Accessibilité des 8 archétypes — exemples trouvés par test de simulation
A15: Archétype | B15: Séquence Q1→Q14 | C15: Affinité | D15: Marge sur le 2e | E15: Utilisation
A16: Stratège | B16: BCBADBADDBCADA | C16: 61.67 | D16: 26.7 | E16: Cas par défaut du simulateur
A17: Visionnaire | B17: ADCBCCAAADADAD | C17: 63.48 | D17: 23.5 | E17: Contrôle d’accessibilité
A18: Bâtisseur | B18: CADBCCBCBADCBB | C18: 58.78 | D18: 15.73 | E18: Contrôle d’accessibilité
A19: Conquérant | B19: DDADCCDBDCDABC | C19: 70.15 | D19: 25.36 | E19: Contrôle d’accessibilité
A20: Fédérateur | B20: CCCCCDADBBCBCA | C20: 71.41 | D20: 27.1 | E20: Contrôle d’accessibilité
A21: Résilient | B21: BADCDDCCCBCCBD | C21: 65.44 | D21: 21.15 | E21: Contrôle d’accessibilité
A22: Gestionnaire | B22: DABBABBBADADDC | C22: 61.38 | D22: 11.45 | E22: Contrôle d’accessibilité
A23: Réformateur | B23: DBDADACADABADA | C23: 67.51 | D23: 26.68 | E23: Contrôle d’accessibilité
A25: Cas limites de la double lecture
A26: Cas | B26: Choix Dirigeant | C26: Choix Rayonnement | D26: Pilotage attendu | E26: Rayonnement attendu | F26: Lecture croisée attendue
A27: Toutes les premières options | B27: AAAAAAAAAAAAAA | C27: AAAAAAA | D27: 100 | E27: 0 | F27: Potentiel sous-exploité
A28: Toutes les deuxièmes options | B28: BBBBBBBBBBBBBB | C28: BBBBBBB | D28: 66.67 | E28: 33.33 | F28: Potentiel sous-exploité
A29: Toutes les troisièmes options | B29: CCCCCCCCCCCCCC | C29: CCCCCCC | D29: 33.33 | E29: 66.67 | F29: Rayonnement sous tension
A30: Toutes les dernières options | B30: DDDDDDDDDDDDDD | C30: DDDDDDD | D30: 0 | E30: 100 | F30: Rayonnement sous tension
A32: Note méthodologique | B32: Le test aléatoire de 500 000 combinaisons a fait apparaître les 8 archétypes comme profils principaux. Il s’agit d’un contrôle d’accessibilité, pas d’une estimation de leur fréquence réelle.
A33: Avertissement | B33: Le diagnostic est un outil de qualification et de restitution ludique. Il ne doit pas être présenté comme un test psychométrique.
A34: Versionnement | B34: Toute modification d’une option, d’un poids ou d’un seuil doit créer une nouvelle version du moteur.
